Workbook

Sheet SCHEDULE OF VALUE WORKSHEET
A1: GENESIS CAPITAL
A3: CLIENT: | B3: Angeleno Investments
A4: DATE: | B4: 11.12.2025
A5: PROJECT: | B5: 10910 Huston Street
B6: DESCRIPTION OF WORK | C6: REHAB BUDGET | D6: PRE-FUNDING COSTS | E6: SCHEDULED VALUES | G6: Full Budget | J6: Spent To Date
A7: 1 | B7: SOFT COSTS | G7: OLD | H7: Delta | J7: OLD | K7: Delta
A8: 2 | B8: Site Security | C8: 20000 | D8: 9419.37 | E8: =SUM(C8-D8) -> 10580.63 | G8: 20000 | H8: =C8-G8 -> 0 | J8: 8669.37 | K8: =D8-J8 -> 750
A9: 3 | B9: Soils Inspection | C9: 4800 | D9: 4800 | E9: =SUM(C9-D9) -> 0 | G9: 4800 | H9: =C9-G9 -> 0 | J9: 4800 | K9: =D9-J9 -> 0
A10: =A9+1 -> 4 | B10: Offsites (Transformer) | C10: 20000 | D10: 0 | E10: =SUM(C10-D10) -> 20000 | G10: 20000 | H10: =C10-G10 -> 0 | J10: 0 | K10: =D10-J10 -> 0
A11: =A10+1 -> 5 | B11: Plan Check Fees | C11: 15000 | D11: 15000 | E11: =SUM(C11-D11) -> 0 | G11: 15000 | H11: =C11-G11 -> 0 | J11: 12665.22 | K11: =D11-J11 -> 2334.78
A12: =A11+1 -> 6 | B12: Permits | C12: =121785.82+61767.91 -> 183553.73 | D12: 183553.73 | E12: =SUM(C12-D12) -> 0 | G12: 121785.82 | H12: =C12-G12 -> 61767.91 | J12: 73183.5 | K12: =D12-J12 -> 110370.23
A13: =A12+1 -> 7 | B13: Survey | C13: 3805.23 | D13: 3805.23 | E13: =SUM(C13-D13) -> 0 | G13: 3805.23 | H13: =C13-G13 -> 0 | J13: 0 | K13: =D13-J13 -> 3805.23
A14: =A13+1 -> 8 | B14: Soils Engineer | C14: 6800 | D14: 6800 | E14: =SUM(C14-D14) -> 0 | G14: 6800 | H14: =C14-G14 -> 0 | J14: 3400 | K14: =D14-J14 -> 3400
A15: =A14+1 -> 9 | B15: Soils Permit + T24 | C15: 2500 | D15: 0 | E15: =SUM(C15-D15) -> 2500 | G15: 2500 | H15: =C15-G15 -> 0 | J15: 0 | K15: =D15-J15 -> 0
A16: =A15+1 -> 10 | B16: Special Inspections - Deputy | C16: 15000 | D16: 0 | E16: =SUM(C16-D16) -> 15000 | G16: 15000 | H16: =C16-G16 -> 0 | J16: 0 | K16: =D16-J16 -> 0
A17: =A16+1 -> 11 | B17: Architect | C17: 122917 | D17: 122917 | E17: =SUM(C17-D17) -> 0 | G17: 113100 | H17: =C17-G17 -> 9817 | J17: 109989.75 | K17: =D17-J17 -> 12927.25
A18: =A17+1 -> 12 | B18: Structural Engineer | C18: 36600 | D18: 36600 | E18: =SUM(C18-D18) -> 0 | G18: 31600 | H18: =C18-G18 -> 5000 | J18: 31600 | K18: =D18-J18 -> 5000
A19: =A18+1 -> 13 | B19: Structural Observation | C19: 8000 | D19: 0 | E19: =SUM(C19-D19) -> 8000 | G19: 8000 | H19: =C19-G19 -> 0 | J19: 0 | K19: =D19-J19 -> 0
A20: =A19+1 -> 14 | B20: Civil Engineering | C20: 20000 | D20: 20000 | E20: =SUM(C20-D20) -> 0 | G20: 20000 | H20: =C20-G20 -> 0 | J20: 18000 | K20: =D20-J20 -> 2000
A21: =A20+1 -> 15 | B21: Grading Permit | C21: 2313.4 | D21: 2313.4 | E21: =SUM(C21-D21) -> 0 | G21: 2313.4 | H21: =C21-G21 -> 0 | J21: 2313.4 | K21: =D21-J21 -> 0
A22: =A21+1 -> 16 | B22: Landscape Architect/Designer | C22: 4200 | D22: 4200 | E22: =SUM(C22-D22) -> 0 | G22: 4200 | H22: =C22-G22 -> 0 | J22: 2700 | K22: =D22-J22 -> 1500
A23: =A22+1 -> 17 | B23: Driveway Apron Permit | C23: 2500 | D23: 0 | E23: =SUM(C23-D23) -> 2500 | G23: 2500 | H23: =C23-G23 -> 0 | J23: 0 | K23: =D23-J23 -> 0
A24: =A23+1 -> 18 | B24: Punch List - Misc. | C24: 21962.77 | D24: 0 | E24: =SUM(C24-D24) -> 21962.77 | G24: 21983 | H24: =C24-G24 -> -20.23 | J24: 0 | K24: =D24-J24 -> 0
... A42: =A41+1 -> 36 | B42: Construction Management / Observation (OO) | C42: 55000 | D42: 5572.1 | E42: =SUM(C42-D42) -> 49427.9 | G42: 55000 | H42: =C42-G42 -> 0 | J42: 0 | K42: =D42-J42 -> 5572.1
A43: 37 | B43: CMFA Startup Fee | C43: 22800 | D43: 0 | E43: =SUM(C43-D43) -> 22800 | G43: 22800 | H43: =C43-G43 -> 0 | J43: 0 | K43: =D43-J43 -> 0
A44: 38 | B44: Non-Profit Start Up Fee | C44: 25000 | D44: 0 | E44: =SUM(C44-D44) -> 25000 | G44: 25000 | H44: =C44-G44 -> 0 | J44: 0 | K44: =D44-J44 -> 0
A45: =A44+1 -> 39 | B45: CMFA Construction Fee | C45: 12000 | D45: 0 | E45: =SUM(C45-D45) -> 12000 | G45: 12000 | H45: =C45-G45 -> 0 | J45: 0 | K45: =D45-J45 -> 0
A46: =A45+1 -> 40 | B46: Non-Profit Construction Fee | C46: 10000 | D46: 0 | E46: =SUM(C46-D46) -> 10000 | G46: 10000 | H46: =C46-G46 -> 0 | J46: 0 | K46: =D46-J46 -> 0
A47: =A46+1 -> 41 | B47: WTE Legal Costs for CMFA & Non-Profit Partner | C47: 20000 | D47: 0 | E47: =SUM(C47-D47) -> 20000 | F47: =SUM(C8:C47) -> 857521.21 | G47: 20000 | H47: =C47-G47 -> 0 | J47: 0 | K47: =D47-J47 -> 0
A48: 42 | B48: HARD COSTS | E48: =SUM(C48-D48) -> 0
A49: 43 | B49: GENERAL CONDITIONS | C49: 565545 | D49: 203429.76 | E49: =SUM(C49-D49) -> 362115.24 | G49: 565545 | H49: =C49-G49 -> 0 | J49: 197892.71 | K49: =D49-J49 -> 5537.05
A50: =A49+1 -> 44 | B50: GENERAL REQUIREMENT | C50: 135922 | D50: 11264.12 | E50: =SUM(C50-D50) -> 124657.88 | G50: 135922 | H50: =C50-G50 -> 0 | J50: 11264.12 | K50: =D50-J50 -> 0
A51: =A50+1 -> 45 | B51: SITE WORK | C51: 139049.51 | D51: 0 | E51: =SUM(C51-D51) -> 139049.51 | G51: 139049.51 | H51: =C51-G51 -> 0 | J51: 0 | K51: =D51-J51 -> 0
A52: =A51+1 -> 46 | B52: CONCRETE | C52: 253182 | D52: 0 | E52: =SUM(C52-D52) -> 253182 | G52: 253182 | H52: =C52-G52 -> 0 | J52: 0 | K52: =D52-J52 -> 0
A53: =A52+1 -> 47 | B53: MASONRY | C53: 3562.64 | D53: 0 | E53: =SUM(C53-D53) -> 3562.64 | G53: 3562.64 | H53: =C53-G53 -> 0 | J53: 0 | K53: =D53-J53 -> 0
A54: =A53+1 -> 48 | B54: METALS | C54: 324100 | D54: 0 | E54: =SUM(C54-D54) -> 324100 | G54: 324100 | H54: =C54-G54 -> 0 | J54: 0 | K54: =D54-J54 -> 0
A55: =A54+1 -> 49 | B55: FRAMING | C55: 818554 | D55: 0 | E55: =SUM(C55-D55) -> 818554 | G55: 818554 | H55: =C55-G55 -> 0 | J55: 0 | K55: =D55-J55 -> 0
A56: =A55+1 -> 50 | B56: COUNTERTOPS | C56: 56930 | D56: 0 | E56: =SUM(C56-D56) -> 56930 | G56: 56930 | H56: =C56-G56 -> 0 | J56: 0 | K56: =D56-J56 -> 0
A57: =A56+1 -> 51 | B57: CABINETS | C57: 56930 | D57: 0 | E57: =SUM(C57-D57) -> 56930 | G57: 56930 | H57: =C57-G57 -> 0 | J57: 0 | K57: =D57-J57 -> 0
A58: =A57+1 -> 52 | B58: THERMAL MOISTURE PROTECTION | C58: 173148 | D58: 0 | E58: =SUM(C58-D58) -> 173148 | G58: 173148 | H58: =C58-G58 -> 0 | J58: 0 | K58: =D58-J58 -> 0
A59: =A58+1 -> 53 | B59: DOORS | C59: 204087.33 | D59: 0 | E59: =SUM(C59-D59) -> 204087.33 | G59: 204087.33 | H59: =C59-G59 -> 0 | J59: 0 | K59: =D59-J59 -> 0
A60: =A59+1 -> 54 | B60: WINDOWS | C60: 106274.25 | D60: 0 | E60: =SUM(C60-D60) -> 106274.25 | G60: 106274.25 | H60: =C60-G60 -> 0 | J60: 0 | K60: =D60-J60 -> 0
A61: =A60+1 -> 55 | B61: STUCCO | C61: 208002 | D61: 0 | E61: =SUM(C61-D61) -> 208002 | G61: 208002 | H61: =C61-G61 -> 0 | J61: 0 | K61: =D61-J61 -> 0
... A67: =A66+1 -> 61 | B67: EQUIPMENT | C67: 153636 | D67: 0 | E67: =SUM(C67-D67) -> 153636 | G67: 153636 | H67: =C67-G67 -> 0 | J67: 0 | K67: =D67-J67 -> 0
A68: =A67+1 -> 62 | B68: FURNISHING | D68: 0 | E68: =SUM(C68-D68) -> 0
A69: =A68+1 -> 63 | B69: FIRE SPRINKLERS | C69: 108500 | D69: 0 | E69: =SUM(C69-D69) -> 108500 | G69: 108500 | H69: =C69-G69 -> 0 | J69: 0 | K69: =D69-J69 -> 0
A70: =A69+1 -> 64 | B70: FIRE ALARM | C70: 68401 | D70: 0 | E70: =SUM(C70-D70) -> 68401 | G70: 68401 | H70: =C70-G70 -> 0 | J70: 0 | K70: =D70-J70 -> 0
A71: =A70+1 -> 65 | B71: SOLAR PANELS | C71: 97000 | D71: 0 | E71: =SUM(C71-D71) -> 97000 | G71: 97000 | H71: =C71-G71 -> 0 | J71: 0 | K71: =D71-J71 -> 0
A72: =A71+1 -> 66 | B72: SECURITY ACCESS & SURVEILLANCE | C72: 136430 | D72: 0 | E72: =SUM(C72-D72) -> 136430 | G72: 136430 | H72: =C72-G72 -> 0 | J72: 0 | K72: =D72-J72 -> 0
A73: =A72+1 -> 67 | B73: ELEVATORS & LIFT | C73: 174882 | D73: 0 | E73: =SUM(C73-D73) -> 174882 | G73: 174882 | H73: =C73-G73 -> 0 | J73: 0 | K73: =D73-J73 -> 0
A74: =A73+1 -> 68 | B74: WATER SUBMETER (material) | C74: 12273 | E74: =SUM(C74-D74) -> 12273 | G74: 12273 | H74: =C74-G74 -> 0
A75: =A74+1 -> 69 | B75: WATER SUBMETER (labor) | C75: 0 | D75: 0 | E75: =SUM(C75-D75) -> 0
A76: =A75+1 -> 70 | B76: ROUGH PLUMBING | C76: 751927 | D76: 0 | E76: =SUM(C76-D76) -> 751927 | G76: 751927 | H76: =C76-G76 -> 0 | J76: 0 | K76: =D76-J76 -> 0
A77: =A76+1 -> 71 | B77: FINISH PLUMBING | C77: 90000 | D77: 0 | E77: =SUM(C77-D77) -> 90000 | G77: 90000 | H77: =C77-G77 -> 0 | J77: 0 | K77: =D77-J77 -> 0
A78: =A77+1 -> 72 | B78: HVAC | C78: 259000 | D78: 0 | E78: =SUM(C78-D78) -> 259000 | G78: 259000 | H78: =C78-G78 -> 0 | J78: 0 | K78: =D78-J78 -> 0
A79: =A78+1 -> 73 | B79: ELECTRICAL | C79: 880486.32 | D79: 0 | E79: =SUM(C79-D79) -> 880486.32 | F79: =SUM(C49:C79) -> 6478471.3 | G79: 880486.32 | H79: =C79-G79 -> 0 | J79: 0 | K79: =D79-J79 -> 0
A80: =A79+1 -> 74 | B80: CONTINGENCY | C80: 546491.43 | D80: 17276.23 | E80: =SUM(C80-D80) -> 529215.2 | G80: 537822.68 | H80: =C80-G80 -> 8668.75 | J80: 17276.23 | K80: =D80-J80 -> 0
A81: =A80+1 -> 75 | B81: INSURANCE (GL w/auto, workers compl) | C81: 97177.07 | D81: 0 | E81: =SUM(C81-D81) -> 97177.07 | G81: 97177.07 | H81: =C81-G81 -> 0 | J81: 0 | K81: =D81-J81 -> 0
A82: =A81+1 -> 76 | B82: GROSS RECEIPT TAX | C82: 6543.26 | D82: 0 | E82: =SUM(C82-D82) -> 6543.26 | G82: 6543.26 | H82: =C82-G82 -> 0 | J82: 0 | K82: =D82-J82 -> 0
A83: =A82+1 -> 77 | B83: GC FEE | C83: 388708.28 | D83: 0 | E83: =SUM(C83-D83) -> 388708.28 | G83: 388708.28 | H83: =C83-G83 -> 0 | J83: 0 | K83: =D83-J83 -> 0
A84: =A83+1 -> 78 | B84: DEVELOPMENT FEE | C84: 340285 | D84: 159761.5 | E84: =SUM(C84-D84) -> 180523.5 | G84: 335434 | H84: =C84-G84 -> 4851 | J84: 134536 | K84: =D84-J84 -> 25225.5
A85: =A84+1 -> 79 | B85: CARRYING COSTS | C85: 122215 | D85: 29329.47 | E85: =SUM(C85-D85) -> 92885.53 | G85: 122215 | H85: =C85-G85 -> 0 | J85: 26862.19 | K85: =D85-J85 -> 2467.28
A86: =A85+1 -> 80 | B86: FINANCING COSTS | C86: 0 | E86: =SUM(C86-D86) -> 0
A87: 82 | B87: Open Item | C87: 0 | D87: 0 | E87: =SUM(C87-D87) -> 0
A88: =A87+1 -> 83 | B88: Open Item | C88: 0 | D88: 0 | E88: =SUM(C88-D88) -> 0
A89: =A88+1 -> 84 | B89: Open Item | C89: 0 | D89: 0 | E89: =SUM(C89-D89) -> 0
A90: =A89+1 -> 85 | B90: Open Item | C90: 0 | D90: 0 | E90: =SUM(C90-D90) -> 0
A91: =A90+1 -> 86 | B91: Open Item | C91: 0 | D91: 0 | E91: =SUM(C91-D91) -> 0
A92: =A91+1 -> 87 | B92: Open Item | C92: 0 | D92: 0 | E92: =SUM(C92-D92) -> 0
A93: =A92+1 -> 88 | B93: Open Item | C93: 0 | D93: 0 | E93: =SUM(C93-D93) -> 0
A94: =A93+1 -> 89 | B94: Open Item | C94: 0 | D94: 0 | E94: =SUM(C94-D94) -> 0
A95: =A94+1 -> 90 | B95: Open Item | C95: 0 | D95: 0 | E95: =SUM(C95-D95) -> 0
A96: =A95+1 -> 91 | B96: Open Item | C96: 0 | D96: 0 | E96: =SUM(C96-D96) -> 0
A97: =A96+1 -> 92 | B97: Open Item | C97: 0 | D97: 0 | E97: =SUM(C97-D97) -> 0
A98: =A97+1 -> 93 | B98: Open Item | C98: 0 | D98: 0 | E98: =SUM(C98-D98) -> 0
A99: =A98+1 -> 94 | B99: Open Item | C99: 0 | D99: 0 | E99: =SUM(C99-D99) -> 0
... A104: =A103+1 -> 99 | B104: Open Item | C104: 0 | D104: 0 | E104: =SUM(C104-D104) -> 0
B106: TOTAL | C106: =SUM(C7:C104) -> 8837412.5 | D106: =SUM(D7:D104) -> 1011919.6 | E106: =SUM(E7:E104) -> 7825492.9
B108: CONTINGENCY NOTE: Hard cost $323,923.56 + Soft cost $38,386.06 + Schedule $184181.97 = $546,491.43 / Cost spent $2,444.53 + $14,831 = $17,276.23

Sheet Draw #1
A1: GENESIS CAPITAL DRAW REQUEST FORM
B3: CLIENT: | C3: ='SCHEDULE OF VALUE WORKSHEET'!$B$3 -> Angeleno Investments | H3: TOTAL COMPLETED TO DATE: | I3: =SUM(I137) -> 0 | J3: =IF(I3=0,"",I3/I7)
B4: PROJECT: | C4: ='SCHEDULE OF VALUE WORKSHEET'!B5 -> 10910 Huston Street | H4: REMAINING $ IN BUDGET: | I4: =SUM(G137) -> #REF!
B5: DATE: | C5: =TODAY() -> 45978 | H5: ORIGINAL SCHEDULE OF VALUES: | I5: =SUM(D137) -> #REF!
B6: DRAW REQUEST: | C6: =SUM(H137) -> 0 | H6: CHANGE ORDERS: | I6: =SUM(E137) -> 0
H7: REVISED SCHEDULE OF VALUES: | I7: =SUM(F137) -> #REF!
B9: DESCRIPTION OF WORK | D9: SCHEDULED VALUES | E9: + / - CHANGES | F9: REVISED VALUES | G9: REMAINING | H9: DRAW | I9: COMPLETED AND
G10: $ PER BUDGET | H10: 1 | I10: STORED TO DATE
A11: ='SCHEDULE OF VALUE WORKSHEET'!A7 -> 1 | B11: ='SCHEDULE OF VALUE WORKSHEET'!B7 -> SOFT COSTS | D11: =SUM('SCHEDULE OF VALUE WORKSHEET'!E7) -> 0 | E11: 0 | F11: =SUM(D11)+E11 -> 0 | G11: =SUM(F11-I11) -> 0 | H11: 0 | I11: =SUM(H11) -> 0 | J11: =IF(I11=0,"",I11/F11)
A12: ='SCHEDULE OF VALUE WORKSHEET'!A8 -> 2 | B12: ='SCHEDULE OF VALUE WORKSHEET'!B8 -> Site Security | D12: =SUM('SCHEDULE OF VALUE WORKSHEET'!E8) -> 10580.63 | E12: 0 | F12: =SUM(D12)+E12 -> 10580.63 | G12: =SUM(F12-I12) -> 10580.63 | H12: 0 | I12: =SUM(H12) -> 0 | J12: =IF(I12=0,"",I12/F12)
A13: ='SCHEDULE OF VALUE WORKSHEET'!A9 -> 3 | B13: ='SCHEDULE OF VALUE WORKSHEET'!B9 -> Soils Inspection | D13: =SUM('SCHEDULE OF VALUE WORKSHEET'!E9) -> 0 | E13: 0 | F13: =SUM(D13)+E13 -> 0 | G13: =SUM(F13-I13) -> 0 | H13: 0 | I13: =SUM(H13) -> 0 | J13: =IF(I13=0,"",I13/F13)
A14: ='SCHEDULE OF VALUE WORKSHEET'!A10 -> 4 | B14: ='SCHEDULE OF VALUE WORKSHEET'!B10 -> Offsites (Transformer) | D14: =SUM('SCHEDULE OF VALUE WORKSHEET'!E10) -> 20000 | E14: 0 | F14: =SUM(D14)+E14 -> 20000 | G14: =SUM(F14-I14) -> 20000 | H14: 0 | I14: =SUM(H14) -> 0 | J14: =IF(I14=0,"",I14/F14)
A15: ='SCHEDULE OF VALUE WORKSHEET'!A11 -> 5 | B15: ='SCHEDULE OF VALUE WORKSHEET'!B11 -> Plan Check Fees | D15: =SUM('SCHEDULE OF VALUE WORKSHEET'!E11) -> 0 | E15: 0 | F15: =SUM(D15)+E15 -> 0 | G15: =SUM(F15-I15) -> 0 | H15: 0 | I15: =SUM(H15) -> 0 | J15: =IF(I15=0,"",I15/F15)
A16: ='SCHEDULE OF VALUE WORKSHEET'!A12 -> 6 | B16: ='SCHEDULE OF VALUE WORKSHEET'!B12 -> Permits | D16: =SUM('SCHEDULE OF VALUE WORKSHEET'!E12) -> 0 | E16: 0 | F16: =SUM(D16)+E16 -> 0 | G16: =SUM(F16-I16) -> 0 | H16: 0 | I16: =SUM(H16) -> 0 | J16: =IF(I16=0,"",I16/F16)
A17: ='SCHEDULE OF VALUE WORKSHEET'!A13 -> 7 | B17: ='SCHEDULE OF VALUE WORKSHEET'!B13 -> Survey | D17: =SUM('SCHEDULE OF VALUE WORKSHEET'!E13) -> 0 | E17: 0 | F17: =SUM(D17)+E17 -> 0 | G17: =SUM(F17-I17) -> 0 | H17: 0 | I17: =SUM(H17) -> 0 | J17: =IF(I17=0,"",I17/F17)
A18: ='SCHEDULE OF VALUE WORKSHEET'!A14 -> 8 | B18: ='SCHEDULE OF VALUE WORKSHEET'!B14 -> Soils Engineer | D18: =SUM('SCHEDULE OF VALUE WORKSHEET'!E14) -> 0 | E18: 0 | F18: =SUM(D18)+E18 -> 0 | G18: =SUM(F18-I18) -> 0 | H18: 0 | I18: =SUM(H18) -> 0 | J18: =IF(I18=0,"",I18/F18)
A19: ='SCHEDULE OF VALUE WORKSHEET'!A15 -> 9 | B19: ='SCHEDULE OF VALUE WORKSHEET'!B15 -> Soils Permit + T24 | D19: =SUM('SCHEDULE OF VALUE WORKSHEET'!E15) -> 2500 | E19: 0 | F19: =SUM(D19)+E19 -> 2500 | G19: =SUM(F19-I19) -> 2500 | H19: 0 | I19: =SUM(H19) -> 0 | J19: =IF(I19=0,"",I19/F19)
A20: ='SCHEDULE OF VALUE WORKSHEET'!A16 -> 10 | B20: ='SCHEDULE OF VALUE WORKSHEET'!B16 -> Special Inspections - Deputy | D20: =SUM('SCHEDULE OF VALUE WORKSHEET'!E16) -> 15000 | E20: 0 | F20: =SUM(D20)+E20 -> 15000 | G20: =SUM(F20-I20) -> 15000 | H20: 0 | I20: =SUM(H20) -> 0 | J20: =IF(I20=0,"",I20/F20)
A21: ='SCHEDULE OF VALUE WORKSHEET'!A17 -> 11 | B21: ='SCHEDULE OF VALUE WORKSHEET'!B17 -> Architect | D21: =SUM('SCHEDULE OF VALUE WORKSHEET'!E17) -> 0 | E21: 0 | F21: =SUM(D21)+E21 -> 0 | G21: =SUM(F21-I21) -> 0 | H21: 0 | I21: =SUM(H21) -> 0 | J21: =IF(I21=0,"",I21/F21)
A22: ='SCHEDULE OF VALUE WORKSHEET'!A18 -> 12 | B22: ='SCHEDULE OF VALUE WORKSHEET'!B18 -> Structural Engineer | D22: =SUM('SCHEDULE OF VALUE WORKSHEET'!E18) -> 0 | E22: 0 | F22: =SUM(D22)+E22 -> 0 | G22: =SUM(F22-I22) -> 0 | H22: 0 | I22: =SUM(H22) -> 0 | J22: =IF(I22=0,"",I22/F22)
... A46: ='SCHEDULE OF VALUE WORKSHEET'!A42 -> 36 | B46: ='SCHEDULE OF VALUE WORKSHEET'!B42 -> Construction Management / Observation (OO) | D46: =SUM('SCHEDULE OF VALUE WORKSHEET'!E42) -> 49427.9 | E46: 0 | F46: =SUM(D46)+E46 -> 49427.9 | G46: =SUM(F46-I46) -> 49427.9 | H46: 0 | I46: =SUM(H46) -> 0 | J46: =IF(I46=0,"",I46/F46)
A47: ='SCHEDULE OF VALUE WORKSHEET'!#REF! -> #REF! | B47: ='SCHEDULE OF VALUE WORKSHEET'!#REF! -> #REF! | D47: =SUM('SCHEDULE OF VALUE WORKSHEET'!#REF!) -> #REF! | E47: 0 | F47: =SUM(D47)+E47 -> #REF! | G47: =SUM(F47-I47) -> #REF! | H47: 0 | I47: =SUM(H47) -> 0 | J47: =IF(I47=0,"",I47/F47)
A48: ='SCHEDULE OF VALUE WORKSHEET'!A43 -> 37 | B48: ='SCHEDULE OF VALUE WORKSHEET'!B43 -> CMFA Startup Fee | D48: =SUM('SCHEDULE OF VALUE WORKSHEET'!E43) -> 22800 | E48: 0 | F48: =SUM(D48)+E48 -> 22800 | G48: =SUM(F48-I48) -> 22800 | H48: 0 | I48: =SUM(H48) -> 0 | J48: =IF(I48=0,"",I48/F48)
A49: ='SCHEDULE OF VALUE WORKSHEET'!A44 -> 38 | B49: ='SCHEDULE OF VALUE WORKSHEET'!B44 -> Non-Profit Start Up Fee | D49: =SUM('SCHEDULE OF VALUE WORKSHEET'!E44) -> 25000 | E49: 0 | F49: =SUM(D49)+E49 -> 25000 | G49: =SUM(F49-I49) -> 25000 | H49: 0 | I49: =SUM(H49) -> 0 | J49: =IF(I49=0,"",I49/F49)
A50: ='SCHEDULE OF VALUE WORKSHEET'!A45 -> 39 | B50: ='SCHEDULE OF VALUE WORKSHEET'!B45 -> CMFA Construction Fee | D50: =SUM('SCHEDULE OF VALUE WORKSHEET'!E45) -> 12000 | E50: 0 | F50: =SUM(D50)+E50 -> 12000 | G50: =SUM(F50-I50) -> 12000 | H50: 0 | I50: =SUM(H50) -> 0 | J50: =IF(I50=0,"",I50/F50)
A51: ='SCHEDULE OF VALUE WORKSHEET'!A46 -> 40 | B51: ='SCHEDULE OF VALUE WORKSHEET'!B46 -> Non-Profit Construction Fee | D51: =SUM('SCHEDULE OF VALUE WORKSHEET'!E46) -> 10000 | E51: 0 | F51: =SUM(D51)+E51 -> 10000 | G51: =SUM(F51-I51) -> 10000 | H51: 0 | I51: =SUM(H51) -> 0 | J51: =IF(I51=0,"",I51/F51)
A52: ='SCHEDULE OF VALUE WORKSHEET'!A47 -> 41 | B52: ='SCHEDULE OF VALUE WORKSHEET'!B47 -> WTE Legal Costs for CMFA & Non-Profit Partner | D52: =SUM('SCHEDULE OF VALUE WORKSHEET'!E47) -> 20000 | E52: 0 | F52: =SUM(D52)+E52 -> 20000 | G52: =SUM(F52-I52) -> 20000 | H52: 0 | I52: =SUM(H52) -> 0 | J52: =IF(I52=0,"",I52/F52)
A53: ='SCHEDULE OF VALUE WORKSHEET'!#REF! -> #REF! | B53: ='SCHEDULE OF VALUE WORKSHEET'!#REF! -> #REF! | D53: =SUM('SCHEDULE OF VALUE WORKSHEET'!#REF!) -> #REF! | E53: 0 | F53: =SUM(D53)+E53 -> #REF! | G53: =SUM(F53-I53) -> #REF! | H53: 0 | I53: =SUM(H53) -> 0 | J53: =IF(I53=0,"",I53/F53)
A54: ='SCHEDULE OF VALUE WORKSHEET'!A49 -> 43 | B54: ='SCHEDULE OF VALUE WORKSHEET'!B49 -> GENERAL CONDITIONS | D54: =SUM('SCHEDULE OF VALUE WORKSHEET'!E49) -> 362115.24 | E54: 0 | F54: =SUM(D54)+E54 -> 362115.24 | G54: =SUM(F54-I54) -> 362115.24 | H54: 0 | I54: =SUM(H54) -> 0 | J54: =IF(I54=0,"",I54/F54)
A55: ='SCHEDULE OF VALUE WORKSHEET'!A50 -> 44 | B55: ='SCHEDULE OF VALUE WORKSHEET'!B50 -> GENERAL REQUIREMENT | D55: =SUM('SCHEDULE OF VALUE WORKSHEET'!E50) -> 124657.88 | E55: 0 | F55: =SUM(D55)+E55 -> 124657.88 | G55: =SUM(F55-I55) -> 124657.88 | H55: 0 | I55: =SUM(H55) -> 0 | J55: =IF(I55=0,"",I55/F55)
A56: ='SCHEDULE OF VALUE WORKSHEET'!A51 -> 45 | B56: ='SCHEDULE OF VALUE WORKSHEET'!B51 -> SITE WORK | D56: =SUM('SCHEDULE OF VALUE WORKSHEET'!E51) -> 139049.51 | E56: 0 | F56: =SUM(D56)+E56 -> 139049.51 | G56: =SUM(F56-I56) -> 139049.51 | H56: 0 | I56: =SUM(H56) -> 0 | J56: =IF(I56=0,"",I56/F56)
A57: ='SCHEDULE OF VALUE WORKSHEET'!A52 -> 46 | B57: ='SCHEDULE OF VALUE WORKSHEET'!B52 -> CONCRETE | D57: =SUM('SCHEDULE OF VALUE WORKSHEET'!E52) -> 253182 | E57: 0 | F57: =SUM(D57)+E57 -> 253182 | G57: =SUM(F57-I57) -> 253182 | H57: 0 | I57: =SUM(H57) -> 0 | J57: =IF(I57=0,"",I57/F57)
A58: ='SCHEDULE OF VALUE WORKSHEET'!A53 -> 47 | B58: ='SCHEDULE OF VALUE WORKSHEET'!B53 -> MASONRY | D58: =SUM('SCHEDULE OF VALUE WORKSHEET'!E53) -> 3562.64 | E58: 0 | F58: =SUM(D58)+E58 -> 3562.64 | G58: =SUM(F58-I58) -> 3562.64 | H58: 0 | I58: =SUM(H58) -> 0 | J58: =IF(I58=0,"",I58/F58)
A59: ='SCHEDULE OF VALUE WORKSHEET'!A54 -> 48 | B59: ='SCHEDULE OF VALUE WORKSHEET'!B54 -> METALS | D59: =SUM('SCHEDULE OF VALUE WORKSHEET'!E54) -> 324100 | E59: 0 | F59: =SUM(D59)+E59 -> 324100 | G59: =SUM(F59-I59) -> 324100 | H59: 0 | I59: =SUM(H59) -> 0 | J59: =IF(I59=0,"",I59/F59)
A60: ='SCHEDULE OF VALUE WORKSHEET'!A55 -> 49 | B60: ='SCHEDULE OF VALUE WORKSHEET'!B55 -> FRAMING | D60: =SUM('SCHEDULE OF VALUE WORKSHEET'!E55) -> 818554 | E60: 0 | F60: =SUM(D60)+E60 -> 818554 | G60: =SUM(F60-I60) -> 818554 | H60: 0 | I60: =SUM(H60) -> 0 | J60: =IF(I60=0,"",I60/F60)
A61: ='SCHEDULE OF VALUE WORKSHEET'!A56 -> 50 | B61: ='SCHEDULE OF VALUE WORKSHEET'!B56 -> COUNTERTOPS | D61: =SUM('SCHEDULE OF VALUE WORKSHEET'!E56) -> 56930 | E61: 0 | F61: =SUM(D61)+E61 -> 56930 | G61: =SUM(F61-I61) -> 56930 | H61: 0 | I61: =SUM(H61) -> 0 | J61: =IF(I61=0,"",I61/F61)
A62: ='SCHEDULE OF VALUE WORKSHEET'!A57 -> 51 | B62: ='SCHEDULE OF VALUE WORKSHEET'!B57 -> CABINETS | D62: =SUM('SCHEDULE OF VALUE WORKSHEET'!E57) -> 56930 | E62: 0 | F62: =SUM(D62)+E62 -> 56930 | G62: =SUM(F62-I62) -> 56930 | H62: 0 | I62: =SUM(H62) -> 0 | J62: =IF(I62=0,"",I62/F62)
A63: ='SCHEDULE OF VALUE WORKSHEET'!A58 -> 52 | B63: ='SCHEDULE OF VALUE WORKSHEET'!B58 -> THERMAL MOISTURE PROTECTION | D63: =SUM('SCHEDULE OF VALUE WORKSHEET'!E58) -> 173148 | E63: 0 | F63: =SUM(D63)+E63 -> 173148 | G63: =SUM(F63-I63) -> 173148 | H63: 0 | I63: =SUM(H63) -> 0 | J63: =IF(I63=0,"",I63/F63)
A64: ='SCHEDULE OF VALUE WORKSHEET'!A59 -> 53 | B64: ='SCHEDULE OF VALUE WORKSHEET'!B59 -> DOORS | D64: =SUM('SCHEDULE OF VALUE WORKSHEET'!E59) -> 204087.33 | E64: 0 | F64: =SUM(D64)+E64 -> 204087.33 | G64: =SUM(F64-I64) -> 204087.33 | H64: 0 | I64: =SUM(H64) -> 0 | J64: =IF(I64=0,"",I64/F64)
A65: ='SCHEDULE OF VALUE WORKSHEET'!A60 -> 54 | B65: ='SCHEDULE OF VALUE WORKSHEET'!B60 -> WINDOWS | D65: =SUM('SCHEDULE OF VALUE WORKSHEET'!E60) -> 106274.25 | E65: 0 | F65: =SUM(D65)+E65 -> 106274.25 | G65: =SUM(F65-I65) -> 106274.25 | H65: 0 | I65: =SUM(H65) -> 0 | J65: =IF(I65=0,"",I65/F65)
... A91: ='SCHEDULE OF VALUE WORKSHEET'!A86 -> 80 | B91: ='SCHEDULE OF VALUE WORKSHEET'!B86 -> FINANCING COSTS | D91: =SUM('SCHEDULE OF VALUE WORKSHEET'!E86) -> 0 | E91: 0 | F91: =SUM(D91)+E91 -> 0 | G91: =SUM(F91-I91) -> 0 | H91: 0 | I91: =SUM(H91) -> 0 | J91: =IF(I91=0,"",I91/F91)
A92: ='SCHEDULE OF VALUE WORKSHEET'!#REF! -> #REF! | B92: ='SCHEDULE OF VALUE WORKSHEET'!#REF! -> #REF! | D92: =SUM('SCHEDULE OF VALUE WORKSHEET'!#REF!) -> #REF! | E92: 0 | F92: =SUM(D92)+E92 -> #REF! | G92: =SUM(F92-I92) -> #REF! | H92: 0 | I92: =SUM(H92) -> 0 | J92: =IF(I92=0,"",I92/F92)
A93: ='SCHEDULE OF VALUE WORKSHEET'!#REF! -> #REF! | B93: ='SCHEDULE OF VALUE WORKSHEET'!#REF! -> #REF! | D93: =SUM('SCHEDULE OF VALUE WORKSHEET'!#REF!) -> #REF! | E93: 0 | F93: =SUM(D93)+E93 -> #REF! | G93: =SUM(F93-I93) -> #REF! | H93: 0 | I93: =SUM(H93) -> 0 | J93: =IF(I93=0,"",I93/F93)
A94: ='SCHEDULE OF VALUE WORKSHEET'!#REF! -> #REF! | B94: ='SCHEDULE OF VALUE WORKSHEET'!#REF! -> #REF! | D94: =SUM('SCHEDULE OF VALUE WORKSHEET'!#REF!) -> #REF! | E94: 0 | F94: =SUM(D94)+E94 -> #REF! | G94: =SUM(F94-I94) -> #REF! | H94: 0 | I94: =SUM(H94) -> 0 | J94: =IF(I94=0,"",I94/F94)
A95: ='SCHEDULE OF VALUE WORKSHEET'!#REF! -> #REF! | B95: ='SCHEDULE OF VALUE WORKSHEET'!#REF! -> #REF! | D95: =SUM('SCHEDULE OF VALUE WORKSHEET'!#REF!) -> #REF! | E95: 0 | F95: =SUM(D95)+E95 -> #REF! | G95: =SUM(F95-I95) -> #REF! | H95: 0 | I95: =SUM(H95) -> 0 | J95: =IF(I95=0,"",I95/F95)
A96: ='SCHEDULE OF VALUE WORKSHEET'!#REF! -> #REF! | B96: ='SCHEDULE OF VALUE WORKSHEET'!#REF! -> #REF! | D96: =SUM('SCHEDULE OF VALUE WORKSHEET'!#REF!) -> #REF! | E96: 0 | F96: =SUM(D96)+E96 -> #REF! | G96: =SUM(F96-I96) -> #REF! | H96: 0 | I96: =SUM(H96) -> 0 | J96: =IF(I96=0,"",I96/F96)
A97: ='SCHEDULE OF VALUE WORKSHEET'!#REF! -> #REF! | B97: ='SCHEDULE OF VALUE WORKSHEET'!#REF! -> #REF! | D97: =SUM('SCHEDULE OF VALUE WORKSHEET'!#REF!) -> #REF! | E97: 0 | F97: =SUM(D97)+E97 -> #REF! | G97: =SUM(F97-I97) -> #REF! | H97: 0 | I97: =SUM(H97) -> 0 | J97: =IF(I97=0,"",I97/F97)
A98: ='SCHEDULE OF VALUE WORKSHEET'!#REF! -> #REF! | B98: ='SCHEDULE OF VALUE WORKSHEET'!#REF! -> #REF! | D98: =SUM('SCHEDULE OF VALUE WORKSHEET'!#REF!) -> #REF! | E98: 0 | F98: =SUM(D98)+E98 -> #REF! | G98: =SUM(F98-I98) -> #REF! | H98: 0 | I98: =SUM(H98) -> 0 | J98: =IF(I98=0,"",I98/F98)
A99: ='SCHEDULE OF VALUE WORKSHEET'!#REF! -> #REF! | B99: ='SCHEDULE OF VALUE WORKSHEET'!#REF! -> #REF! | D99: =SUM('SCHEDULE OF VALUE WORKSHEET'!#REF!) -> #REF! | E99: 0 | F99: =SUM(D99)+E99 -> #REF! | G99: =SUM(F99-I99) -> #REF! | H99: 0 | I99: =SUM(H99) -> 0 | J99: =IF(I99=0,"",I99/F99)
A100: ='SCHEDULE OF VALUE WORKSHEET'!#REF! -> #REF! | B100: ='SCHEDULE OF VALUE WORKSHEET'!#REF! -> #REF! | D100: =SUM('SCHEDULE OF VALUE WORKSHEET'!#REF!) -> #REF! | E100: 0 | F100: =SUM(D100)+E100 -> #REF! | G100: =SUM(F100-I100) -> #REF! | H100: 0 | I100: =SUM(H100) -> 0 | J100: =IF(I100=0,"",I100/F100)
A101: ='SCHEDULE OF VALUE WORKSHEET'!#REF! -> #REF! | B101: ='SCHEDULE OF VALUE WORKSHEET'!#REF! -> #REF! | D101: =SUM('SCHEDULE OF VALUE WORKSHEET'!#REF!) -> #REF! | E101: 0 | F101: =SUM(D101)+E101 -> #REF! | G101: =SUM(F101-I101) -> #REF! | H101: 0 | I101: =SUM(H101) -> 0 | J101: =IF(I101=0,"",I101/F101)
A102: ='SCHEDULE OF VALUE WORKSHEET'!#REF! -> #REF! | B102: ='SCHEDULE OF VALUE WORKSHEET'!#REF! -> #REF! | D102: =SUM('SCHEDULE OF VALUE WORKSHEET'!#REF!) -> #REF! | E102: 0 | F102: =SUM(D102)+E102 -> #REF! | G102: =SUM(F102-I102) -> #REF! | H102: 0 | I102: =SUM(H102) -> 0 | J102: =IF(I102=0,"",I102/F102)
A103: ='SCHEDULE OF VALUE WORKSHEET'!#REF! -> #REF! | B103: ='SCHEDULE OF VALUE WORKSHEET'!#REF! -> #REF! | D103: =SUM('SCHEDULE OF VALUE WORKSHEET'!#REF!) -> #REF! | E103: 0 | F103: =SUM(D103)+E103 -> #REF! | G103: =SUM(F103-I103) -> #REF! | H103: 0 | I103: =SUM(H103) -> 0 | J103: =IF(I103=0,"",I103/F103)
... A117: ='SCHEDULE OF VALUE WORKSHEET'!#REF! -> #REF! | B117: ='SCHEDULE OF VALUE WORKSHEET'!#REF! -> #REF! | D117: =SUM('SCHEDULE OF VALUE WORKSHEET'!#REF!) -> #REF! | E117: 0 | F117: =SUM(D117)+E117 -> #REF! | G117: =SUM(F117-I117) -> #REF! | H117: 0 | I117: =SUM(H117) -> 0 | J117: =IF(I117=0,"",I117/F117)
A118: ='SCHEDULE OF VALUE WORKSHEET'!A87 -> 82 | B118: ='SCHEDULE OF VALUE WORKSHEET'!B87 -> Open Item | D118: =SUM('SCHEDULE OF VALUE WORKSHEET'!E87) -> 0 | E118: 0 | F118: =SUM(D118)+E118 -> 0 | G118: =SUM(F118-I118) -> 0 | H118: 0 | I118: =SUM(H118) -> 0 | J118: =IF(I118=0,"",I118/F118)
A119: ='SCHEDULE OF VALUE WORKSHEET'!A88 -> 83 | B119: ='SCHEDULE OF VALUE WORKSHEET'!B88 -> Open Item | D119: =SUM('SCHEDULE OF VALUE WORKSHEET'!E88) -> 0 | E119: 0 | F119: =SUM(D119)+E119 -> 0 | G119: =SUM(F119-I119) -> 0 | H119: 0 | I119: =SUM(H119) -> 0 | J119: =IF(I119=0,"",I119/F119)
A120: ='SCHEDULE OF VALUE WORKSHEET'!A89 -> 84 | B120: ='SCHEDULE OF VALUE WORKSHEET'!B89 -> Open Item | D120: =SUM('SCHEDULE OF VALUE WORKSHEET'!E89) -> 0 | E120: 0 | F120: =SUM(D120)+E120 -> 0 | G120: =SUM(F120-I120) -> 0 | H120: 0 | I120: =SUM(H120) -> 0 | J120: =IF(I120=0,"",I120/F120)
A121: ='SCHEDULE OF VALUE WORKSHEET'!A90 -> 85 | B121: ='SCHEDULE OF VALUE WORKSHEET'!B90 -> Open Item | D121: =SUM('SCHEDULE OF VALUE WORKSHEET'!E90) -> 0 | E121: 0 | F121: =SUM(D121)+E121 -> 0 | G121: =SUM(F121-I121) -> 0 | H121: 0 | I121: =SUM(H121) -> 0 | J121: =IF(I121=0,"",I121/F121)
A122: ='SCHEDULE OF VALUE WORKSHEET'!A91 -> 86 | B122: ='SCHEDULE OF VALUE WORKSHEET'!B91 -> Open Item | D122: =SUM('SCHEDULE OF VALUE WORKSHEET'!E91) -> 0 | E122: 0 | F122: =SUM(D122)+E122 -> 0 | G122: =SUM(F122-I122) -> 0 | H122: 0 | I122: =SUM(H122) -> 0 | J122: =IF(I122=0,"",I122/F122)
A123: ='SCHEDULE OF VALUE WORKSHEET'!A92 -> 87 | B123: ='SCHEDULE OF VALUE WORKSHEET'!B92 -> Open Item | D123: =SUM('SCHEDULE OF VALUE WORKSHEET'!E92) -> 0 | E123: 0 | F123: =SUM(D123)+E123 -> 0 | G123: =SUM(F123-I123) -> 0 | H123: 0 | I123: =SUM(H123) -> 0 | J123: =IF(I123=0,"",I123/F123)
A124: ='SCHEDULE OF VALUE WORKSHEET'!A93 -> 88 | B124: ='SCHEDULE OF VALUE WORKSHEET'!B93 -> Open Item | D124: =SUM('SCHEDULE OF VALUE WORKSHEET'!E93) -> 0 | E124: 0 | F124: =SUM(D124)+E124 -> 0 | G124: =SUM(F124-I124) -> 0 | H124: 0 | I124: =SUM(H124) -> 0 | J124: =IF(I124=0,"",I124/F124)
A125: ='SCHEDULE OF VALUE WORKSHEET'!A94 -> 89 | B125: ='SCHEDULE OF VALUE WORKSHEET'!B94 -> Open Item | D125: =SUM('SCHEDULE OF VALUE WORKSHEET'!E94) -> 0 | E125: 0 | F125: =SUM(D125)+E125 -> 0 | G125: =SUM(F125-I125) -> 0 | H125: 0 | I125: =SUM(H125) -> 0 | J125: =IF(I125=0,"",I125/F125)
A126: ='SCHEDULE OF VALUE WORKSHEET'!A95 -> 90 | B126: ='SCHEDULE OF VALUE WORKSHEET'!B95 -> Open Item | D126: =SUM('SCHEDULE OF VALUE WORKSHEET'!E95) -> 0 | E126: 0 | F126: =SUM(D126)+E126 -> 0 | G126: =SUM(F126-I126) -> 0 | H126: 0 | I126: =SUM(H126) -> 0 | J126: =IF(I126=0,"",I126/F126)
A127: ='SCHEDULE OF VALUE WORKSHEET'!A96 -> 91 | B127: ='SCHEDULE OF VALUE WORKSHEET'!B96 -> Open Item | D127: =SUM('SCHEDULE OF VALUE WORKSHEET'!E96) -> 0 | E127: 0 | F127: =SUM(D127)+E127 -> 0 | G127: =SUM(F127-I127) -> 0 | H127: 0 | I127: =SUM(H127) -> 0 | J127: =IF(I127=0,"",I127/F127)
A128: ='SCHEDULE OF VALUE WORKSHEET'!A97 -> 92 | B128: ='SCHEDULE OF VALUE WORKSHEET'!B97 -> Open Item | D128: =SUM('SCHEDULE OF VALUE WORKSHEET'!E97) -> 0 | E128: 0 | F128: =SUM(D128)+E128 -> 0 | G128: =SUM(F128-I128) -> 0 | H128: 0 | I128: =SUM(H128) -> 0 | J128: =IF(I128=0,"",I128/F128)
A129: ='SCHEDULE OF VALUE WORKSHEET'!A98 -> 93 | B129: ='SCHEDULE OF VALUE WORKSHEET'!B98 -> Open Item | D129: =SUM('SCHEDULE OF VALUE WORKSHEET'!E98) -> 0 | E129: 0 | F129: =SUM(D129)+E129 -> 0 | G129: =SUM(F129-I129) -> 0 | H129: 0 | I129: =SUM(H129) -> 0 | J129: =IF(I129=0,"",I129/F129)
... A135: ='SCHEDULE OF VALUE WORKSHEET'!A104 -> 99 | B135: ='SCHEDULE OF VALUE WORKSHEET'!B104 -> Open Item | D135: =SUM('SCHEDULE OF VALUE WORKSHEET'!E104) -> 0 | E135: 0 | F135: =SUM(D135)+E135 -> 0 | G135: =SUM(F135-I135) -> 0 | H135: 0 | I135: =SUM(H135) -> 0 | J135: =IF(I135=0,"",I135/F135)
A136: ='SCHEDULE OF VALUE WORKSHEET'!#REF! -> #REF! | B136: ='SCHEDULE OF VALUE WORKSHEET'!#REF! -> #REF! | D136: =SUM('SCHEDULE OF VALUE WORKSHEET'!#REF!) -> #REF! | E136: 0 | F136: =SUM(D136)+E136 -> #REF! | G136: =SUM(F136-I136) -> #REF! | H136: 0 | I136: =SUM(H136) -> 0 | J136: =IF(I136=0,"",I136/F136)
B137: TOTAL | D137: =SUM(D11:D136) -> #REF! | E137: =SUM(E11:E136) -> 0 | F137: =SUM(F11:F136) -> #REF! | G137: =SUM(G11:G136) -> #REF! | H137: =SUM(H11:H136) -> 0 | I137: =SUM(I11:I136) -> 0

Sheet Draw #2
A1: GENESIS CAPITAL DRAW FORM
B3: CLIENT: | C3: ='SCHEDULE OF VALUE WORKSHEET'!$B$3 -> Angeleno Investments | I3: TOTAL COMPLETED TO DATE: | J3: =SUM(J137) -> 0 | K3: =SUM(J3)/J7 -> #REF!
B4: DATE: | C4: =TODAY() -> 45978 | I4: REMAINING $ IN BUDGET: | J4: =SUM(H137) -> #REF!
B5: PROJECT: | C5: ='SCHEDULE OF VALUE WORKSHEET'!B5 -> 10910 Huston Street | I5: ORIGINAL SCHEDULE OF VALUES: | J5: =SUM(D137) -> #REF!
B6: DRAW REQUEST: | C6: =SUM(I137) -> 0 | I6: CHANGE ORDERS: | J6: =SUM(F137) -> 0
I7: REVISED SCHEDULE OF VALUES: | J7: =SUM(G137) -> #REF!
B8: DESCRIPTION OF WORK | D8: SCHEDULED VALUES | E8: PREVIOUS | F8: + / - CHANGES | G8: REVISED VALUES | H8: REMAINING | I8: DRAW | J8: COMPLETED AND
E9: CHANGES | H9: BUDGET | I9: 2 | J9: STORED TO DATE
A10: ='SCHEDULE OF VALUE WORKSHEET'!A7 -> 1 | B10: ='SCHEDULE OF VALUE WORKSHEET'!B7 -> SOFT COSTS | D10: =SUM('SCHEDULE OF VALUE WORKSHEET'!E7) -> 0 | E10: =SUM('Draw #1'!E11) -> 0 | F10: 0 | G10: =SUM('Draw #1'!F11)+F10 -> 0 | H10: =SUM(G10-J10) -> 0 | I10: 0 | J10: =SUM(I10+'Draw #1'!I11) -> 0 | K10: =IF(J10=0,"",J10/G10)
A11: ='SCHEDULE OF VALUE WORKSHEET'!A8 -> 2 | B11: ='SCHEDULE OF VALUE WORKSHEET'!B8 -> Site Security | D11: =SUM('SCHEDULE OF VALUE WORKSHEET'!E8) -> 10580.63 | E11: =SUM('Draw #1'!E12) -> 0 | F11: 0 | G11: =SUM('Draw #1'!F12)+F11 -> 10580.63 | H11: =SUM(G11-J11) -> 10580.63 | I11: 0 | J11: =SUM(I11+'Draw #1'!I12) -> 0 | K11: =IF(J11=0,"",J11/G11)
A12: ='SCHEDULE OF VALUE WORKSHEET'!A9 -> 3 | B12: ='SCHEDULE OF VALUE WORKSHEET'!B9 -> Soils Inspection | D12: =SUM('SCHEDULE OF VALUE WORKSHEET'!E9) -> 0 | E12: =SUM('Draw #1'!E13) -> 0 | F12: 0 | G12: =SUM('Draw #1'!F13)+F12 -> 0 | H12: =SUM(G12-J12) -> 0 | I12: 0 | J12: =SUM(I12+'Draw #1'!I13) -> 0 | K12: =IF(J12=0,"",J12/G12)
A13: ='SCHEDULE OF VALUE WORKSHEET'!A10 -> 4 | B13: ='SCHEDULE OF VALUE WORKSHEET'!B10 -> Offsites (Transformer) | D13: =SUM('SCHEDULE OF VALUE WORKSHEET'!E10) -> 20000 | E13: =SUM('Draw #1'!E14) -> 0 | F13: 0 | G13: =SUM('Draw #1'!F14)+F13 -> 20000 | H13: =SUM(G13-J13) -> 20000 | I13: 0 | J13: =SUM(I13+'Draw #1'!I14) -> 0 | K13: =IF(J13=0,"",J13/G13)
A14: ='SCHEDULE OF VALUE WORKSHEET'!A11 -> 5 | B14: ='SCHEDULE OF VALUE WORKSHEET'!B11 -> Plan Check Fees | D14: =SUM('SCHEDULE OF VALUE WORKSHEET'!E11) -> 0 | E14: =SUM('Draw #1'!E15) -> 0 | F14: 0 | G14: =SUM('Draw #1'!F15)+F14 -> 0 | H14: =SUM(G14-J14) -> 0 | I14: 0 | J14: =SUM(I14+'Draw #1'!I15) -> 0 | K14: =IF(J14=0,"",J14/G14)
A15: ='SCHEDULE OF VALUE WORKSHEET'!A12 -> 6 | B15: ='SCHEDULE OF VALUE WORKSHEET'!B12 -> Permits | D15: =SUM('SCHEDULE OF VALUE WORKSHEET'!E12) -> 0 | E15: =SUM('Draw #1'!E16) -> 0 | F15: 0 | G15: =SUM('Draw #1'!F16)+F15 -> 0 | H15: =SUM(G15-J15) -> 0 | I15: 0 | J15: =SUM(I15+'Draw #1'!I16) -> 0 | K15: =IF(J15=0,"",J15/G15)
A16: ='SCHEDULE OF VALUE WORKSHEET'!A13 -> 7 | B16: ='SCHEDULE OF VALUE WORKSHEET'!B13 -> Survey | D16: =SUM('SCHEDULE OF VALUE WORKSHEET'!E13) -> 0 | E16: =SUM('Draw #1'!E17) -> 0 | F16: 0 | G16: =SUM('Draw #1'!F17)+F16 -> 0 | H16: =SUM(G16-J16) -> 0 | I16: 0 | J16: =SUM(I16+'Draw #1'!I17) -> 0 | K16: =IF(J16=0,"",J16/G16)
A17: ='SCHEDULE OF VALUE WORKSHEET'!A14 -> 8 | B17: ='SCHEDULE OF VALUE WORKSHEET'!B14 -> Soils Engineer | D17: =SUM('SCHEDULE OF VALUE WORKSHEET'!E14) -> 0 | E17: =SUM('Draw #1'!E18) -> 0 | F17: 0 | G17: =SUM('Draw #1'!F18)+F17 -> 0 | H17: =SUM(G17-J17) -> 0 | I17: 0 | J17: =SUM(I17+'Draw #1'!I18) -> 0 | K17: =IF(J17=0,"",J17/G17)
A18: ='SCHEDULE OF VALUE WORKSHEET'!A15 -> 9 | B18: ='SCHEDULE OF VALUE WORKSHEET'!B15 -> Soils Permit + T24 | D18: =SUM('SCHEDULE OF VALUE WORKSHEET'!E15) -> 2500 | E18: =SUM('Draw #1'!E19) -> 0 | F18: 0 | G18: =SUM('Draw #1'!F19)+F18 -> 2500 | H18: =SUM(G18-J18) -> 2500 | I18: 0 | J18: =SUM(I18+'Draw #1'!I19) -> 0 | K18: =IF(J18=0,"",J18/G18)
A19: ='SCHEDULE OF VALUE WORKSHEET'!A16 -> 10 | B19: ='SCHEDULE OF VALUE WORKSHEET'!B16 -> Special Inspections - Deputy | D19: =SUM('SCHEDULE OF VALUE WORKSHEET'!E16) -> 15000 | E19: =SUM('Draw #1'!E20) -> 0 | F19: 0 | G19: =SUM('Draw #1'!F20)+F19 -> 15000 | H19: =SUM(G19-J19) -> 15000 | I19: 0 | J19: =SUM(I19+'Draw #1'!I20) -> 0 | K19: =IF(J19=0,"",J19/G19)
A20: ='SCHEDULE OF VALUE WORKSHEET'!A17 -> 11 | B20: ='SCHEDULE OF VALUE WORKSHEET'!B17 -> Architect | D20: =SUM('SCHEDULE OF VALUE WORKSHEET'!E17) -> 0 | E20: =SUM('Draw #1'!E21) -> 0 | F20: 0 | G20: =SUM('Draw #1'!F21)+F20 -> 0 | H20: =SUM(G20-J20) -> 0 | I20: 0 | J20: =SUM(I20+'Draw #1'!I21) -> 0 | K20: =IF(J20=0,"",J20/G20)
A21: ='SCHEDULE OF VALUE WORKSHEET'!A18 -> 12 | B21: ='SCHEDULE OF VALUE WORKSHEET'!B18 -> Structural Engineer | D21: =SUM('SCHEDULE OF VALUE WORKSHEET'!E18) -> 0 | E21: =SUM('Draw #1'!E22) -> 0 | F21: 0 | G21: =SUM('Draw #1'!F22)+F21 -> 0 | H21: =SUM(G21-J21) -> 0 | I21: 0 | J21: =SUM(I21+'Draw #1'!I22) -> 0 | K21: =IF(J21=0,"",J21/G21)
... A45: ='SCHEDULE OF VALUE WORKSHEET'!A42 -> 36 | B45: ='SCHEDULE OF VALUE WORKSHEET'!B42 -> Construction Management / Observation (OO) | D45: =SUM('SCHEDULE OF VALUE WORKSHEET'!E42) -> 49427.9 | E45: =SUM('Draw #1'!E46) -> 0 | F45: 0 | G45: =SUM('Draw #1'!F46)+F45 -> 49427.9 | H45: =SUM(G45-J45) -> 49427.9 | I45: 0 | J45: =SUM(I45+'Draw #1'!I46) -> 0 | K45: =IF(J45=0,"",J45/G45)
A46: ='SCHEDULE OF VALUE WORKSHEET'!#REF! -> #REF! | B46: ='SCHEDULE OF VALUE WORKSHEET'!#REF! -> #REF! | D46: =SUM('SCHEDULE OF VALUE WORKSHEET'!#REF!) -> #REF! | E46: =SUM('Draw #1'!E47) -> 0 | F46: 0 | G46: =SUM('Draw #1'!F47)+F46 -> #REF! | H46: =SUM(G46-J46) -> #REF! | I46: 0 | J46: =SUM(I46+'Draw #1'!I47) -> 0 | K46: =IF(J46=0,"",J46/G46)
A47: ='SCHEDULE OF VALUE WORKSHEET'!A43 -> 37 | B47: ='SCHEDULE OF VALUE WORKSHEET'!B43 -> CMFA Startup Fee | D47: =SUM('SCHEDULE OF VALUE WORKSHEET'!E43) -> 22800 | E47: =SUM('Draw #1'!E48) -> 0 | F47: 0 | G47: =SUM('Draw #1'!F48)+F47 -> 22800 | H47: =SUM(G47-J47) -> 22800 | I47: 0 | J47: =SUM(I47+'Draw #1'!I48) -> 0 | K47: =IF(J47=0,"",J47/G47)
A48: ='SCHEDULE OF VALUE WORKSHEET'!A44 -> 38 | B48: ='SCHEDULE OF VALUE WORKSHEET'!B44 -> Non-Profit Start Up Fee | D48: =SUM('SCHEDULE OF VALUE WORKSHEET'!E44) -> 25000 | E48: =SUM('Draw #1'!E49) -> 0 | F48: 0 | G48: =SUM('Draw #1'!F49)+F48 -> 25000 | H48: =SUM(G48-J48) -> 25000 | I48: 0 | J48: =SUM(I48+'Draw #1'!I49) -> 0 | K48: =IF(J48=0,"",J48/G48)
A49: ='SCHEDULE OF VALUE WORKSHEET'!A45 -> 39 | B49: ='SCHEDULE OF VALUE WORKSHEET'!B45 -> CMFA Construction Fee | D49: =SUM('SCHEDULE OF VALUE WORKSHEET'!E45) -> 12000 | E49: =SUM('Draw #1'!E50) -> 0 | F49: 0 | G49: =SUM('Draw #1'!F50)+F49 -> 12000 | H49: =SUM(G49-J49) -> 12000 | I49: 0 | J49: =SUM(I49+'Draw #1'!I50) -> 0 | K49: =IF(J49=0,"",J49/G49)
A50: ='SCHEDULE OF VALUE WORKSHEET'!A46 -> 40 | B50: ='SCHEDULE OF VALUE WORKSHEET'!B46 -> Non-Profit Construction Fee | D50: =SUM('SCHEDULE OF VALUE WORKSHEET'!E46) -> 10000 | E50: =SUM('Draw #1'!E51) -> 0 | F50: 0 | G50: =SUM('Draw #1'!F51)+F50 -> 10000 | H50: =SUM(G50-J50) -> 10000 | I50: 0 | J50: =SUM(I50+'Draw #1'!I51) -> 0 | K50: =IF(J50=0,"",J50/G50)
A51: ='SCHEDULE OF VALUE WORKSHEET'!A47 -> 41 | B51: ='SCHEDULE OF VALUE WORKSHEET'!B47 -> WTE Legal Costs for CMFA & Non-Profit Partner | D51: =SUM('SCHEDULE OF VALUE WORKSHEET'!E47) -> 20000 | E51: =SUM('Draw #1'!E52) -> 0 | F51: 0 | G51: =SUM('Draw #1'!F52)+F51 -> 20000 | H51: =SUM(G51-J51) -> 20000 | I51: 0 | J51: =SUM(I51+'Draw #1'!I52) -> 0 | K51: =IF(J51=0,"",J51/G51)
A52: ='SCHEDULE OF VALUE WORKSHEET'!#REF! -> #REF! | B52: ='SCHEDULE OF VALUE WORKSHEET'!#REF! -> #REF! | D52: =SUM('SCHEDULE OF VALUE WORKSHEET'!#REF!) -> #REF! | E52: =SUM('Draw #1'!E53) -> 0 | F52: 0 | G52: =SUM('Draw #1'!F53)+F52 -> #REF! | H52: =SUM(G52-J52) -> #REF! | I52: 0 | J52: =SUM(I52+'Draw #1'!I53) -> 0 | K52: =IF(J52=0,"",J52/G52)
A53: ='SCHEDULE OF VALUE WORKSHEET'!A49 -> 43 | B53: ='SCHEDULE OF VALUE WORKSHEET'!B49 -> GENERAL CONDITIONS | D53: =SUM('SCHEDULE OF VALUE WORKSHEET'!E49) -> 362115.24 | E53: =SUM('Draw #1'!E54) -> 0 | F53: 0 | G53: =SUM('Draw #1'!F54)+F53 -> 362115.24 | H53: =SUM(G53-J53) -> 362115.24 | I53: 0 | J53: =SUM(I53+'Draw #1'!I54) -> 0 | K53: =IF(J53=0,"",J53/G53)
A54: ='SCHEDULE OF VALUE WORKSHEET'!A50 -> 44 | B54: ='SCHEDULE OF VALUE WORKSHEET'!B50 -> GENERAL REQUIREMENT | D54: =SUM('SCHEDULE OF VALUE WORKSHEET'!E50) -> 124657.88 | E54: =SUM('Draw #1'!E55) -> 0 | F54: 0 | G54: =SUM('Draw #1'!F55)+F54 -> 124657.88 | H54: =SUM(G54-J54) -> 124657.88 | I54: 0 | J54: =SUM(I54+'Draw #1'!I55) -> 0 | K54: =IF(J54=0,"",J54/G54)
A55: ='SCHEDULE OF VALUE WORKSHEET'!A51 -> 45 | B55: ='SCHEDULE OF VALUE WORKSHEET'!B51 -> SITE WORK | D55: =SUM('SCHEDULE OF VALUE WORKSHEET'!E51) -> 139049.51 | E55: =SUM('Draw #1'!E56) -> 0 | F55: 0 | G55: =SUM('Draw #1'!F56)+F55 -> 139049.51 | H55: =SUM(G55-J55) -> 139049.51 | I55: 0 | J55: =SUM(I55+'Draw #1'!I56) -> 0 | K55: =IF(J55=0,"",J55/G55)
A56: ='SCHEDULE OF VALUE WORKSHEET'!A52 -> 46 | B56: ='SCHEDULE OF VALUE WORKSHEET'!B52 -> CONCRETE | D56: =SUM('SCHEDULE OF VALUE WORKSHEET'!E52) -> 253182 | E56: =SUM('Draw #1'!E57) -> 0 | F56: 0 | G56: =SUM('Draw #1'!F57)+F56 -> 253182 | H56: =SUM(G56-J56) -> 253182 | I56: 0 | J56: =SUM(I56+'Draw #1'!I57) -> 0 | K56: =IF(J56=0,"",J56/G56)
A57: ='SCHEDULE OF VALUE WORKSHEET'!A53 -> 47 | B57: ='SCHEDULE OF VALUE WORKSHEET'!B53 -> MASONRY | D57: =SUM('SCHEDULE OF VALUE WORKSHEET'!E53) -> 3562.64 | E57: =SUM('Draw #1'!E58) -> 0 | F57: 0 | G57: =SUM('Draw #1'!F58)+F57 -> 3562.64 | H57: =SUM(G57-J57) -> 3562.64 | I57: 0 | J57: =SUM(I57+'Draw #1'!I58) -> 0 | K57: =IF(J57=0,"",J57/G57)
A58: ='SCHEDULE OF VALUE WORKSHEET'!A54 -> 48 | B58: ='SCHEDULE OF VALUE WORKSHEET'!B54 -> METALS | D58: =SUM('SCHEDULE OF VALUE WORKSHEET'!E54) -> 324100 | E58: =SUM('Draw #1'!E59) -> 0 | F58: 0 | G58: =SUM('Draw #1'!F59)+F58 -> 324100 | H58: =SUM(G58-J58) -> 324100 | I58: 0 | J58: =SUM(I58+'Draw #1'!I59) -> 0 | K58: =IF(J58=0,"",J58/G58)
A59: ='SCHEDULE OF VALUE WORKSHEET'!A55 -> 49 | B59: ='SCHEDULE OF VALUE WORKSHEET'!B55 -> FRAMING | D59: =SUM('SCHEDULE OF VALUE WORKSHEET'!E55) -> 818554 | E59: =SUM('Draw #1'!E60) -> 0 | F59: 0 | G59: =SUM('Draw #1'!F60)+F59 -> 818554 | H59: =SUM(G59-J59) -> 818554 | I59: 0 | J59: =SUM(I59+'Draw #1'!I60) -> 0 | K59: =IF(J59=0,"",J59/G59)
A60: ='SCHEDULE OF VALUE WORKSHEET'!A56 -> 50 | B60: ='SCHEDULE OF VALUE WORKSHEET'!B56 -> COUNTERTOPS | D60: =SUM('SCHEDULE OF VALUE WORKSHEET'!E56) -> 56930 | E60: =SUM('Draw #1'!E61) -> 0 | F60: 0 | G60: =SUM('Draw #1'!F61)+F60 -> 56930 | H60: =SUM(G60-J60) -> 56930 | I60: 0 | J60: =SUM(I60+'Draw #1'!I61) -> 0 | K60: =IF(J60=0,"",J60/G60)
A61: ='SCHEDULE OF VALUE WORKSHEET'!A57 -> 51 | B61: ='SCHEDULE OF VALUE WORKSHEET'!B57 -> CABINETS | D61: =SUM('SCHEDULE OF VALUE WORKSHEET'!E57) -> 56930 | E61: =SUM('Draw #1'!E62) -> 0 | F61: 0 | G61: =SUM('Draw #1'!F62)+F61 -> 56930 | H61: =SUM(G61-J61) -> 56930 | I61: 0 | J61: =SUM(I61+'Draw #1'!I62) -> 0 | K61: =IF(J61=0,"",J61/G61)
A62: ='SCHEDULE OF VALUE WORKSHEET'!A58 -> 52 | B62: ='SCHEDULE OF VALUE WORKSHEET'!B58 -> THERMAL MOISTURE PROTECTION | D62: =SUM('SCHEDULE OF VALUE WORKSHEET'!E58) -> 173148 | E62: =SUM('Draw #1'!E63) -> 0 | F62: 0 | G62: =SUM('Draw #1'!F63)+F62 -> 173148 | H62: =SUM(G62-J62) -> 173148 | I62: 0 | J62: =SUM(I62+'Draw #1'!I63) -> 0 | K62: =IF(J62=0,"",J62/G62)
A63: ='SCHEDULE OF VALUE WORKSHEET'!A59 -> 53 | B63: ='SCHEDULE OF VALUE WORKSHEET'!B59 -> DOORS | D63: =SUM('SCHEDULE OF VALUE WORKSHEET'!E59) -> 204087.33 | E63: =SUM('Draw #1'!E64) -> 0 | F63: 0 | G63: =SUM('Draw #1'!F64)+F63 -> 204087.33 | H63: =SUM(G63-J63) -> 204087.33 | I63: 0 | J63: =SUM(I63+'Draw #1'!I64) -> 0 | K63: =IF(J63=0,"",J63/G63)
A64: ='SCHEDULE OF VALUE WORKSHEET'!A60 -> 54 | B64: ='SCHEDULE OF VALUE WORKSHEET'!B60 -> WINDOWS | D64: =SUM('SCHEDULE OF VALUE WORKSHEET'!E60) -> 106274.25 | E64: =SUM('Draw #1'!E65) -> 0 | F64: 0 | G64: =SUM('Draw #1'!F65)+F64 -> 106274.25 | H64: =SUM(G64-J64) -> 106274.25 | I64: 0 | J64: =SUM(I64+'Draw #1'!I65) -> 0 | K64: =IF(J64=0,"",J64/G64)
... A90: ='SCHEDULE OF VALUE WORKSHEET'!A86 -> 80 | B90: ='SCHEDULE OF VALUE WORKSHEET'!B86 -> FINANCING COSTS | D90: =SUM('SCHEDULE OF VALUE WORKSHEET'!E86) -> 0 | E90: =SUM('Draw #1'!E91) -> 0 | F90: 0 | G90: =SUM('Draw #1'!F91)+F90 -> 0 | H90: =SUM(G90-J90) -> 0 | I90: 0 | J90: =SUM(I90+'Draw #1'!I91) -> 0 | K90: =IF(J90=0,"",J90/G90)
A91: ='SCHEDULE OF VALUE WORKSHEET'!#REF! -> #REF! | B91: ='SCHEDULE OF VALUE WORKSHEET'!#REF! -> #REF! | D91: =SUM('SCHEDULE OF VALUE WORKSHEET'!#REF!) -> #REF! | E91: =SUM('Draw #1'!E92) -> 0 | F91: 0 | G91: =SUM('Draw #1'!F92)+F91 -> #REF! | H91: =SUM(G91-J91) -> #REF! | I91: 0 | J91: =SUM(I91+'Draw #1'!I92) -> 0 | K91: =IF(J91=0,"",J91/G91)
A92: ='SCHEDULE OF VALUE WORKSHEET'!#REF! -> #REF! | B92: ='SCHEDULE OF VALUE WORKSHEET'!#REF! -> #REF! | D92: =SUM('SCHEDULE OF VALUE WORKSHEET'!#REF!) -> #REF! | E92: =SUM('Draw #1'!E93) -> 0 | F92: 0 | G92: =SUM('Draw #1'!F93)+F92 -> #REF! | H92: =SUM(G92-J92) -> #REF! | I92: 0 | J92: =SUM(I92+'Draw #1'!I93) -> 0 | K92: =IF(J92=0,"",J92/G92)
A93: ='SCHEDULE OF VALUE WORKSHEET'!#REF! -> #REF! | B93: ='SCHEDULE OF VALUE WORKSHEET'!#REF! -> #REF! | D93: =SUM('SCHEDULE OF VALUE WORKSHEET'!#REF!) -> #REF! | E93: =SUM('Draw #1'!E94) -> 0 | F93: 0 | G93: =SUM('Draw #1'!F94)+F93 -> #REF! | H93: =SUM(G93-J93) -> #REF! | I93: 0 | J93: =SUM(I93+'Draw #1'!I94) -> 0 | K93: =IF(J93=0,"",J93/G93)
A94: ='SCHEDULE OF VALUE WORKSHEET'!#REF! -> #REF! | B94: ='SCHEDULE OF VALUE WORKSHEET'!#REF! -> #REF! | D94: =SUM('SCHEDULE OF VALUE WORKSHEET'!#REF!) -> #REF! | E94: =SUM('Draw #1'!E95) -> 0 | F94: 0 | G94: =SUM('Draw #1'!F95)+F94 -> #REF! | H94: =SUM(G94-J94) -> #REF! | I94: 0 | J94: =SUM(I94+'Draw #1'!I95) -> 0 | K94: =IF(J94=0,"",J94/G94)
A95: ='SCHEDULE OF VALUE WORKSHEET'!#REF! -> #REF! | B95: ='SCHEDULE OF VALUE WORKSHEET'!#REF! -> #REF! | D95: =SUM('SCHEDULE OF VALUE WORKSHEET'!#REF!) -> #REF! | E95: =SUM('Draw #1'!E96) -> 0 | F95: 0 | G95: =SUM('Draw #1'!F96)+F95 -> #REF! | H95: =SUM(G95-J95) -> #REF! | I95: 0 | J95: =SUM(I95+'Draw #1'!I96) -> 0 | K95: =IF(J95=0,"",J95/G95)
A96: ='SCHEDULE OF VALUE WORKSHEET'!#REF! -> #REF! | B96: ='SCHEDULE OF VALUE WORKSHEET'!#REF! -> #REF! | D96: =SUM('SCHEDULE OF VALUE WORKSHEET'!#REF!) -> #REF! | E96: =SUM('Draw #1'!E97) -> 0 | F96: 0 | G96: =SUM('Draw #1'!F97)+F96 -> #REF! | H96: =SUM(G96-J96) -> #REF! | I96: 0 | J96: =SUM(I96+'Draw #1'!I97) -> 0 | K96: =IF(J96=0,"",J96/G96)
A97: ='SCHEDULE OF VALUE WORKSHEET'!#REF! -> #REF! | B97: ='SCHEDULE OF VALUE WORKSHEET'!#REF! -> #REF! | D97: =SUM('SCHEDULE OF VALUE WORKSHEET'!#REF!) -> #REF! | E97: =SUM('Draw #1'!E98) -> 0 | F97: 0 | G97: =SUM('Draw #1'!F98)+F97 -> #REF! | H97: =SUM(G97-J97) -> #REF! | I97: 0 | J97: =SUM(I97+'Draw #1'!I98) -> 0 | K97: =IF(J97=0,"",J97/G97)
A98: ='SCHEDULE OF VALUE WORKSHEET'!#REF! -> #REF! | B98: ='SCHEDULE OF VALUE WORKSHEET'!#REF! -> #REF! | D98: =SUM('SCHEDULE OF VALUE WORKSHEET'!#REF!) -> #REF! | E98: =SUM('Draw #1'!E99) -> 0 | F98: 0 | G98: =SUM('Draw #1'!F99)+F98 -> #REF! | H98: =SUM(G98-J98) -> #REF! | I98: 0 | J98: =SUM(I98+'Draw #1'!I99) -> 0 | K98: =IF(J98=0,"",J98/G98)
A99: ='SCHEDULE OF VALUE WORKSHEET'!#REF! -> #REF! | B99: ='SCHEDULE OF VALUE WORKSHEET'!#REF! -> #REF! | D99: =SUM('SCHEDULE OF VALUE WORKSHEET'!#REF!) -> #REF! | E99: =SUM('Draw #1'!E100) -> 0 | F99: 0 | G99: =SUM('Draw #1'!F100)+F99 -> #REF! | H99: =SUM(G99-J99) -> #REF! | I99: 0 | J99: =SUM(I99+'Draw #1'!I100) -> 0 | K99: =IF(J99=0,"",J99/G99)
A100: ='SCHEDULE OF VALUE WORKSHEET'!#REF! -> #REF! | B100: ='SCHEDULE OF VALUE WORKSHEET'!#REF! -> #REF! | D100: =SUM('SCHEDULE OF VALUE WORKSHEET'!#REF!) -> #REF! | E100: =SUM('Draw #1'!E101) -> 0 | F100: 0 | G100: =SUM('Draw #1'!F101)+F100 -> #REF! | H100: =SUM(G100-J100) -> #REF! | I100: 0 | J100: =SUM(I100+'Draw #1'!I101) -> 0 | K100: =IF(J100=0,"",J100/G100)
A101: ='SCHEDULE OF VALUE WORKSHEET'!#REF! -> #REF! | B101: ='SCHEDULE OF VALUE WORKSHEET'!#REF! -> #REF! | D101: =SUM('SCHEDULE OF VALUE WORKSHEET'!#REF!) -> #REF! | E101: =SUM('Draw #1'!E102) -> 0 | F101: 0 | G101: =SUM('Draw #1'!F102)+F101 -> #REF! | H101: =SUM(G101-J101) -> #REF! | I101: 0 | J101: =SUM(I101+'Draw #1'!I102) -> 0 | K101: =IF(J101=0,"",J101/G101)
A102: ='SCHEDULE OF VALUE WORKSHEET'!#REF! -> #REF! | B102: ='SCHEDULE OF VALUE WORKSHEET'!#REF! -> #REF! | D102: =SUM('SCHEDULE OF VALUE WORKSHEET'!#REF!) -> #REF! | E102: =SUM('Draw #1'!E103) -> 0 | F102: 0 | G102: =SUM('Draw #1'!F103)+F102 -> #REF! | H102: =SUM(G102-J102) -> #REF! | I102: 0 | J102: =SUM(I102+'Draw #1'!I103) -> 0 | K102: =IF(J102=0,"",J102/G102)
... A116: ='SCHEDULE OF VALUE WORKSHEET'!#REF! -> #REF! | B116: ='SCHEDULE OF VALUE WORKSHEET'!#REF! -> #REF! | D116: =SUM('SCHEDULE OF VALUE WORKSHEET'!#REF!) -> #REF! | E116: =SUM('Draw #1'!E117) -> 0 | F116: 0 | G116: =SUM('Draw #1'!F117)+F116 -> #REF! | H116: =SUM(G116-J116) -> #REF! | I116: 0 | J116: =SUM(I116+'Draw #1'!I117) -> 0 | K116: =IF(J116=0,"",J116/G116)
A117: ='SCHEDULE OF VALUE WORKSHEET'!A87 -> 82 | B117: ='SCHEDULE OF VALUE WORKSHEET'!B87 -> Open Item | D117: =SUM('SCHEDULE OF VALUE WORKSHEET'!E87) -> 0 | E117: =SUM('Draw #1'!E118) -> 0 | F117: 0 | G117: =SUM('Draw #1'!F118)+F117 -> 0 | H117: =SUM(G117-J117) -> 0 | I117: 0 | J117: =SUM(I117+'Draw #1'!I118) -> 0 | K117: =IF(J117=0,"",J117/G117)
A118: ='SCHEDULE OF VALUE WORKSHEET'!A88 -> 83 | B118: ='SCHEDULE OF VALUE WORKSHEET'!B88 -> Open Item | D118: =SUM('SCHEDULE OF VALUE WORKSHEET'!E88) -> 0 | E118: =SUM('Draw #1'!E119) -> 0 | F118: 0 | G118: =SUM('Draw #1'!F119)+F118 -> 0 | H118: =SUM(G118-J118) -> 0 | I118: 0 | J118: =SUM(I118+'Draw #1'!I119) -> 0 | K118: =IF(J118=0,"",J118/G118)
A119: ='SCHEDULE OF VALUE WORKSHEET'!A89 -> 84 | B119: ='SCHEDULE OF VALUE WORKSHEET'!B89 -> Open Item | D119: =SUM('SCHEDULE OF VALUE WORKSHEET'!E89) -> 0 | E119: =SUM('Draw #1'!E120) -> 0 | F119: 0 | G119: =SUM('Draw #1'!F120)+F119 -> 0 | H119: =SUM(G119-J119) -> 0 | I119: 0 | J119: =SUM(I119+'Draw #1'!I120) -> 0 | K119: =IF(J119=0,"",J119/G119)
A120: ='SCHEDULE OF VALUE WORKSHEET'!A90 -> 85 | B120: ='SCHEDULE OF VALUE WORKSHEET'!B90 -> Open Item | D120: =SUM('SCHEDULE OF VALUE WORKSHEET'!E90) -> 0 | E120: =SUM('Draw #1'!E121) -> 0 | F120: 0 | G120: =SUM('Draw #1'!F121)+F120 -> 0 | H120: =SUM(G120-J120) -> 0 | I120: 0 | J120: =SUM(I120+'Draw #1'!I121) -> 0 | K120: =IF(J120=0,"",J120/G120)
A121: ='SCHEDULE OF VALUE WORKSHEET'!A91 -> 86 | B121: ='SCHEDULE OF VALUE WORKSHEET'!B91 -> Open Item | D121: =SUM('SCHEDULE OF VALUE WORKSHEET'!E91) -> 0 | E121: =SUM('Draw #1'!E122) -> 0 | F121: 0 | G121: =SUM('Draw #1'!F122)+F121 -> 0 | H121: =SUM(G121-J121) -> 0 | I121: 0 | J121: =SUM(I121+'Draw #1'!I122) -> 0 | K121: =IF(J121=0,"",J121/G121)
A122: ='SCHEDULE OF VALUE WORKSHEET'!A92 -> 87 | B122: ='SCHEDULE OF VALUE WORKSHEET'!B92 -> Open Item | D122: =SUM('SCHEDULE OF VALUE WORKSHEET'!E92) -> 0 | E122: =SUM('Draw #1'!E123) -> 0 | F122: 0 | G122: =SUM('Draw #1'!F123)+F122 -> 0 | H122: =SUM(G122-J122) -> 0 | I122: 0 | J122: =SUM(I122+'Draw #1'!I123) -> 0 | K122: =IF(J122=0,"",J122/G122)
A123: ='SCHEDULE OF VALUE WORKSHEET'!A93 -> 88 | B123: ='SCHEDULE OF VALUE WORKSHEET'!B93 -> Open Item | D123: =SUM('SCHEDULE OF VALUE WORKSHEET'!E93) -> 0 | E123: =SUM('Draw #1'!E124) -> 0 | F123: 0 | G123: =SUM('Draw #1'!F124)+F123 -> 0 | H123: =SUM(G123-J123) -> 0 | I123: 0 | J123: =SUM(I123+'Draw #1'!I124) -> 0 | K123: =IF(J123=0,"",J123/G123)
A124: ='SCHEDULE OF VALUE WORKSHEET'!A94 -> 89 | B124: ='SCHEDULE OF VALUE WORKSHEET'!B94 -> Open Item | D124: =SUM('SCHEDULE OF VALUE WORKSHEET'!E94) -> 0 | E124: =SUM('Draw #1'!E125) -> 0 | F124: 0 | G124: =SUM('Draw #1'!F125)+F124 -> 0 | H124: =SUM(G124-J124) -> 0 | I124: 0 | J124: =SUM(I124+'Draw #1'!I125) -> 0 | K124: =IF(J124=0,"",J124/G124)
A125: ='SCHEDULE OF VALUE WORKSHEET'!A95 -> 90 | B125: ='SCHEDULE OF VALUE WORKSHEET'!B95 -> Open Item | D125: =SUM('SCHEDULE OF VALUE WORKSHEET'!E95) -> 0 | E125: =SUM('Draw #1'!E126) -> 0 | F125: 0 | G125: =SUM('Draw #1'!F126)+F125 -> 0 | H125: =SUM(G125-J125) -> 0 | I125: 0 | J125: =SUM(I125+'Draw #1'!I126) -> 0 | K125: =IF(J125=0,"",J125/G125)
A126: ='SCHEDULE OF VALUE WORKSHEET'!A96 -> 91 | B126: ='SCHEDULE OF VALUE WORKSHEET'!B96 -> Open Item | D126: =SUM('SCHEDULE OF VALUE WORKSHEET'!E96) -> 0 | E126: =SUM('Draw #1'!E127) -> 0 | F126: 0 | G126: =SUM('Draw #1'!F127)+F126 -> 0 | H126: =SUM(G126-J126) -> 0 | I126: 0 | J126: =SUM(I126+'Draw #1'!I127) -> 0 | K126: =IF(J126=0,"",J126/G126)
A127: ='SCHEDULE OF VALUE WORKSHEET'!A97 -> 92 | B127: ='SCHEDULE OF VALUE WORKSHEET'!B97 -> Open Item | D127: =SUM('SCHEDULE OF VALUE WORKSHEET'!E97) -> 0 | E127: =SUM('Draw #1'!E128) -> 0 | F127: 0 | G127: =SUM('Draw #1'!F128)+F127 -> 0 | H127: =SUM(G127-J127) -> 0 | I127: 0 | J127: =SUM(I127+'Draw #1'!I128) -> 0 | K127: =IF(J127=0,"",J127/G127)
A128: ='SCHEDULE OF VALUE WORKSHEET'!A98 -> 93 | B128: ='SCHEDULE OF VALUE WORKSHEET'!B98 -> Open Item | D128: =SUM('SCHEDULE OF VALUE WORKSHEET'!E98) -> 0 | E128: =SUM('Draw #1'!E129) -> 0 | F128: 0 | G128: =SUM('Draw #1'!F129)+F128 -> 0 | H128: =SUM(G128-J128) -> 0 | I128: 0 | J128: =SUM(I128+'Draw #1'!I129) -> 0 | K128: =IF(J128=0,"",J128/G128)
... A134: ='SCHEDULE OF VALUE WORKSHEET'!A104 -> 99 | B134: ='SCHEDULE OF VALUE WORKSHEET'!B104 -> Open Item | D134: =SUM('SCHEDULE OF VALUE WORKSHEET'!E104) -> 0 | E134: =SUM('Draw #1'!E135) -> 0 | F134: 0 | G134: =SUM('Draw #1'!F135)+F134 -> 0 | H134: =SUM(G134-J134) -> 0 | I134: 0 | J134: =SUM(I134+'Draw #1'!I135) -> 0 | K134: =IF(J134=0,"",J134/G134)
A135: ='SCHEDULE OF VALUE WORKSHEET'!#REF! -> #REF! | B135: ='SCHEDULE OF VALUE WORKSHEET'!#REF! -> #REF! | D135: =SUM('SCHEDULE OF VALUE WORKSHEET'!#REF!) -> #REF! | E135: =SUM('Draw #1'!E136) -> 0 | F135: 0 | G135: =SUM('Draw #1'!F136)+F135 -> #REF! | H135: =SUM(G135-J135) -> #REF! | I135: 0 | J135: =SUM(I135+'Draw #1'!I136) -> 0 | K135: =IF(J135=0,"",J135/G135)
B137: TOTAL | D137: =SUM(D10:D135) -> #REF! | E137: =SUM(E10:E135) -> 0 | F137: =SUM(F10:F135) -> 0 | G137: =SUM(G10:G135) -> #REF! | H137: =SUM(H10:H135) -> #REF! | I137: =SUM(I10:I135) -> 0 | J137: =SUM(J10:J135) -> 0

Sheet Draw #3
A1: GENESIS CAPITAL DRAW FORM
B3: CLIENT: | C3: ='SCHEDULE OF VALUE WORKSHEET'!$B$3 -> Angeleno Investments | I3: TOTAL COMPLETED TO DATE: | J3: =SUM(J137) -> 0 | K3: =SUM(J3)/J7 -> #REF!
B4: DATE: | C4: =TODAY() -> 45978 | I4: REMAINING $ IN BUDGET: | J4: =SUM(H137) -> #REF!
B5: PROJECT: | C5: ='SCHEDULE OF VALUE WORKSHEET'!B5 -> 10910 Huston Street | I5: ORIGINAL SCHEDULE OF VALUES: | J5: =SUM(D137) -> #REF!
B6: DRAW REQUEST: | C6: =SUM(I137) -> 0 | I6: CHANGE ORDERS: | J6: =SUM(F137) -> 0
I7: REVISED SCHEDULE OF VALUES: | J7: =SUM(G137) -> #REF!
B8: DESCRIPTION OF WORK | D8: SCHEDULED VALUES | E8: PREVIOUS | F8: + / - CHANGES | G8: REVISED VALUES | H8: REMAINING | I8: DRAW | J8: COMPLETED AND
E9: CHANGES | H9: BUDGET | I9: 3 | J9: STORED TO DATE
A10: ='SCHEDULE OF VALUE WORKSHEET'!A7 -> 1 | B10: ='SCHEDULE OF VALUE WORKSHEET'!B7 -> SOFT COSTS | D10: =SUM('SCHEDULE OF VALUE WORKSHEET'!E7) -> 0 | E10: =SUM('Draw #2'!E10:F10) -> 0 | F10: 0 | G10: =SUM('Draw #2'!G10)+F10 -> 0 | H10: =SUM(G10-J10) -> 0 | I10: 0 | J10: =SUM(I10+'Draw #2'!J10) -> 0 | K10: =IF(J10=0,"",J10/G10)
A11: ='SCHEDULE OF VALUE WORKSHEET'!A8 -> 2 | B11: ='SCHEDULE OF VALUE WORKSHEET'!B8 -> Site Security | D11: =SUM('SCHEDULE OF VALUE WORKSHEET'!E8) -> 10580.63 | E11: =SUM('Draw #2'!E11:F11) -> 0 | F11: 0 | G11: =SUM('Draw #2'!G11)+F11 -> 10580.63 | H11: =SUM(G11-J11) -> 10580.63 | I11: 0 | J11: =SUM(I11+'Draw #2'!J11) -> 0 | K11: =IF(J11=0,"",J11/G11)
A12: ='SCHEDULE OF VALUE WORKSHEET'!A9 -> 3 | B12: ='SCHEDULE OF VALUE WORKSHEET'!B9 -> Soils Inspection | D12: =SUM('SCHEDULE OF VALUE WORKSHEET'!E9) -> 0 | E12: =SUM('Draw #2'!E12:F12) -> 0 | F12: 0 | G12: =SUM('Draw #2'!G12)+F12 -> 0 | H12: =SUM(G12-J12) -> 0 | I12: 0 | J12: =SUM(I12+'Draw #2'!J12) -> 0 | K12: =IF(J12=0,"",J12/G12)
A13: ='SCHEDULE OF VALUE WORKSHEET'!A10 -> 4 | B13: ='SCHEDULE OF VALUE WORKSHEET'!B10 -> Offsites (Transformer) | D13: =SUM('SCHEDULE OF VALUE WORKSHEET'!E10) -> 20000 | E13: =SUM('Draw #2'!E13:F13) -> 0 | F13: 0 | G13: =SUM('Draw #2'!G13)+F13 -> 20000 | H13: =SUM(G13-J13) -> 20000 | I13: 0 | J13: =SUM(I13+'Draw #2'!J13) -> 0 | K13: =IF(J13=0,"",J13/G13)
A14: ='SCHEDULE OF VALUE WORKSHEET'!A11 -> 5 | B14: ='SCHEDULE OF VALUE WORKSHEET'!B11 -> Plan Check Fees | D14: =SUM('SCHEDULE OF VALUE WORKSHEET'!E11) -> 0 | E14: =SUM('Draw #2'!E14:F14) -> 0 | F14: 0 | G14: =SUM('Draw #2'!G14)+F14 -> 0 | H14: =SUM(G14-J14) -> 0 | I14: 0 | J14: =SUM(I14+'Draw #2'!J14) -> 0 | K14: =IF(J14=0,"",J14/G14)
A15: ='SCHEDULE OF VALUE WORKSHEET'!A12 -> 6 | B15: ='SCHEDULE OF VALUE WORKSHEET'!B12 -> Permits | D15: =SUM('SCHEDULE OF VALUE WORKSHEET'!E12) -> 0 | E15: =SUM('Draw #2'!E15:F15) -> 0 | F15: 0 | G15: =SUM('Draw #2'!G15)+F15 -> 0 | H15: =SUM(G15-J15) -> 0 | I15: 0 | J15: =SUM(I15+'Draw #2'!J15) -> 0 | K15: =IF(J15=0,"",J15/G15)
A16: ='SCHEDULE OF VALUE WORKSHEET'!A13 -> 7 | B16: ='SCHEDULE OF VALUE WORKSHEET'!B13 -> Survey | D16: =SUM('SCHEDULE OF VALUE WORKSHEET'!E13) -> 0 | E16: =SUM('Draw #2'!E16:F16) -> 0 | F16: 0 | G16: =SUM('Draw #2'!G16)+F16 -> 0 | H16: =SUM(G16-J16) -> 0 | I16: 0 | J16: =SUM(I16+'Draw #2'!J16) -> 0 | K16: =IF(J16=0,"",J16/G16)
A17: ='SCHEDULE OF VALUE WORKSHEET'!A14 -> 8 | B17: ='SCHEDULE OF VALUE WORKSHEET'!B14 -> Soils Engineer | D17: =SUM('SCHEDULE OF VALUE WORKSHEET'!E14) -> 0 | E17: =SUM('Draw #2'!E17:F17) -> 0 | F17: 0 | G17: =SUM('Draw #2'!G17)+F17 -> 0 | H17: =SUM(G17-J17) -> 0 | I17: 0 | J17: =SUM(I17+'Draw #2'!J17) -> 0 | K17: =IF(J17=0,"",J17/G17)
A18: ='SCHEDULE OF VALUE WORKSHEET'!A15 -> 9 | B18: ='SCHEDULE OF VALUE WORKSHEET'!B15 -> Soils Permit + T24 | D18: =SUM('SCHEDULE OF VALUE WORKSHEET'!E15) -> 2500 | E18: =SUM('Draw #2'!E18:F18) -> 0 | F18: 0 | G18: =SUM('Draw #2'!G18)+F18 -> 2500 | H18: =SUM(G18-J18) -> 2500 | I18: 0 | J18: =SUM(I18+'Draw #2'!J18) -> 0 | K18: =IF(J18=0,"",J18/G18)
A19: ='SCHEDULE OF VALUE WORKSHEET'!A16 -> 10 | B19: ='SCHEDULE OF VALUE WORKSHEET'!B16 -> Special Inspections - Deputy | D19: =SUM('SCHEDULE OF VALUE WORKSHEET'!E16) -> 15000 | E19: =SUM('Draw #2'!E19:F19) -> 0 | F19: 0 | G19: =SUM('Draw #2'!G19)+F19 -> 15000 | H19: =SUM(G19-J19) -> 15000 | I19: 0 | J19: =SUM(I19+'Draw #2'!J19) -> 0 | K19: =IF(J19=0,"",J19/G19)
A20: ='SCHEDULE OF VALUE WORKSHEET'!A17 -> 11 | B20: ='SCHEDULE OF VALUE WORKSHEET'!B17 -> Architect | D20: =SUM('SCHEDULE OF VALUE WORKSHEET'!E17) -> 0 | E20: =SUM('Draw #2'!E20:F20) -> 0 | F20: 0 | G20: =SUM('Draw #2'!G20)+F20 -> 0 | H20: =SUM(G20-J20) -> 0 | I20: 0 | J20: =SUM(I20+'Draw #2'!J20) -> 0 | K20: =IF(J20=0,"",J20/G20)
A21: ='SCHEDULE OF VALUE WORKSHEET'!A18 -> 12 | B21: ='SCHEDULE OF VALUE WORKSHEET'!B18 -> Structural Engineer | D21: =SUM('SCHEDULE OF VALUE WORKSHEET'!E18) -> 0 | E21: =SUM('Draw #2'!E21:F21) -> 0 | F21: 0 | G21: =SUM('Draw #2'!G21)+F21 -> 0 | H21: =SUM(G21-J21) -> 0 | I21: 0 | J21: =SUM(I21+'Draw #2'!J21) -> 0 | K21: =IF(J21=0,"",J21/G21)
... A45: ='SCHEDULE OF VALUE WORKSHEET'!A42 -> 36 | B45: ='SCHEDULE OF VALUE WORKSHEET'!B42 -> Construction Management / Observation (OO) | D45: =SUM('SCHEDULE OF VALUE WORKSHEET'!E42) -> 49427.9 | E45: =SUM('Draw #2'!E45:F45) -> 0 | F45: 0 | G45: =SUM('Draw #2'!G45)+F45 -> 49427.9 | H45: =SUM(G45-J45) -> 49427.9 | I45: 0 | J45: =SUM(I45+'Draw #2'!J45) -> 0 | K45: =IF(J45=0,"",J45/G45)
A46: ='SCHEDULE OF VALUE WORKSHEET'!#REF! -> #REF! | B46: ='SCHEDULE OF VALUE WORKSHEET'!#REF! -> #REF! | D46: =SUM('SCHEDULE OF VALUE WORKSHEET'!#REF!) -> #REF! | E46: =SUM('Draw #2'!E46:F46) -> 0 | F46: 0 | G46: =SUM('Draw #2'!G46)+F46 -> #REF! | H46: =SUM(G46-J46) -> #REF! | I46: 0 | J46: =SUM(I46+'Draw #2'!J46) -> 0 | K46: =IF(J46=0,"",J46/G46)
A47: ='SCHEDULE OF VALUE WORKSHEET'!A43 -> 37 | B47: ='SCHEDULE OF VALUE WORKSHEET'!B43 -> CMFA Startup Fee | D47: =SUM('SCHEDULE OF VALUE WORKSHEET'!E43) -> 22800 | E47: =SUM('Draw #2'!E47:F47) -> 0 | F47: 0 | G47: =SUM('Draw #2'!G47)+F47 -> 22800 | H47: =SUM(G47-J47) -> 22800 | I47: 0 | J47: =SUM(I47+'Draw #2'!J47) -> 0 | K47: =IF(J47=0,"",J47/G47)
A48: ='SCHEDULE OF VALUE WORKSHEET'!A44 -> 38 | B48: ='SCHEDULE OF VALUE WORKSHEET'!B44 -> Non-Profit Start Up Fee | D48: =SUM('SCHEDULE OF VALUE WORKSHEET'!E44) -> 25000 | E48: =SUM('Draw #2'!E48:F48) -> 0 | F48: 0 | G48: =SUM('Draw #2'!G48)+F48 -> 25000 | H48: =SUM(G48-J48) -> 25000 | I48: 0 | J48: =SUM(I48+'Draw #2'!J48) -> 0 | K48: =IF(J48=0,"",J48/G48)
A49: ='SCHEDULE OF VALUE WORKSHEET'!A45 -> 39 | B49: ='SCHEDULE OF VALUE WORKSHEET'!B45 -> CMFA Construction Fee | D49: =SUM('SCHEDULE OF VALUE WORKSHEET'!E45) -> 12000 | E49: =SUM('Draw #2'!E49:F49) -> 0 | F49: 0 | G49: =SUM('Draw #2'!G49)+F49 -> 12000 | H49: =SUM(G49-J49) -> 12000 | I49: 0 | J49: =SUM(I49+'Draw #2'!J49) -> 0 | K49: =IF(J49=0,"",J49/G49)
A50: ='SCHEDULE OF VALUE WORKSHEET'!A46 -> 40 | B50: ='SCHEDULE OF VALUE WORKSHEET'!B46 -> Non-Profit Construction Fee | D50: =SUM('SCHEDULE OF VALUE WORKSHEET'!E46) -> 10000 | E50: =SUM('Draw #2'!E50:F50) -> 0 | F50: 0 | G50: =SUM('Draw #2'!G50)+F50 -> 10000 | H50: =SUM(G50-J50) -> 10000 | I50: 0 | J50: =SUM(I50+'Draw #2'!J50) -> 0 | K50: =IF(J50=0,"",J50/G50)
A51: ='SCHEDULE OF VALUE WORKSHEET'!A47 -> 41 | B51: ='SCHEDULE OF VALUE WORKSHEET'!B47 -> WTE Legal Costs for CMFA & Non-Profit Partner | D51: =SUM('SCHEDULE OF VALUE WORKSHEET'!E47) -> 20000 | E51: =SUM('Draw #2'!E51:F51) -> 0 | F51: 0 | G51: =SUM('Draw #2'!G51)+F51 -> 20000 | H51: =SUM(G51-J51) -> 20000 | I51: 0 | J51: =SUM(I51+'Draw #2'!J51) -> 0 | K51: =IF(J51=0,"",J51/G51)
A52: ='SCHEDULE OF VALUE WORKSHEET'!#REF! -> #REF! | B52: ='SCHEDULE OF VALUE WORKSHEET'!#REF! -> #REF! | D52: =SUM('SCHEDULE OF VALUE WORKSHEET'!#REF!) -> #REF! | E52: =SUM('Draw #2'!E52:F52) -> 0 | F52: 0 | G52: =SUM('Draw #2'!G52)+F52 -> #REF! | H52: =SUM(G52-J52) -> #REF! | I52: 0 | J52: =SUM(I52+'Draw #2'!J52) -> 0 | K52: =IF(J52=0,"",J52/G52)
A53: ='SCHEDULE OF VALUE WORKSHEET'!A49 -> 43 | B53: ='SCHEDULE OF VALUE WORKSHEET'!B49 -> GENERAL CONDITIONS | D53: =SUM('SCHEDULE OF VALUE WORKSHEET'!E49) -> 362115.24 | E53: =SUM('Draw #2'!E53:F53) -> 0 | F53: 0 | G53: =SUM('Draw #2'!G53)+F53 -> 362115.24 | H53: =SUM(G53-J53) -> 362115.24 | I53: 0 | J53: =SUM(I53+'Draw #2'!J53) -> 0 | K53: =IF(J53=0,"",J53/G53)
A54: ='SCHEDULE OF VALUE WORKSHEET'!A50 -> 44 | B54: ='SCHEDULE OF VALUE WORKSHEET'!B50 -> GENERAL REQUIREMENT | D54: =SUM('SCHEDULE OF VALUE WORKSHEET'!E50) -> 124657.88 | E54: =SUM('Draw #2'!E54:F54) -> 0 | F54: 0 | G54: =SUM('Draw #2'!G54)+F54 -> 124657.88 | H54: =SUM(G54-J54) -> 124657.88 | I54: 0 | J54: =SUM(I54+'Draw #2'!J54) -> 0 | K54: =IF(J54=0,"",J54/G54)
A55: ='SCHEDULE OF VALUE WORKSHEET'!A51 -> 45 | B55: ='SCHEDULE OF VALUE WORKSHEET'!B51 -> SITE WORK | D55: =SUM('SCHEDULE OF VALUE WORKSHEET'!E51) -> 139049.51 | E55: =SUM('Draw #2'!E55:F55) -> 0 | F55: 0 | G55: =SUM('Draw #2'!G55)+F55 -> 139049.51 | H55: =SUM(G55-J55) -> 139049.51 | I55: 0 | J55: =SUM(I55+'Draw #2'!J55) -> 0 | K55: =IF(J55=0,"",J55/G55)
A56: ='SCHEDULE OF VALUE WORKSHEET'!A52 -> 46 | B56: ='SCHEDULE OF VALUE WORKSHEET'!B52 -> CONCRETE | D56: =SUM('SCHEDULE OF VALUE WORKSHEET'!E52) -> 253182 | E56: =SUM('Draw #2'!E56:F56) -> 0 | F56: 0 | G56: =SUM('Draw #2'!G56)+F56 -> 253182 | H56: =SUM(G56-J56) -> 253182 | I56: 0 | J56: =SUM(I56+'Draw #2'!J56) -> 0 | K56: =IF(J56=0,"",J56/G56)
A57: ='SCHEDULE OF VALUE WORKSHEET'!A53 -> 47 | B57: ='SCHEDULE OF VALUE WORKSHEET'!B53 -> MASONRY | D57: =SUM('SCHEDULE OF VALUE WORKSHEET'!E53) -> 3562.64 | E57: =SUM('Draw #2'!E57:F57) -> 0 | F57: 0 | G57: =SUM('Draw #2'!G57)+F57 -> 3562.64 | H57: =SUM(G57-J57) -> 3562.64 | I57: 0 | J57: =SUM(I57+'Draw #2'!J57) -> 0 | K57: =IF(J57=0,"",J57/G57)
A58: ='SCHEDULE OF VALUE WORKSHEET'!A54 -> 48 | B58: ='SCHEDULE OF VALUE WORKSHEET'!B54 -> METALS | D58: =SUM('SCHEDULE OF VALUE WORKSHEET'!E54) -> 324100 | E58: =SUM('Draw #2'!E58:F58) -> 0 | F58: 0 | G58: =SUM('Draw #2'!G58)+F58 -> 324100 | H58: =SUM(G58-J58) -> 324100 | I58: 0 | J58: =SUM(I58+'Draw #2'!J58) -> 0 | K58: =IF(J58=0,"",J58/G58)
A59: ='SCHEDULE OF VALUE WORKSHEET'!A55 -> 49 | B59: ='SCHEDULE OF VALUE WORKSHEET'!B55 -> FRAMING | D59: =SUM('SCHEDULE OF VALUE WORKSHEET'!E55) -> 818554 | E59: =SUM('Draw #2'!E59:F59) -> 0 | F59: 0 | G59: =SUM('Draw #2'!G59)+F59 -> 818554 | H59: =SUM(G59-J59) -> 818554 | I59: 0 | J59: =SUM(I59+'Draw #2'!J59) -> 0 | K59: =IF(J59=0,"",J59/G59)
A60: ='SCHEDULE OF VALUE WORKSHEET'!A56 -> 50 | B60: ='SCHEDULE OF VALUE WORKSHEET'!B56 -> COUNTERTOPS | D60: =SUM('SCHEDULE OF VALUE WORKSHEET'!E56) -> 56930 | E60: =SUM('Draw #2'!E60:F60) -> 0 | F60: 0 | G60: =SUM('Draw #2'!G60)+F60 -> 56930 | H60: =SUM(G60-J60) -> 56930 | I60: 0 | J60: =SUM(I60+'Draw #2'!J60) -> 0 | K60: =IF(J60=0,"",J60/G60)
A61: ='SCHEDULE OF VALUE WORKSHEET'!A57 -> 51 | B61: ='SCHEDULE OF VALUE WORKSHEET'!B57 -> CABINETS | D61: =SUM('SCHEDULE OF VALUE WORKSHEET'!E57) -> 56930 | E61: =SUM('Draw #2'!E61:F61) -> 0 | F61: 0 | G61: =SUM('Draw #2'!G61)+F61 -> 56930 | H61: =SUM(G61-J61) -> 56930 | I61: 0 | J61: =SUM(I61+'Draw #2'!J61) -> 0 | K61: =IF(J61=0,"",J61/G61)
A62: ='SCHEDULE OF VALUE WORKSHEET'!A58 -> 52 | B62: ='SCHEDULE OF VALUE WORKSHEET'!B58 -> THERMAL MOISTURE PROTECTION | D62: =SUM('SCHEDULE OF VALUE WORKSHEET'!E58) -> 173148 | E62: =SUM('Draw #2'!E62:F62) -> 0 | F62: 0 | G62: =SUM('Draw #2'!G62)+F62 -> 173148 | H62: =SUM(G62-J62) -> 173148 | I62: 0 | J62: =SUM(I62+'Draw #2'!J62) -> 0 | K62: =IF(J62=0,"",J62/G62)
A63: ='SCHEDULE OF VALUE WORKSHEET'!A59 -> 53 | B63: ='SCHEDULE OF VALUE WORKSHEET'!B59 -> DOORS | D63: =SUM('SCHEDULE OF VALUE WORKSHEET'!E59) -> 204087.33 | E63: =SUM('Draw #2'!E63:F63) -> 0 | F63: 0 | G63: =SUM('Draw #2'!G63)+F63 -> 204087.33 | H63: =SUM(G63-J63) -> 204087.33 | I63: 0 | J63: =SUM(I63+'Draw #2'!J63) -> 0 | K63: =IF(J63=0,"",J63/G63)
A64: ='SCHEDULE OF VALUE WORKSHEET'!A60 -> 54 | B64: ='SCHEDULE OF VALUE WORKSHEET'!B60 -> WINDOWS | D64: =SUM('SCHEDULE OF VALUE WORKSHEET'!E60) -> 106274.25 | E64: =SUM('Draw #2'!E64:F64) -> 0 | F64: 0 | G64: =SUM('Draw #2'!G64)+F64 -> 106274.25 | H64: =SUM(G64-J64) -> 106274.25 | I64: 0 | J64: =SUM(I64+'Draw #2'!J64) -> 0 | K64: =IF(J64=0,"",J64/G64)
... A90: ='SCHEDULE OF VALUE WORKSHEET'!A86 -> 80 | B90: ='SCHEDULE OF VALUE WORKSHEET'!B86 -> FINANCING COSTS | D90: =SUM('SCHEDULE OF VALUE WORKSHEET'!E86) -> 0 | E90: =SUM('Draw #2'!E90:F90) -> 0 | F90: 0 | G90: =SUM('Draw #2'!G90)+F90 -> 0 | H90: =SUM(G90-J90) -> 0 | I90: 0 | J90: =SUM(I90+'Draw #2'!J90) -> 0 | K90: =IF(J90=0,"",J90/G90)
A91: ='SCHEDULE OF VALUE WORKSHEET'!#REF! -> #REF! | B91: ='SCHEDULE OF VALUE WORKSHEET'!#REF! -> #REF! | D91: =SUM('SCHEDULE OF VALUE WORKSHEET'!#REF!) -> #REF! | E91: =SUM('Draw #2'!E91:F91) -> 0 | F91: 0 | G91: =SUM('Draw #2'!G91)+F91 -> #REF! | H91: =SUM(G91-J91) -> #REF! | I91: 0 | J91: =SUM(I91+'Draw #2'!J91) -> 0 | K91: =IF(J91=0,"",J91/G91)
A92: ='SCHEDULE OF VALUE WORKSHEET'!#REF! -> #REF! | B92: ='SCHEDULE OF VALUE WORKSHEET'!#REF! -> #REF! | D92: =SUM('SCHEDULE OF VALUE WORKSHEET'!#REF!) -> #REF! | E92: =SUM('Draw #2'!E92:F92) -> 0 | F92: 0 | G92: =SUM('Draw #2'!G92)+F92 -> #REF! | H92: =SUM(G92-J92) -> #REF! | I92: 0 | J92: =SUM(I92+'Draw #2'!J92) -> 0 | K92: =IF(J92=0,"",J92/G92)
A93: ='SCHEDULE OF VALUE WORKSHEET'!#REF! -> #REF! | B93: ='SCHEDULE OF VALUE WORKSHEET'!#REF! -> #REF! | D93: =SUM('SCHEDULE OF VALUE WORKSHEET'!#REF!) -> #REF! | E93: =SUM('Draw #2'!E93:F93) -> 0 | F93: 0 | G93: =SUM('Draw #2'!G93)+F93 -> #REF! | H93: =SUM(G93-J93) -> #REF! | I93: 0 | J93: =SUM(I93+'Draw #2'!J93) -> 0 | K93: =IF(J93=0,"",J93/G93)
A94: ='SCHEDULE OF VALUE WORKSHEET'!#REF! -> #REF! | B94: ='SCHEDULE OF VALUE WORKSHEET'!#REF! -> #REF! | D94: =SUM('SCHEDULE OF VALUE WORKSHEET'!#REF!) -> #REF! | E94: =SUM('Draw #2'!E94:F94) -> 0 | F94: 0 | G94: =SUM('Draw #2'!G94)+F94 -> #REF! | H94: =SUM(G94-J94) -> #REF! | I94: 0 | J94: =SUM(I94+'Draw #2'!J94) -> 0 | K94: =IF(J94=0,"",J94/G94)
A95: ='SCHEDULE OF VALUE WORKSHEET'!#REF! -> #REF! | B95: ='SCHEDULE OF VALUE WORKSHEET'!#REF! -> #REF! | D95: =SUM('SCHEDULE OF VALUE WORKSHEET'!#REF!) -> #REF! | E95: =SUM('Draw #2'!E95:F95) -> 0 | F95: 0 | G95: =SUM('Draw #2'!G95)+F95 -> #REF! | H95: =SUM(G95-J95) -> #REF! | I95: 0 | J95: =SUM(I95+'Draw #2'!J95) -> 0 | K95: =IF(J95=0,"",J95/G95)
A96: ='SCHEDULE OF VALUE WORKSHEET'!#REF! -> #REF! | B96: ='SCHEDULE OF VALUE WORKSHEET'!#REF! -> #REF! | D96: =SUM('SCHEDULE OF VALUE WORKSHEET'!#REF!) -> #REF! | E96: =SUM('Draw #2'!E96:F96) -> 0 | F96: 0 | G96: =SUM('Draw #2'!G96)+F96 -> #REF! | H96: =SUM(G96-J96) -> #REF! | I96: 0 | J96: =SUM(I96+'Draw #2'!J96) -> 0 | K96: =IF(J96=0,"",J96/G96)
A97: ='SCHEDULE OF VALUE WORKSHEET'!#REF! -> #REF! | B97: ='SCHEDULE OF VALUE WORKSHEET'!#REF! -> #REF! | D97: =SUM('SCHEDULE OF VALUE WORKSHEET'!#REF!) -> #REF! | E97: =SUM('Draw #2'!E97:F97) -> 0 | F97: 0 | G97: =SUM('Draw #2'!G97)+F97 -> #REF! | H97: =SUM(G97-J97) -> #REF! | I97: 0 | J97: =SUM(I97+'Draw #2'!J97) -> 0 | K97: =IF(J97=0,"",J97/G97)
A98: ='SCHEDULE OF VALUE WORKSHEET'!#REF! -> #REF! | B98: ='SCHEDULE OF VALUE WORKSHEET'!#REF! -> #REF! | D98: =SUM('SCHEDULE OF VALUE WORKSHEET'!#REF!) -> #REF! | E98: =SUM('Draw #2'!E98:F98) -> 0 | F98: 0 | G98: =SUM('Draw #2'!G98)+F98 -> #REF! | H98: =SUM(G98-J98) -> #REF! | I98: 0 | J98: =SUM(I98+'Draw #2'!J98) -> 0 | K98: =IF(J98=0,"",J98/G98)
A99: ='SCHEDULE OF VALUE WORKSHEET'!#REF! -> #REF! | B99: ='SCHEDULE OF VALUE WORKSHEET'!#REF! -> #REF! | D99: =SUM('SCHEDULE OF VALUE WORKSHEET'!#REF!) -> #REF! | E99: =SUM('Draw #2'!E99:F99) -> 0 | F99: 0 | G99: =SUM('Draw #2'!G99)+F99 -> #REF! | H99: =SUM(G99-J99) -> #REF! | I99: 0 | J99: =SUM(I99+'Draw #2'!J99) -> 0 | K99: =IF(J99=0,"",J99/G99)
A100: ='SCHEDULE OF VALUE WORKSHEET'!#REF! -> #REF! | B100: ='SCHEDULE OF VALUE WORKSHEET'!#REF! -> #REF! | D100: =SUM('SCHEDULE OF VALUE WORKSHEET'!#REF!) -> #REF! | E100: =SUM('Draw #2'!E100:F100) -> 0 | F100: 0 | G100: =SUM('Draw #2'!G100)+F100 -> #REF! | H100: =SUM(G100-J100) -> #REF! | I100: 0 | J100: =SUM(I100+'Draw #2'!J100) -> 0 | K100: =IF(J100=0,"",J100/G100)
A101: ='SCHEDULE OF VALUE WORKSHEET'!#REF! -> #REF! | B101: ='SCHEDULE OF VALUE WORKSHEET'!#REF! -> #REF! | D101: =SUM('SCHEDULE OF VALUE WORKSHEET'!#REF!) -> #REF! | E101: =SUM('Draw #2'!E101:F101) -> 0 | F101: 0 | G101: =SUM('Draw #2'!G101)+F101 -> #REF! | H101: =SUM(G101-J101) -> #REF! | I101: 0 | J101: =SUM(I101+'Draw #2'!J101) -> 0 | K101: =IF(J101=0,"",J101/G101)
A102: ='SCHEDULE OF VALUE WORKSHEET'!#REF! -> #REF! | B102: ='SCHEDULE OF VALUE WORKSHEET'!#REF! -> #REF! | D102: =SUM('SCHEDULE OF VALUE WORKSHEET'!#REF!) -> #REF! | E102: =SUM('Draw #2'!E102:F102) -> 0 | F102: 0 | G102: =SUM('Draw #2'!G102)+F102 -> #REF! | H102: =SUM(G102-J102) -> #REF! | I102: 0 | J102: =SUM(I102+'Draw #2'!J102) -> 0 | K102: =IF(J102=0,"",J102/G102)
... A116: ='SCHEDULE OF VALUE WORKSHEET'!#REF! -> #REF! | B116: ='SCHEDULE OF VALUE WORKSHEET'!#REF! -> #REF! | D116: =SUM('SCHEDULE OF VALUE WORKSHEET'!#REF!) -> #REF! | E116: =SUM('Draw #2'!E116:F116) -> 0 | F116: 0 | G116: =SUM('Draw #2'!G116)+F116 -> #REF! | H116: =SUM(G116-J116) -> #REF! | I116: 0 | J116: =SUM(I116+'Draw #2'!J116) -> 0 | K116: =IF(J116=0,"",J116/G116)
A117: ='SCHEDULE OF VALUE WORKSHEET'!A87 -> 82 | B117: ='SCHEDULE OF VALUE WORKSHEET'!B87 -> Open Item | D117: =SUM('SCHEDULE OF VALUE WORKSHEET'!E87) -> 0 | E117: =SUM('Draw #2'!E117:F117) -> 0 | F117: 0 | G117: =SUM('Draw #2'!G117)+F117 -> 0 | H117: =SUM(G117-J117) -> 0 | I117: 0 | J117: =SUM(I117+'Draw #2'!J117) -> 0 | K117: =IF(J117=0,"",J117/G117)
A118: ='SCHEDULE OF VALUE WORKSHEET'!A88 -> 83 | B118: ='SCHEDULE OF VALUE WORKSHEET'!B88 -> Open Item | D118: =SUM('SCHEDULE OF VALUE WORKSHEET'!E88) -> 0 | E118: =SUM('Draw #2'!E118:F118) -> 0 | F118: 0 | G118: =SUM('Draw #2'!G118)+F118 -> 0 | H118: =SUM(G118-J118) -> 0 | I118: 0 | J118: =SUM(I118+'Draw #2'!J118) -> 0 | K118: =IF(J118=0,"",J118/G118)
A119: ='SCHEDULE OF VALUE WORKSHEET'!A89 -> 84 | B119: ='SCHEDULE OF VALUE WORKSHEET'!B89 -> Open Item | D119: =SUM('SCHEDULE OF VALUE WORKSHEET'!E89) -> 0 | E119: =SUM('Draw #2'!E119:F119) -> 0 | F119: 0 | G119: =SUM('Draw #2'!G119)+F119 -> 0 | H119: =SUM(G119-J119) -> 0 | I119: 0 | J119: =SUM(I119+'Draw #2'!J119) -> 0 | K119: =IF(J119=0,"",J119/G119)
A120: ='SCHEDULE OF VALUE WORKSHEET'!A90 -> 85 | B120: ='SCHEDULE OF VALUE WORKSHEET'!B90 -> Open Item | D120: =SUM('SCHEDULE OF VALUE WORKSHEET'!E90) -> 0 | E120: =SUM('Draw #2'!E120:F120) -> 0 | F120: 0 | G120: =SUM('Draw #2'!G120)+F120 -> 0 | H120: =SUM(G120-J120) -> 0 | I120: 0 | J120: =SUM(I120+'Draw #2'!J120) -> 0 | K120: =IF(J120=0,"",J120/G120)
A121: ='SCHEDULE OF VALUE WORKSHEET'!A91 -> 86 | B121: ='SCHEDULE OF VALUE WORKSHEET'!B91 -> Open Item | D121: =SUM('SCHEDULE OF VALUE WORKSHEET'!E91) -> 0 | E121: =SUM('Draw #2'!E121:F121) -> 0 | F121: 0 | G121: =SUM('Draw #2'!G121)+F121 -> 0 | H121: =SUM(G121-J121) -> 0 | I121: 0 | J121: =SUM(I121+'Draw #2'!J121) -> 0 | K121: =IF(J121=0,"",J121/G121)
A122: ='SCHEDULE OF VALUE WORKSHEET'!A92 -> 87 | B122: ='SCHEDULE OF VALUE WORKSHEET'!B92 -> Open Item | D122: =SUM('SCHEDULE OF VALUE WORKSHEET'!E92) -> 0 | E122: =SUM('Draw #2'!E122:F122) -> 0 | F122: 0 | G122: =SUM('Draw #2'!G122)+F122 -> 0 | H122: =SUM(G122-J122) -> 0 | I122: 0 | J122: =SUM(I122+'Draw #2'!J122) -> 0 | K122: =IF(J122=0,"",J122/G122)
A123: ='SCHEDULE OF VALUE WORKSHEET'!A93 -> 88 | B123: ='SCHEDULE OF VALUE WORKSHEET'!B93 -> Open Item | D123: =SUM('SCHEDULE OF VALUE WORKSHEET'!E93) -> 0 | E123: =SUM('Draw #2'!E123:F123) -> 0 | F123: 0 | G123: =SUM('Draw #2'!G123)+F123 -> 0 | H123: =SUM(G123-J123) -> 0 | I123: 0 | J123: =SUM(I123+'Draw #2'!J123) -> 0 | K123: =IF(J123=0,"",J123/G123)
A124: ='SCHEDULE OF VALUE WORKSHEET'!A94 -> 89 | B124: ='SCHEDULE OF VALUE WORKSHEET'!B94 -> Open Item | D124: =SUM('SCHEDULE OF VALUE WORKSHEET'!E94) -> 0 | E124: =SUM('Draw #2'!E124:F124) -> 0 | F124: 0 | G124: =SUM('Draw #2'!G124)+F124 -> 0 | H124: =SUM(G124-J124) -> 0 | I124: 0 | J124: =SUM(I124+'Draw #2'!J124) -> 0 | K124: =IF(J124=0,"",J124/G124)
A125: ='SCHEDULE OF VALUE WORKSHEET'!A95 -> 90 | B125: ='SCHEDULE OF VALUE WORKSHEET'!B95 -> Open Item | D125: =SUM('SCHEDULE OF VALUE WORKSHEET'!E95) -> 0 | E125: =SUM('Draw #2'!E125:F125) -> 0 | F125: 0 | G125: =SUM('Draw #2'!G125)+F125 -> 0 | H125: =SUM(G125-J125) -> 0 | I125: 0 | J125: =SUM(I125+'Draw #2'!J125) -> 0 | K125: =IF(J125=0,"",J125/G125)
A126: ='SCHEDULE OF VALUE WORKSHEET'!A96 -> 91 | B126: ='SCHEDULE OF VALUE WORKSHEET'!B96 -> Open Item | D126: =SUM('SCHEDULE OF VALUE WORKSHEET'!E96) -> 0 | E126: =SUM('Draw #2'!E126:F126) -> 0 | F126: 0 | G126: =SUM('Draw #2'!G126)+F126 -> 0 | H126: =SUM(G126-J126) -> 0 | I126: 0 | J126: =SUM(I126+'Draw #2'!J126) -> 0 | K126: =IF(J126=0,"",J126/G126)
A127: ='SCHEDULE OF VALUE WORKSHEET'!A97 -> 92 | B127: ='SCHEDULE OF VALUE WORKSHEET'!B97 -> Open Item | D127: =SUM('SCHEDULE OF VALUE WORKSHEET'!E97) -> 0 | E127: =SUM('Draw #2'!E127:F127) -> 0 | F127: 0 | G127: =SUM('Draw #2'!G127)+F127 -> 0 | H127: =SUM(G127-J127) -> 0 | I127: 0 | J127: =SUM(I127+'Draw #2'!J127) -> 0 | K127: =IF(J127=0,"",J127/G127)
A128: ='SCHEDULE OF VALUE WORKSHEET'!A98 -> 93 | B128: ='SCHEDULE OF VALUE WORKSHEET'!B98 -> Open Item | D128: =SUM('SCHEDULE OF VALUE WORKSHEET'!E98) -> 0 | E128: =SUM('Draw #2'!E128:F128) -> 0 | F128: 0 | G128: =SUM('Draw #2'!G128)+F128 -> 0 | H128: =SUM(G128-J128) -> 0 | I128: 0 | J128: =SUM(I128+'Draw #2'!J128) -> 0 | K128: =IF(J128=0,"",J128/G128)
... A134: ='SCHEDULE OF VALUE WORKSHEET'!A104 -> 99 | B134: ='SCHEDULE OF VALUE WORKSHEET'!B104 -> Open Item | D134: =SUM('SCHEDULE OF VALUE WORKSHEET'!E104) -> 0 | E134: =SUM('Draw #2'!E134:F134) -> 0 | F134: 0 | G134: =SUM('Draw #2'!G134)+F134 -> 0 | H134: =SUM(G134-J134) -> 0 | I134: 0 | J134: =SUM(I134+'Draw #2'!J134) -> 0 | K134: =IF(J134=0,"",J134/G134)
A135: ='SCHEDULE OF VALUE WORKSHEET'!#REF! -> #REF! | B135: ='SCHEDULE OF VALUE WORKSHEET'!#REF! -> #REF! | D135: =SUM('SCHEDULE OF VALUE WORKSHEET'!#REF!) -> #REF! | E135: =SUM('Draw #2'!E135:F135) -> 0 | F135: 0 | G135: =SUM('Draw #2'!G135)+F135 -> #REF! | H135: =SUM(G135-J135) -> #REF! | I135: 0 | J135: =SUM(I135+'Draw #2'!J135) -> 0 | K135: =IF(J135=0,"",J135/G135)
B137: TOTAL | D137: =SUM(D10:D135) -> #REF! | E137: =SUM(E10:E135) -> 0 | F137: =SUM(F10:F135) -> 0 | G137: =SUM(G10:G135) -> #REF! | H137: =SUM(H10:H135) -> #REF! | I137: =SUM(I10:I135) -> 0 | J137: =SUM(J10:J135) -> 0

Sheet Draw #4
A1: GENESIS CAPITAL DRAW FORM
B3: CLIENT: | C3: ='SCHEDULE OF VALUE WORKSHEET'!$B$3 -> Angeleno Investments | I3: TOTAL COMPLETED TO DATE: | J3: =SUM(J137) -> 0 | K3: =SUM(J3)/J7 -> #REF!
B4: DATE: | C4: =TODAY() -> 45978 | I4: REMAINING $ IN BUDGET: | J4: =SUM(H137) -> #REF!
B5: PROJECT: | C5: ='SCHEDULE OF VALUE WORKSHEET'!B5 -> 10910 Huston Street | I5: ORIGINAL SCHEDULE OF VALUES: | J5: =SUM(D137) -> #REF!
B6: DRAW REQUEST: | C6: =SUM(I137) -> 0 | I6: CHANGE ORDERS: | J6: =SUM(F137) -> 0
I7: REVISED SCHEDULE OF VALUES: | J7: =SUM(G137) -> #REF!
B8: DESCRIPTION OF WORK | D8: SCHEDULED VALUES | E8: PREVIOUS | F8: + / - CHANGES | G8: REVISED VALUES | H8: REMAINING | I8: DRAW | J8: COMPLETED AND
E9: CHANGES | H9: BUDGET | I9: 4 | J9: STORED TO DATE
A10: ='SCHEDULE OF VALUE WORKSHEET'!A7 -> 1 | B10: ='SCHEDULE OF VALUE WORKSHEET'!B7 -> SOFT COSTS | D10: =SUM('SCHEDULE OF VALUE WORKSHEET'!E7) -> 0 | E10: =SUM('Draw #3'!E10:F10) -> 0 | F10: 0 | G10: =SUM('Draw #3'!G10)+'Draw #4'!F10 -> 0 | H10: =SUM(G10-J10) -> 0 | I10: 0 | J10: =SUM(I10+'Draw #3'!J10) -> 0 | K10: =IF(J10=0,"",J10/G10)
A11: ='SCHEDULE OF VALUE WORKSHEET'!A8 -> 2 | B11: ='SCHEDULE OF VALUE WORKSHEET'!B8 -> Site Security | D11: =SUM('SCHEDULE OF VALUE WORKSHEET'!E8) -> 10580.63 | E11: =SUM('Draw #3'!E11:F11) -> 0 | F11: 0 | G11: =SUM('Draw #3'!G11)+'Draw #4'!F11 -> 10580.63 | H11: =SUM(G11-J11) -> 10580.63 | I11: 0 | J11: =SUM(I11+'Draw #3'!J11) -> 0 | K11: =IF(J11=0,"",J11/G11)
A12: ='SCHEDULE OF VALUE WORKSHEET'!A9 -> 3 | B12: ='SCHEDULE OF VALUE WORKSHEET'!B9 -> Soils Inspection | D12: =SUM('SCHEDULE OF VALUE WORKSHEET'!E9) -> 0 | E12: =SUM('Draw #3'!E12:F12) -> 0 | F12: 0 | G12: =SUM('Draw #3'!G12)+'Draw #4'!F12 -> 0 | H12: =SUM(G12-J12) -> 0 | I12: 0 | J12: =SUM(I12+'Draw #3'!J12) -> 0 | K12: =IF(J12=0,"",J12/G12)
A13: ='SCHEDULE OF VALUE WORKSHEET'!A10 -> 4 | B13: ='SCHEDULE OF VALUE WORKSHEET'!B10 -> Offsites (Transformer) | D13: =SUM('SCHEDULE OF VALUE WORKSHEET'!E10) -> 20000 | E13: =SUM('Draw #3'!E13:F13) -> 0 | F13: 0 | G13: =SUM('Draw #3'!G13)+'Draw #4'!F13 -> 20000 | H13: =SUM(G13-J13) -> 20000 | I13: 0 | J13: =SUM(I13+'Draw #3'!J13) -> 0 | K13: =IF(J13=0,"",J13/G13)
A14: ='SCHEDULE OF VALUE WORKSHEET'!A11 -> 5 | B14: ='SCHEDULE OF VALUE WORKSHEET'!B11 -> Plan Check Fees | D14: =SUM('SCHEDULE OF VALUE WORKSHEET'!E11) -> 0 | E14: =SUM('Draw #3'!E14:F14) -> 0 | F14: 0 | G14: =SUM('Draw #3'!G14)+'Draw #4'!F14 -> 0 | H14: =SUM(G14-J14) -> 0 | I14: 0 | J14: =SUM(I14+'Draw #3'!J14) -> 0 | K14: =IF(J14=0,"",J14/G14)
A15: ='SCHEDULE OF VALUE WORKSHEET'!A12 -> 6 | B15: ='SCHEDULE OF VALUE WORKSHEET'!B12 -> Permits | D15: =SUM('SCHEDULE OF VALUE WORKSHEET'!E12) -> 0 | E15: =SUM('Draw #3'!E15:F15) -> 0 | F15: 0 | G15: =SUM('Draw #3'!G15)+'Draw #4'!F15 -> 0 | H15: =SUM(G15-J15) -> 0 | I15: 0 | J15: =SUM(I15+'Draw #3'!J15) -> 0 | K15: =IF(J15=0,"",J15/G15)
A16: ='SCHEDULE OF VALUE WORKSHEET'!A13 -> 7 | B16: ='SCHEDULE OF VALUE WORKSHEET'!B13 -> Survey | D16: =SUM('SCHEDULE OF VALUE WORKSHEET'!E13) -> 0 | E16: =SUM('Draw #3'!E16:F16) -> 0 | F16: 0 | G16: =SUM('Draw #3'!G16)+'Draw #4'!F16 -> 0 | H16: =SUM(G16-J16) -> 0 | I16: 0 | J16: =SUM(I16+'Draw #3'!J16) -> 0 | K16: =IF(J16=0,"",J16/G16)
A17: ='SCHEDULE OF VALUE WORKSHEET'!A14 -> 8 | B17: ='SCHEDULE OF VALUE WORKSHEET'!B14 -> Soils Engineer | D17: =SUM('SCHEDULE OF VALUE WORKSHEET'!E14) -> 0 | E17: =SUM('Draw #3'!E17:F17) -> 0 | F17: 0 | G17: =SUM('Draw #3'!G17)+'Draw #4'!F17 -> 0 | H17: =SUM(G17-J17) -> 0 | I17: 0 | J17: =SUM(I17+'Draw #3'!J17) -> 0 | K17: =IF(J17=0,"",J17/G17)
A18: ='SCHEDULE OF VALUE WORKSHEET'!A15 -> 9 | B18: ='SCHEDULE OF VALUE WORKSHEET'!B15 -> Soils Permit + T24 | D18: =SUM('SCHEDULE OF VALUE WORKSHEET'!E15) -> 2500 | E18: =SUM('Draw #3'!E18:F18) -> 0 | F18: 0 | G18: =SUM('Draw #3'!G18)+'Draw #4'!F18 -> 2500 | H18: =SUM(G18-J18) -> 2500 | I18: 0 | J18: =SUM(I18+'Draw #3'!J18) -> 0 | K18: =IF(J18=0,"",J18/G18)
A19: ='SCHEDULE OF VALUE WORKSHEET'!A16 -> 10 | B19: ='SCHEDULE OF VALUE WORKSHEET'!B16 -> Special Inspections - Deputy | D19: =SUM('SCHEDULE OF VALUE WORKSHEET'!E16) -> 15000 | E19: =SUM('Draw #3'!E19:F19) -> 0 | F19: 0 | G19: =SUM('Draw #3'!G19)+'Draw #4'!F19 -> 15000 | H19: =SUM(G19-J19) -> 15000 | I19: 0 | J19: =SUM(I19+'Draw #3'!J19) -> 0 | K19: =IF(J19=0,"",J19/G19)
A20: ='SCHEDULE OF VALUE WORKSHEET'!A17 -> 11 | B20: ='SCHEDULE OF VALUE WORKSHEET'!B17 -> Architect | D20: =SUM('SCHEDULE OF VALUE WORKSHEET'!E17) -> 0 | E20: =SUM('Draw #3'!E20:F20) -> 0 | F20: 0 | G20: =SUM('Draw #3'!G20)+'Draw #4'!F20 -> 0 | H20: =SUM(G20-J20) -> 0 | I20: 0 | J20: =SUM(I20+'Draw #3'!J20) -> 0 | K20: =IF(J20=0,"",J20/G20)
A21: ='SCHEDULE OF VALUE WORKSHEET'!A18 -> 12 | B21: ='SCHEDULE OF VALUE WORKSHEET'!B18 -> Structural Engineer | D21: =SUM('SCHEDULE OF VALUE WORKSHEET'!E18) -> 0 | E21: =SUM('Draw #3'!E21:F21) -> 0 | F21: 0 | G21: =SUM('Draw #3'!G21)+'Draw #4'!F21 -> 0 | H21: =SUM(G21-J21) -> 0 | I21: 0 | J21: =SUM(I21+'Draw #3'!J21) -> 0 | K21: =IF(J21=0,"",J21/G21)
... A45: ='SCHEDULE OF VALUE WORKSHEET'!A42 -> 36 | B45: ='SCHEDULE OF VALUE WORKSHEET'!B42 -> Construction Management / Observation (OO) | D45: =SUM('SCHEDULE OF VALUE WORKSHEET'!E42) -> 49427.9 | E45: =SUM('Draw #3'!E45:F45) -> 0 | F45: 0 | G45: =SUM('Draw #3'!G45)+'Draw #4'!F45 -> 49427.9 | H45: =SUM(G45-J45) -> 49427.9 | I45: 0 | J45: =SUM(I45+'Draw #3'!J45) -> 0 | K45: =IF(J45=0,"",J45/G45)
A46: ='SCHEDULE OF VALUE WORKSHEET'!#REF! -> #REF! | B46: ='SCHEDULE OF VALUE WORKSHEET'!#REF! -> #REF! | D46: =SUM('SCHEDULE OF VALUE WORKSHEET'!#REF!) -> #REF! | E46: =SUM('Draw #3'!E46:F46) -> 0 | F46: 0 | G46: =SUM('Draw #3'!G46)+'Draw #4'!F46 -> #REF! | H46: =SUM(G46-J46) -> #REF! | I46: 0 | J46: =SUM(I46+'Draw #3'!J46) -> 0 | K46: =IF(J46=0,"",J46/G46)
A47: ='SCHEDULE OF VALUE WORKSHEET'!A43 -> 37 | B47: ='SCHEDULE OF VALUE WORKSHEET'!B43 -> CMFA Startup Fee | D47: =SUM('SCHEDULE OF VALUE WORKSHEET'!E43) -> 22800 | E47: =SUM('Draw #3'!E47:F47) -> 0 | F47: 0 | G47: =SUM('Draw #3'!G47)+'Draw #4'!F47 -> 22800 | H47: =SUM(G47-J47) -> 22800 | I47: 0 | J47: =SUM(I47+'Draw #3'!J47) -> 0 | K47: =IF(J47=0,"",J47/G47)
A48: ='SCHEDULE OF VALUE WORKSHEET'!A44 -> 38 | B48: ='SCHEDULE OF VALUE WORKSHEET'!B44 -> Non-Profit Start Up Fee | D48: =SUM('SCHEDULE OF VALUE WORKSHEET'!E44) -> 25000 | E48: =SUM('Draw #3'!E48:F48) -> 0 | F48: 0 | G48: =SUM('Draw #3'!G48)+'Draw #4'!F48 -> 25000 | H48: =SUM(G48-J48) -> 25000 | I48: 0 | J48: =SUM(I48+'Draw #3'!J48) -> 0 | K48: =IF(J48=0,"",J48/G48)
A49: ='SCHEDULE OF VALUE WORKSHEET'!A45 -> 39 | B49: ='SCHEDULE OF VALUE WORKSHEET'!B45 -> CMFA Construction Fee | D49: =SUM('SCHEDULE OF VALUE WORKSHEET'!E45) -> 12000 | E49: =SUM('Draw #3'!E49:F49) -> 0 | F49: 0 | G49: =SUM('Draw #3'!G49)+'Draw #4'!F49 -> 12000 | H49: =SUM(G49-J49) -> 12000 | I49: 0 | J49: =SUM(I49+'Draw #3'!J49) -> 0 | K49: =IF(J49=0,"",J49/G49)
A50: ='SCHEDULE OF VALUE WORKSHEET'!A46 -> 40 | B50: ='SCHEDULE OF VALUE WORKSHEET'!B46 -> Non-Profit Construction Fee | D50: =SUM('SCHEDULE OF VALUE WORKSHEET'!E46) -> 10000 | E50: =SUM('Draw #3'!E50:F50) -> 0 | F50: 0 | G50: =SUM('Draw #3'!G50)+'Draw #4'!F50 -> 10000 | H50: =SUM(G50-J50) -> 10000 | I50: 0 | J50: =SUM(I50+'Draw #3'!J50) -> 0 | K50: =IF(J50=0,"",J50/G50)
A51: ='SCHEDULE OF VALUE WORKSHEET'!A47 -> 41 | B51: ='SCHEDULE OF VALUE WORKSHEET'!B47 -> WTE Legal Costs for CMFA & Non-Profit Partner | D51: =SUM('SCHEDULE OF VALUE WORKSHEET'!E47) -> 20000 | E51: =SUM('Draw #3'!E51:F51) -> 0 | F51: 0 | G51: =SUM('Draw #3'!G51)+'Draw #4'!F51 -> 20000 | H51: =SUM(G51-J51) -> 20000 | I51: 0 | J51: =SUM(I51+'Draw #3'!J51) -> 0 | K51: =IF(J51=0,"",J51/G51)
A52: ='SCHEDULE OF VALUE WORKSHEET'!#REF! -> #REF! | B52: ='SCHEDULE OF VALUE WORKSHEET'!#REF! -> #REF! | D52: =SUM('SCHEDULE OF VALUE WORKSHEET'!#REF!) -> #REF! | E52: =SUM('Draw #3'!E52:F52) -> 0 | F52: 0 | G52: =SUM('Draw #3'!G52)+'Draw #4'!F52 -> #REF! | H52: =SUM(G52-J52) -> #REF! | I52: 0 | J52: =SUM(I52+'Draw #3'!J52) -> 0 | K52: =IF(J52=0,"",J52/G52)
A53: ='SCHEDULE OF VALUE WORKSHEET'!A49 -> 43 | B53: ='SCHEDULE OF VALUE WORKSHEET'!B49 -> GENERAL CONDITIONS | D53: =SUM('SCHEDULE OF VALUE WORKSHEET'!E49) -> 362115.24 | E53: =SUM('Draw #3'!E53:F53) -> 0 | F53: 0 | G53: =SUM('Draw #3'!G53)+'Draw #4'!F53 -> 362115.24 | H53: =SUM(G53-J53) -> 362115.24 | I53: 0 | J53: =SUM(I53+'Draw #3'!J53) -> 0 | K53: =IF(J53=0,"",J53/G53)
A54: ='SCHEDULE OF VALUE WORKSHEET'!A50 -> 44 | B54: ='SCHEDULE OF VALUE WORKSHEET'!B50 -> GENERAL REQUIREMENT | D54: =SUM('SCHEDULE OF VALUE WORKSHEET'!E50) -> 124657.88 | E54: =SUM('Draw #3'!E54:F54) -> 0 | F54: 0 | G54: =SUM('Draw #3'!G54)+'Draw #4'!F54 -> 124657.88 | H54: =SUM(G54-J54) -> 124657.88 | I54: 0 | J54: =SUM(I54+'Draw #3'!J54) -> 0 | K54: =IF(J54=0,"",J54/G54)
A55: ='SCHEDULE OF VALUE WORKSHEET'!A51 -> 45 | B55: ='SCHEDULE OF VALUE WORKSHEET'!B51 -> SITE WORK | D55: =SUM('SCHEDULE OF VALUE WORKSHEET'!E51) -> 139049.51 | E55: =SUM('Draw #3'!E55:F55) -> 0 | F55: 0 | G55: =SUM('Draw #3'!G55)+'Draw #4'!F55 -> 139049.51 | H55: =SUM(G55-J55) -> 139049.51 | I55: 0 | J55: =SUM(I55+'Draw #3'!J55) -> 0 | K55: =IF(J55=0,"",J55/G55)
A56: ='SCHEDULE OF VALUE WORKSHEET'!A52 -> 46 | B56: ='SCHEDULE OF VALUE WORKSHEET'!B52 -> CONCRETE | D56: =SUM('SCHEDULE OF VALUE WORKSHEET'!E52) -> 253182 | E56: =SUM('Draw #3'!E56:F56) -> 0 | F56: 0 | G56: =SUM('Draw #3'!G56)+'Draw #4'!F56 -> 253182 | H56: =SUM(G56-J56) -> 253182 | I56: 0 | J56: =SUM(I56+'Draw #3'!J56) -> 0 | K56: =IF(J56=0,"",J56/G56)
A57: ='SCHEDULE OF VALUE WORKSHEET'!A53 -> 47 | B57: ='SCHEDULE OF VALUE WORKSHEET'!B53 -> MASONRY | D57: =SUM('SCHEDULE OF VALUE WORKSHEET'!E53) -> 3562.64 | E57: =SUM('Draw #3'!E57:F57) -> 0 | F57: 0 | G57: =SUM('Draw #3'!G57)+'Draw #4'!F57 -> 3562.64 | H57: =SUM(G57-J57) -> 3562.64 | I57: 0 | J57: =SUM(I57+'Draw #3'!J57) -> 0 | K57: =IF(J57=0,"",J57/G57)
A58: ='SCHEDULE OF VALUE WORKSHEET'!A54 -> 48 | B58: ='SCHEDULE OF VALUE WORKSHEET'!B54 -> METALS | D58: =SUM('SCHEDULE OF VALUE WORKSHEET'!E54) -> 324100 | E58: =SUM('Draw #3'!E58:F58) -> 0 | F58: 0 | G58: =SUM('Draw #3'!G58)+'Draw #4'!F58 -> 324100 | H58: =SUM(G58-J58) -> 324100 | I58: 0 | J58: =SUM(I58+'Draw #3'!J58) -> 0 | K58: =IF(J58=0,"",J58/G58)
A59: ='SCHEDULE OF VALUE WORKSHEET'!A55 -> 49 | B59: ='SCHEDULE OF VALUE WORKSHEET'!B55 -> FRAMING | D59: =SUM('SCHEDULE OF VALUE WORKSHEET'!E55) -> 818554 | E59: =SUM('Draw #3'!E59:F59) -> 0 | F59: 0 | G59: =SUM('Draw #3'!G59)+'Draw #4'!F59 -> 818554 | H59: =SUM(G59-J59) -> 818554 | I59: 0 | J59: =SUM(I59+'Draw #3'!J59) -> 0 | K59: =IF(J59=0,"",J59/G59)
A60: ='SCHEDULE OF VALUE WORKSHEET'!A56 -> 50 | B60: ='SCHEDULE OF VALUE WORKSHEET'!B56 -> COUNTERTOPS | D60: =SUM('SCHEDULE OF VALUE WORKSHEET'!E56) -> 56930 | E60: =SUM('Draw #3'!E60:F60) -> 0 | F60: 0 | G60: =SUM('Draw #3'!G60)+'Draw #4'!F60 -> 56930 | H60: =SUM(G60-J60) -> 56930 | I60: 0 | J60: =SUM(I60+'Draw #3'!J60) -> 0 | K60: =IF(J60=0,"",J60/G60)
A61: ='SCHEDULE OF VALUE WORKSHEET'!A57 -> 51 | B61: ='SCHEDULE OF VALUE WORKSHEET'!B57 -> CABINETS | D61: =SUM('SCHEDULE OF VALUE WORKSHEET'!E57) -> 56930 | E61: =SUM('Draw #3'!E61:F61) -> 0 | F61: 0 | G61: =SUM('Draw #3'!G61)+'Draw #4'!F61 -> 56930 | H61: =SUM(G61-J61) -> 56930 | I61: 0 | J61: =SUM(I61+'Draw #3'!J61) -> 0 | K61: =IF(J61=0,"",J61/G61)
A62: ='SCHEDULE OF VALUE WORKSHEET'!A58 -> 52 | B62: ='SCHEDULE OF VALUE WORKSHEET'!B58 -> THERMAL MOISTURE PROTECTION | D62: =SUM('SCHEDULE OF VALUE WORKSHEET'!E58) -> 173148 | E62: =SUM('Draw #3'!E62:F62) -> 0 | F62: 0 | G62: =SUM('Draw #3'!G62)+'Draw #4'!F62 -> 173148 | H62: =SUM(G62-J62) -> 173148 | I62: 0 | J62: =SUM(I62+'Draw #3'!J62) -> 0 | K62: =IF(J62=0,"",J62/G62)
A63: ='SCHEDULE OF VALUE WORKSHEET'!A59 -> 53 | B63: ='SCHEDULE OF VALUE WORKSHEET'!B59 -> DOORS | D63: =SUM('SCHEDULE OF VALUE WORKSHEET'!E59) -> 204087.33 | E63: =SUM('Draw #3'!E63:F63) -> 0 | F63: 0 | G63: =SUM('Draw #3'!G63)+'Draw #4'!F63 -> 204087.33 | H63: =SUM(G63-J63) -> 204087.33 | I63: 0 | J63: =SUM(I63+'Draw #3'!J63) -> 0 | K63: =IF(J63=0,"",J63/G63)
A64: ='SCHEDULE OF VALUE WORKSHEET'!A60 -> 54 | B64: ='SCHEDULE OF VALUE WORKSHEET'!B60 -> WINDOWS | D64: =SUM('SCHEDULE OF VALUE WORKSHEET'!E60) -> 106274.25 | E64: =SUM('Draw #3'!E64:F64) -> 0 | F64: 0 | G64: =SUM('Draw #3'!G64)+'Draw #4'!F64 -> 106274.25 | H64: =SUM(G64-J64) -> 106274.25 | I64: 0 | J64: =SUM(I64+'Draw #3'!J64) -> 0 | K64: =IF(J64=0,"",J64/G64)
... A90: ='SCHEDULE OF VALUE WORKSHEET'!A86 -> 80 | B90: ='SCHEDULE OF VALUE WORKSHEET'!B86 -> FINANCING COSTS | D90: =SUM('SCHEDULE OF VALUE WORKSHEET'!E86) -> 0 | E90: =SUM('Draw #3'!E90:F90) -> 0 | F90: 0 | G90: =SUM('Draw #3'!G90)+'Draw #4'!F90 -> 0 | H90: =SUM(G90-J90) -> 0 | I90: 0 | J90: =SUM(I90+'Draw #3'!J90) -> 0 | K90: =IF(J90=0,"",J90/G90)
A91: ='SCHEDULE OF VALUE WORKSHEET'!#REF! -> #REF! | B91: ='SCHEDULE OF VALUE WORKSHEET'!#REF! -> #REF! | D91: =SUM('SCHEDULE OF VALUE WORKSHEET'!#REF!) -> #REF! | E91: =SUM('Draw #3'!E91:F91) -> 0 | F91: 0 | G91: =SUM('Draw #3'!G91)+'Draw #4'!F91 -> #REF! | H91: =SUM(G91-J91) -> #REF! | I91: 0 | J91: =SUM(I91+'Draw #3'!J91) -> 0 | K91: =IF(J91=0,"",J91/G91)
A92: ='SCHEDULE OF VALUE WORKSHEET'!#REF! -> #REF! | B92: ='SCHEDULE OF VALUE WORKSHEET'!#REF! -> #REF! | D92: =SUM('SCHEDULE OF VALUE WORKSHEET'!#REF!) -> #REF! | E92: =SUM('Draw #3'!E92:F92) -> 0 | F92: 0 | G92: =SUM('Draw #3'!G92)+'Draw #4'!F92 -> #REF! | H92: =SUM(G92-J92) -> #REF! | I92: 0 | J92: =SUM(I92+'Draw #3'!J92) -> 0 | K92: =IF(J92=0,"",J92/G92)
A93: ='SCHEDULE OF VALUE WORKSHEET'!#REF! -> #REF! | B93: ='SCHEDULE OF VALUE WORKSHEET'!#REF! -> #REF! | D93: =SUM('SCHEDULE OF VALUE WORKSHEET'!#REF!) -> #REF! | E93: =SUM('Draw #3'!E93:F93) -> 0 | F93: 0 | G93: =SUM('Draw #3'!G93)+'Draw #4'!F93 -> #REF! | H93: =SUM(G93-J93) -> #REF! | I93: 0 | J93: =SUM(I93+'Draw #3'!J93) -> 0 | K93: =IF(J93=0,"",J93/G93)
A94: ='SCHEDULE OF VALUE WORKSHEET'!#REF! -> #REF! | B94: ='SCHEDULE OF VALUE WORKSHEET'!#REF! -> #REF! | D94: =SUM('SCHEDULE OF VALUE WORKSHEET'!#REF!) -> #REF! | E94: =SUM('Draw #3'!E94:F94) -> 0 | F94: 0 | G94: =SUM('Draw #3'!G94)+'Draw #4'!F94 -> #REF! | H94: =SUM(G94-J94) -> #REF! | I94: 0 | J94: =SUM(I94+'Draw #3'!J94) -> 0 | K94: =IF(J94=0,"",J94/G94)
A95: ='SCHEDULE OF VALUE WORKSHEET'!#REF! -> #REF! | B95: ='SCHEDULE OF VALUE WORKSHEET'!#REF! -> #REF! | D95: =SUM('SCHEDULE OF VALUE WORKSHEET'!#REF!) -> #REF! | E95: =SUM('Draw #3'!E95:F95) -> 0 | F95: 0 | G95: =SUM('Draw #3'!G95)+'Draw #4'!F95 -> #REF! | H95: =SUM(G95-J95) -> #REF! | I95: 0 | J95: =SUM(I95+'Draw #3'!J95) -> 0 | K95: =IF(J95=0,"",J95/G95)
A96: ='SCHEDULE OF VALUE WORKSHEET'!#REF! -> #REF! | B96: ='SCHEDULE OF VALUE WORKSHEET'!#REF! -> #REF! | D96: =SUM('SCHEDULE OF VALUE WORKSHEET'!#REF!) -> #REF! | E96: =SUM('Draw #3'!E96:F96) -> 0 | F96: 0 | G96: =SUM('Draw #3'!G96)+'Draw #4'!F96 -> #REF! | H96: =SUM(G96-J96) -> #REF! | I96: 0 | J96: =SUM(I96+'Draw #3'!J96) -> 0 | K96: =IF(J96=0,"",J96/G96)
A97: ='SCHEDULE OF VALUE WORKSHEET'!#REF! -> #REF! | B97: ='SCHEDULE OF VALUE WORKSHEET'!#REF! -> #REF! | D97: =SUM('SCHEDULE OF VALUE WORKSHEET'!#REF!) -> #REF! | E97: =SUM('Draw #3'!E97:F97) -> 0 | F97: 0 | G97: =SUM('Draw #3'!G97)+'Draw #4'!F97 -> #REF! | H97: =SUM(G97-J97) -> #REF! | I97: 0 | J97: =SUM(I97+'Draw #3'!J97) -> 0 | K97: =IF(J97=0,"",J97/G97)
A98: ='SCHEDULE OF VALUE WORKSHEET'!#REF! -> #REF! | B98: ='SCHEDULE OF VALUE WORKSHEET'!#REF! -> #REF! | D98: =SUM('SCHEDULE OF VALUE WORKSHEET'!#REF!) -> #REF! | E98: =SUM('Draw #3'!E98:F98) -> 0 | F98: 0 | G98: =SUM('Draw #3'!G98)+'Draw #4'!F98 -> #REF! | H98: =SUM(G98-J98) -> #REF! | I98: 0 | J98: =SUM(I98+'Draw #3'!J98) -> 0 | K98: =IF(J98=0,"",J98/G98)
A99: ='SCHEDULE OF VALUE WORKSHEET'!#REF! -> #REF! | B99: ='SCHEDULE OF VALUE WORKSHEET'!#REF! -> #REF! | D99: =SUM('SCHEDULE OF VALUE WORKSHEET'!#REF!) -> #REF! | E99: =SUM('Draw #3'!E99:F99) -> 0 | F99: 0 | G99: =SUM('Draw #3'!G99)+'Draw #4'!F99 -> #REF! | H99: =SUM(G99-J99) -> #REF! | I99: 0 | J99: =SUM(I99+'Draw #3'!J99) -> 0 | K99: =IF(J99=0,"",J99/G99)
A100: ='SCHEDULE OF VALUE WORKSHEET'!#REF! -> #REF! | B100: ='SCHEDULE OF VALUE WORKSHEET'!#REF! -> #REF! | D100: =SUM('SCHEDULE OF VALUE WORKSHEET'!#REF!) -> #REF! | E100: =SUM('Draw #3'!E100:F100) -> 0 | F100: 0 | G100: =SUM('Draw #3'!G100)+'Draw #4'!F100 -> #REF! | H100: =SUM(G100-J100) -> #REF! | I100: 0 | J100: =SUM(I100+'Draw #3'!J100) -> 0 | K100: =IF(J100=0,"",J100/G100)
A101: ='SCHEDULE OF VALUE WORKSHEET'!#REF! -> #REF! | B101: ='SCHEDULE OF VALUE WORKSHEET'!#REF! -> #REF! | D101: =SUM('SCHEDULE OF VALUE WORKSHEET'!#REF!) -> #REF! | E101: =SUM('Draw #3'!E101:F101) -> 0 | F101: 0 | G101: =SUM('Draw #3'!G101)+'Draw #4'!F101 -> #REF! | H101: =SUM(G101-J101) -> #REF! | I101: 0 | J101: =SUM(I101+'Draw #3'!J101) -> 0 | K101: =IF(J101=0,"",J101/G101)
A102: ='SCHEDULE OF VALUE WORKSHEET'!#REF! -> #REF! | B102: ='SCHEDULE OF VALUE WORKSHEET'!#REF! -> #REF! | D102: =SUM('SCHEDULE OF VALUE WORKSHEET'!#REF!) -> #REF! | E102: =SUM('Draw #3'!E102:F102) -> 0 | F102: 0 | G102: =SUM('Draw #3'!G102)+'Draw #4'!F102 -> #REF! | H102: =SUM(G102-J102) -> #REF! | I102: 0 | J102: =SUM(I102+'Draw #3'!J102) -> 0 | K102: =IF(J102=0,"",J102/G102)
... A116: ='SCHEDULE OF VALUE WORKSHEET'!#REF! -> #REF! | B116: ='SCHEDULE OF VALUE WORKSHEET'!#REF! -> #REF! | D116: =SUM('SCHEDULE OF VALUE WORKSHEET'!#REF!) -> #REF! | E116: =SUM('Draw #3'!E116:F116) -> 0 | F116: 0 | G116: =SUM('Draw #3'!G116)+'Draw #4'!F116 -> #REF! | H116: =SUM(G116-J116) -> #REF! | I116: 0 | J116: =SUM(I116+'Draw #3'!J116) -> 0 | K116: =IF(J116=0,"",J116/G116)
A117: ='SCHEDULE OF VALUE WORKSHEET'!A87 -> 82 | B117: ='SCHEDULE OF VALUE WORKSHEET'!B87 -> Open Item | D117: =SUM('SCHEDULE OF VALUE WORKSHEET'!E87) -> 0 | E117: =SUM('Draw #3'!E117:F117) -> 0 | F117: 0 | G117: =SUM('Draw #3'!G117)+'Draw #4'!F117 -> 0 | H117: =SUM(G117-J117) -> 0 | I117: 0 | J117: =SUM(I117+'Draw #3'!J117) -> 0 | K117: =IF(J117=0,"",J117/G117)
A118: ='SCHEDULE OF VALUE WORKSHEET'!A88 -> 83 | B118: ='SCHEDULE OF VALUE WORKSHEET'!B88 -> Open Item | D118: =SUM('SCHEDULE OF VALUE WORKSHEET'!E88) -> 0 | E118: =SUM('Draw #3'!E118:F118) -> 0 | F118: 0 | G118: =SUM('Draw #3'!G118)+'Draw #4'!F118 -> 0 | H118: =SUM(G118-J118) -> 0 | I118: 0 | J118: =SUM(I118+'Draw #3'!J118) -> 0 | K118: =IF(J118=0,"",J118/G118)
A119: ='SCHEDULE OF VALUE WORKSHEET'!A89 -> 84 | B119: ='SCHEDULE OF VALUE WORKSHEET'!B89 -> Open Item | D119: =SUM('SCHEDULE OF VALUE WORKSHEET'!E89) -> 0 | E119: =SUM('Draw #3'!E119:F119) -> 0 | F119: 0 | G119: =SUM('Draw #3'!G119)+'Draw #4'!F119 -> 0 | H119: =SUM(G119-J119) -> 0 | I119: 0 | J119: =SUM(I119+'Draw #3'!J119) -> 0 | K119: =IF(J119=0,"",J119/G119)
A120: ='SCHEDULE OF VALUE WORKSHEET'!A90 -> 85 | B120: ='SCHEDULE OF VALUE WORKSHEET'!B90 -> Open Item | D120: =SUM('SCHEDULE OF VALUE WORKSHEET'!E90) -> 0 | E120: =SUM('Draw #3'!E120:F120) -> 0 | F120: 0 | G120: =SUM('Draw #3'!G120)+'Draw #4'!F120 -> 0 | H120: =SUM(G120-J120) -> 0 | I120: 0 | J120: =SUM(I120+'Draw #3'!J120) -> 0 | K120: =IF(J120=0,"",J120/G120)
A121: ='SCHEDULE OF VALUE WORKSHEET'!A91 -> 86 | B121: ='SCHEDULE OF VALUE WORKSHEET'!B91 -> Open Item | D121: =SUM('SCHEDULE OF VALUE WORKSHEET'!E91) -> 0 | E121: =SUM('Draw #3'!E121:F121) -> 0 | F121: 0 | G121: =SUM('Draw #3'!G121)+'Draw #4'!F121 -> 0 | H121: =SUM(G121-J121) -> 0 | I121: 0 | J121: =SUM(I121+'Draw #3'!J121) -> 0 | K121: =IF(J121=0,"",J121/G121)
A122: ='SCHEDULE OF VALUE WORKSHEET'!A92 -> 87 | B122: ='SCHEDULE OF VALUE WORKSHEET'!B92 -> Open Item | D122: =SUM('SCHEDULE OF VALUE WORKSHEET'!E92) -> 0 | E122: =SUM('Draw #3'!E122:F122) -> 0 | F122: 0 | G122: =SUM('Draw #3'!G122)+'Draw #4'!F122 -> 0 | H122: =SUM(G122-J122) -> 0 | I122: 0 | J122: =SUM(I122+'Draw #3'!J122) -> 0 | K122: =IF(J122=0,"",J122/G122)
A123: ='SCHEDULE OF VALUE WORKSHEET'!A93 -> 88 | B123: ='SCHEDULE OF VALUE WORKSHEET'!B93 -> Open Item | D123: =SUM('SCHEDULE OF VALUE WORKSHEET'!E93) -> 0 | E123: =SUM('Draw #3'!E123:F123) -> 0 | F123: 0 | G123: =SUM('Draw #3'!G123)+'Draw #4'!F123 -> 0 | H123: =SUM(G123-J123) -> 0 | I123: 0 | J123: =SUM(I123+'Draw #3'!J123) -> 0 | K123: =IF(J123=0,"",J123/G123)
A124: ='SCHEDULE OF VALUE WORKSHEET'!A94 -> 89 | B124: ='SCHEDULE OF VALUE WORKSHEET'!B94 -> Open Item | D124: =SUM('SCHEDULE OF VALUE WORKSHEET'!E94) -> 0 | E124: =SUM('Draw #3'!E124:F124) -> 0 | F124: 0 | G124: =SUM('Draw #3'!G124)+'Draw #4'!F124 -> 0 | H124: =SUM(G124-J124) -> 0 | I124: 0 | J124: =SUM(I124+'Draw #3'!J124) -> 0 | K124: =IF(J124=0,"",J124/G124)
A125: ='SCHEDULE OF VALUE WORKSHEET'!A95 -> 90 | B125: ='SCHEDULE OF VALUE WORKSHEET'!B95 -> Open Item | D125: =SUM('SCHEDULE OF VALUE WORKSHEET'!E95) -> 0 | E125: =SUM('Draw #3'!E125:F125) -> 0 | F125: 0 | G125: =SUM('Draw #3'!G125)+'Draw #4'!F125 -> 0 | H125: =SUM(G125-J125) -> 0 | I125: 0 | J125: =SUM(I125+'Draw #3'!J125) -> 0 | K125: =IF(J125=0,"",J125/G125)
A126: ='SCHEDULE OF VALUE WORKSHEET'!A96 -> 91 | B126: ='SCHEDULE OF VALUE WORKSHEET'!B96 -> Open Item | D126: =SUM('SCHEDULE OF VALUE WORKSHEET'!E96) -> 0 | E126: =SUM('Draw #3'!E126:F126) -> 0 | F126: 0 | G126: =SUM('Draw #3'!G126)+'Draw #4'!F126 -> 0 | H126: =SUM(G126-J126) -> 0 | I126: 0 | J126: =SUM(I126+'Draw #3'!J126) -> 0 | K126: =IF(J126=0,"",J126/G126)
A127: ='SCHEDULE OF VALUE WORKSHEET'!A97 -> 92 | B127: ='SCHEDULE OF VALUE WORKSHEET'!B97 -> Open Item | D127: =SUM('SCHEDULE OF VALUE WORKSHEET'!E97) -> 0 | E127: =SUM('Draw #3'!E127:F127) -> 0 | F127: 0 | G127: =SUM('Draw #3'!G127)+'Draw #4'!F127 -> 0 | H127: =SUM(G127-J127) -> 0 | I127: 0 | J127: =SUM(I127+'Draw #3'!J127) -> 0 | K127: =IF(J127=0,"",J127/G127)
A128: ='SCHEDULE OF VALUE WORKSHEET'!A98 -> 93 | B128: ='SCHEDULE OF VALUE WORKSHEET'!B98 -> Open Item | D128: =SUM('SCHEDULE OF VALUE WORKSHEET'!E98) -> 0 | E128: =SUM('Draw #3'!E128:F128) -> 0 | F128: 0 | G128: =SUM('Draw #3'!G128)+'Draw #4'!F128 -> 0 | H128: =SUM(G128-J128) -> 0 | I128: 0 | J128: =SUM(I128+'Draw #3'!J128) -> 0 | K128: =IF(J128=0,"",J128/G128)
... A134: ='SCHEDULE OF VALUE WORKSHEET'!A104 -> 99 | B134: ='SCHEDULE OF VALUE WORKSHEET'!B104 -> Open Item | D134: =SUM('SCHEDULE OF VALUE WORKSHEET'!E104) -> 0 | E134: =SUM('Draw #3'!E134:F134) -> 0 | F134: 0 | G134: =SUM('Draw #3'!G134)+'Draw #4'!F134 -> 0 | H134: =SUM(G134-J134) -> 0 | I134: 0 | J134: =SUM(I134+'Draw #3'!J134) -> 0 | K134: =IF(J134=0,"",J134/G134)
A135: ='SCHEDULE OF VALUE WORKSHEET'!#REF! -> #REF! | B135: ='SCHEDULE OF VALUE WORKSHEET'!#REF! -> #REF! | D135: =SUM('SCHEDULE OF VALUE WORKSHEET'!#REF!) -> #REF! | E135: =SUM('Draw #3'!E135:F135) -> 0 | F135: 0 | G135: =SUM('Draw #3'!G135)+'Draw #4'!F135 -> #REF! | H135: =SUM(G135-J135) -> #REF! | I135: 0 | J135: =SUM(I135+'Draw #3'!J135) -> 0 | K135: =IF(J135=0,"",J135/G135)
B137: TOTAL | D137: =SUM(D10:D135) -> #REF! | E137: =SUM(E10:E135) -> 0 | F137: =SUM(F10:F135) -> 0 | G137: =SUM(G10:G135) -> #REF! | H137: =SUM(H10:H135) -> #REF! | I137: =SUM(I10:I135) -> 0 | J137: =SUM(J10:J135) -> 0

Sheet Draw #5
A1: GENESIS CAPITAL DRAW FORM
B3: CLIENT: | C3: ='SCHEDULE OF VALUE WORKSHEET'!$B$3 -> Angeleno Investments | I3: TOTAL COMPLETED TO DATE: | J3: =SUM(J137) -> 0 | K3: =SUM(J3)/J7 -> #REF!
B4: DATE: | C4: =TODAY() -> 45978 | I4: REMAINING $ IN BUDGET: | J4: =SUM(H137) -> #REF!
B5: PROJECT: | C5: ='SCHEDULE OF VALUE WORKSHEET'!B5 -> 10910 Huston Street | I5: ORIGINAL SCHEDULE OF VALUES: | J5: =SUM(D137) -> #REF!
B6: DRAW REQUEST: | C6: =SUM(I137) -> 0 | I6: CHANGE ORDERS: | J6: =SUM(F137) -> 0
I7: REVISED SCHEDULE OF VALUES: | J7: =SUM(G137) -> #REF!
B8: DESCRIPTION OF WORK | D8: SCHEDULED VALUES | E8: PREVIOUS | F8: + / - CHANGES | G8: REVISED VALUES | H8: REMAINING | I8: DRAW | J8: COMPLETED AND
E9: CHANGES | H9: BUDGET | I9: 5 | J9: STORED TO DATE
A10: ='SCHEDULE OF VALUE WORKSHEET'!A7 -> 1 | B10: ='SCHEDULE OF VALUE WORKSHEET'!B7 -> SOFT COSTS | D10: =SUM('SCHEDULE OF VALUE WORKSHEET'!E7) -> 0 | E10: =SUM('Draw #4'!E10:F10) -> 0 | F10: 0 | G10: =SUM('Draw #4'!G10)+'Draw #5'!F10 -> 0 | H10: =SUM(G10-J10) -> 0 | I10: 0 | J10: =SUM(I10+'Draw #4'!J10) -> 0 | K10: =IF(J10=0,"",J10/G10)
A11: ='SCHEDULE OF VALUE WORKSHEET'!A8 -> 2 | B11: ='SCHEDULE OF VALUE WORKSHEET'!B8 -> Site Security | D11: =SUM('SCHEDULE OF VALUE WORKSHEET'!E8) -> 10580.63 | E11: =SUM('Draw #4'!E11:F11) -> 0 | F11: 0 | G11: =SUM('Draw #4'!G11)+'Draw #5'!F11 -> 10580.63 | H11: =SUM(G11-J11) -> 10580.63 | I11: 0 | J11: =SUM(I11+'Draw #4'!J11) -> 0 | K11: =IF(J11=0,"",J11/G11)
A12: ='SCHEDULE OF VALUE WORKSHEET'!A9 -> 3 | B12: ='SCHEDULE OF VALUE WORKSHEET'!B9 -> Soils Inspection | D12: =SUM('SCHEDULE OF VALUE WORKSHEET'!E9) -> 0 | E12: =SUM('Draw #4'!E12:F12) -> 0 | F12: 0 | G12: =SUM('Draw #4'!G12)+'Draw #5'!F12 -> 0 | H12: =SUM(G12-J12) -> 0 | I12: 0 | J12: =SUM(I12+'Draw #4'!J12) -> 0 | K12: =IF(J12=0,"",J12/G12)
A13: ='SCHEDULE OF VALUE WORKSHEET'!A10 -> 4 | B13: ='SCHEDULE OF VALUE WORKSHEET'!B10 -> Offsites (Transformer) | D13: =SUM('SCHEDULE OF VALUE WORKSHEET'!E10) -> 20000 | E13: =SUM('Draw #4'!E13:F13) -> 0 | F13: 0 | G13: =SUM('Draw #4'!G13)+'Draw #5'!F13 -> 20000 | H13: =SUM(G13-J13) -> 20000 | I13: 0 | J13: =SUM(I13+'Draw #4'!J13) -> 0 | K13: =IF(J13=0,"",J13/G13)
A14: ='SCHEDULE OF VALUE WORKSHEET'!A11 -> 5 | B14: ='SCHEDULE OF VALUE WORKSHEET'!B11 -> Plan Check Fees | D14: =SUM('SCHEDULE OF VALUE WORKSHEET'!E11) -> 0 | E14: =SUM('Draw #4'!E14:F14) -> 0 | F14: 0 | G14: =SUM('Draw #4'!G14)+'Draw #5'!F14 -> 0 | H14: =SUM(G14-J14) -> 0 | I14: 0 | J14: =SUM(I14+'Draw #4'!J14) -> 0 | K14: =IF(J14=0,"",J14/G14)
A15: ='SCHEDULE OF VALUE WORKSHEET'!A12 -> 6 | B15: ='SCHEDULE OF VALUE WORKSHEET'!B12 -> Permits | D15: =SUM('SCHEDULE OF VALUE WORKSHEET'!E12) -> 0 | E15: =SUM('Draw #4'!E15:F15) -> 0 | F15: 0 | G15: =SUM('Draw #4'!G15)+'Draw #5'!F15 -> 0 | H15: =SUM(G15-J15) -> 0 | I15: 0 | J15: =SUM(I15+'Draw #4'!J15) -> 0 | K15: =IF(J15=0,"",J15/G15)
A16: ='SCHEDULE OF VALUE WORKSHEET'!A13 -> 7 | B16: ='SCHEDULE OF VALUE WORKSHEET'!B13 -> Survey | D16: =SUM('SCHEDULE OF VALUE WORKSHEET'!E13) -> 0 | E16: =SUM('Draw #4'!E16:F16) -> 0 | F16: 0 | G16: =SUM('Draw #4'!G16)+'Draw #5'!F16 -> 0 | H16: =SUM(G16-J16) -> 0 | I16: 0 | J16: =SUM(I16+'Draw #4'!J16) -> 0 | K16: =IF(J16=0,"",J16/G16)
A17: ='SCHEDULE OF VALUE WORKSHEET'!A14 -> 8 | B17: ='SCHEDULE OF VALUE WORKSHEET'!B14 -> Soils Engineer | D17: =SUM('SCHEDULE OF VALUE WORKSHEET'!E14) -> 0 | E17: =SUM('Draw #4'!E17:F17) -> 0 | F17: 0 | G17: =SUM('Draw #4'!G17)+'Draw #5'!F17 -> 0 | H17: =SUM(G17-J17) -> 0 | I17: 0 | J17: =SUM(I17+'Draw #4'!J17) -> 0 | K17: =IF(J17=0,"",J17/G17)
A18: ='SCHEDULE OF VALUE WORKSHEET'!A15 -> 9 | B18: ='SCHEDULE OF VALUE WORKSHEET'!B15 -> Soils Permit + T24 | D18: =SUM('SCHEDULE OF VALUE WORKSHEET'!E15) -> 2500 | E18: =SUM('Draw #4'!E18:F18) -> 0 | F18: 0 | G18: =SUM('Draw #4'!G18)+'Draw #5'!F18 -> 2500 | H18: =SUM(G18-J18) -> 2500 | I18: 0 | J18: =SUM(I18+'Draw #4'!J18) -> 0 | K18: =IF(J18=0,"",J18/G18)
A19: ='SCHEDULE OF VALUE WORKSHEET'!A16 -> 10 | B19: ='SCHEDULE OF VALUE WORKSHEET'!B16 -> Special Inspections - Deputy | D19: =SUM('SCHEDULE OF VALUE WORKSHEET'!E16) -> 15000 | E19: =SUM('Draw #4'!E19:F19) -> 0 | F19: 0 | G19: =SUM('Draw #4'!G19)+'Draw #5'!F19 -> 15000 | H19: =SUM(G19-J19) -> 15000 | I19: 0 | J19: =SUM(I19+'Draw #4'!J19) -> 0 | K19: =IF(J19=0,"",J19/G19)
A20: ='SCHEDULE OF VALUE WORKSHEET'!A17 -> 11 | B20: ='SCHEDULE OF VALUE WORKSHEET'!B17 -> Architect | D20: =SUM('SCHEDULE OF VALUE WORKSHEET'!E17) -> 0 | E20: =SUM('Draw #4'!E20:F20) -> 0 | F20: 0 | G20: =SUM('Draw #4'!G20)+'Draw #5'!F20 -> 0 | H20: =SUM(G20-J20) -> 0 | I20: 0 | J20: =SUM(I20+'Draw #4'!J20) -> 0 | K20: =IF(J20=0,"",J20/G20)
A21: ='SCHEDULE OF VALUE WORKSHEET'!A18 -> 12 | B21: ='SCHEDULE OF VALUE WORKSHEET'!B18 -> Structural Engineer | D21: =SUM('SCHEDULE OF VALUE WORKSHEET'!E18) -> 0 | E21: =SUM('Draw #4'!E21:F21) -> 0 | F21: 0 | G21: =SUM('Draw #4'!G21)+'Draw #5'!F21 -> 0 | H21: =SUM(G21-J21) -> 0 | I21: 0 | J21: =SUM(I21+'Draw #4'!J21) -> 0 | K21: =IF(J21=0,"",J21/G21)
... A45: ='SCHEDULE OF VALUE WORKSHEET'!A42 -> 36 | B45: ='SCHEDULE OF VALUE WORKSHEET'!B42 -> Construction Management / Observation (OO) | D45: =SUM('SCHEDULE OF VALUE WORKSHEET'!E42) -> 49427.9 | E45: =SUM('Draw #4'!E45:F45) -> 0 | F45: 0 | G45: =SUM('Draw #4'!G45)+'Draw #5'!F45 -> 49427.9 | H45: =SUM(G45-J45) -> 49427.9 | I45: 0 | J45: =SUM(I45+'Draw #4'!J45) -> 0 | K45: =IF(J45=0,"",J45/G45)
A46: ='SCHEDULE OF VALUE WORKSHEET'!#REF! -> #REF! | B46: ='SCHEDULE OF VALUE WORKSHEET'!#REF! -> #REF! | D46: =SUM('SCHEDULE OF VALUE WORKSHEET'!#REF!) -> #REF! | E46: =SUM('Draw #4'!E46:F46) -> 0 | F46: 0 | G46: =SUM('Draw #4'!G46)+'Draw #5'!F46 -> #REF! | H46: =SUM(G46-J46) -> #REF! | I46: 0 | J46: =SUM(I46+'Draw #4'!J46) -> 0 | K46: =IF(J46=0,"",J46/G46)
A47: ='SCHEDULE OF VALUE WORKSHEET'!A43 -> 37 | B47: ='SCHEDULE OF VALUE WORKSHEET'!B43 -> CMFA Startup Fee | D47: =SUM('SCHEDULE OF VALUE WORKSHEET'!E43) -> 22800 | E47: =SUM('Draw #4'!E47:F47) -> 0 | F47: 0 | G47: =SUM('Draw #4'!G47)+'Draw #5'!F47 -> 22800 | H47: =SUM(G47-J47) -> 22800 | I47: 0 | J47: =SUM(I47+'Draw #4'!J47) -> 0 | K47: =IF(J47=0,"",J47/G47)
A48: ='SCHEDULE OF VALUE WORKSHEET'!A44 -> 38 | B48: ='SCHEDULE OF VALUE WORKSHEET'!B44 -> Non-Profit Start Up Fee | D48: =SUM('SCHEDULE OF VALUE WORKSHEET'!E44) -> 25000 | E48: =SUM('Draw #4'!E48:F48) -> 0 | F48: 0 | G48: =SUM('Draw #4'!G48)+'Draw #5'!F48 -> 25000 | H48: =SUM(G48-J48) -> 25000 | I48: 0 | J48: =SUM(I48+'Draw #4'!J48) -> 0 | K48: =IF(J48=0,"",J48/G48)
A49: ='SCHEDULE OF VALUE WORKSHEET'!A45 -> 39 | B49: ='SCHEDULE OF VALUE WORKSHEET'!B45 -> CMFA Construction Fee | D49: =SUM('SCHEDULE OF VALUE WORKSHEET'!E45) -> 12000 | E49: =SUM('Draw #4'!E49:F49) -> 0 | F49: 0 | G49: =SUM('Draw #4'!G49)+'Draw #5'!F49 -> 12000 | H49: =SUM(G49-J49) -> 12000 | I49: 0 | J49: =SUM(I49+'Draw #4'!J49) -> 0 | K49: =IF(J49=0,"",J49/G49)
A50: ='SCHEDULE OF VALUE WORKSHEET'!A46 -> 40 | B50: ='SCHEDULE OF VALUE WORKSHEET'!B46 -> Non-Profit Construction Fee | D50: =SUM('SCHEDULE OF VALUE WORKSHEET'!E46) -> 10000 | E50: =SUM('Draw #4'!E50:F50) -> 0 | F50: 0 | G50: =SUM('Draw #4'!G50)+'Draw #5'!F50 -> 10000 | H50: =SUM(G50-J50) -> 10000 | I50: 0 | J50: =SUM(I50+'Draw #4'!J50) -> 0 | K50: =IF(J50=0,"",J50/G50)
A51: ='SCHEDULE OF VALUE WORKSHEET'!A47 -> 41 | B51: ='SCHEDULE OF VALUE WORKSHEET'!B47 -> WTE Legal Costs for CMFA & Non-Profit Partner | D51: =SUM('SCHEDULE OF VALUE WORKSHEET'!E47) -> 20000 | E51: =SUM('Draw #4'!E51:F51) -> 0 | F51: 0 | G51: =SUM('Draw #4'!G51)+'Draw #5'!F51 -> 20000 | H51: =SUM(G51-J51) -> 20000 | I51: 0 | J51: =SUM(I51+'Draw #4'!J51) -> 0 | K51: =IF(J51=0,"",J51/G51)
A52: ='SCHEDULE OF VALUE WORKSHEET'!#REF! -> #REF! | B52: ='SCHEDULE OF VALUE WORKSHEET'!#REF! -> #REF! | D52: =SUM('SCHEDULE OF VALUE WORKSHEET'!#REF!) -> #REF! | E52: =SUM('Draw #4'!E52:F52) -> 0 | F52: 0 | G52: =SUM('Draw #4'!G52)+'Draw #5'!F52 -> #REF! | H52: =SUM(G52-J52) -> #REF! | I52: 0 | J52: =SUM(I52+'Draw #4'!J52) -> 0 | K52: =IF(J52=0,"",J52/G52)
A53: ='SCHEDULE OF VALUE WORKSHEET'!A49 -> 43 | B53: ='SCHEDULE OF VALUE WORKSHEET'!B49 -> GENERAL CONDITIONS | D53: =SUM('SCHEDULE OF VALUE WORKSHEET'!E49) -> 362115.24 | E53: =SUM('Draw #4'!E53:F53) -> 0 | F53: 0 | G53: =SUM('Draw #4'!G53)+'Draw #5'!F53 -> 362115.24 | H53: =SUM(G53-J53) -> 362115.24 | I53: 0 | J53: =SUM(I53+'Draw #4'!J53) -> 0 | K53: =IF(J53=0,"",J53/G53)
A54: ='SCHEDULE OF VALUE WORKSHEET'!A50 -> 44 | B54: ='SCHEDULE OF VALUE WORKSHEET'!B50 -> GENERAL REQUIREMENT | D54: =SUM('SCHEDULE OF VALUE WORKSHEET'!E50) -> 124657.88 | E54: =SUM('Draw #4'!E54:F54) -> 0 | F54: 0 | G54: =SUM('Draw #4'!G54)+'Draw #5'!F54 -> 124657.88 | H54: =SUM(G54-J54) -> 124657.88 | I54: 0 | J54: =SUM(I54+'Draw #4'!J54) -> 0 | K54: =IF(J54=0,"",J54/G54)
A55: ='SCHEDULE OF VALUE WORKSHEET'!A51 -> 45 | B55: ='SCHEDULE OF VALUE WORKSHEET'!B51 -> SITE WORK | D55: =SUM('SCHEDULE OF VALUE WORKSHEET'!E51) -> 139049.51 | E55: =SUM('Draw #4'!E55:F55) -> 0 | F55: 0 | G55: =SUM('Draw #4'!G55)+'Draw #5'!F55 -> 139049.51 | H55: =SUM(G55-J55) -> 139049.51 | I55: 0 | J55: =SUM(I55+'Draw #4'!J55) -> 0 | K55: =IF(J55=0,"",J55/G55)
A56: ='SCHEDULE OF VALUE WORKSHEET'!A52 -> 46 | B56: ='SCHEDULE OF VALUE WORKSHEET'!B52 -> CONCRETE | D56: =SUM('SCHEDULE OF VALUE WORKSHEET'!E52) -> 253182 | E56: =SUM('Draw #4'!E56:F56) -> 0 | F56: 0 | G56: =SUM('Draw #4'!G56)+'Draw #5'!F56 -> 253182 | H56: =SUM(G56-J56) -> 253182 | I56: 0 | J56: =SUM(I56+'Draw #4'!J56) -> 0 | K56: =IF(J56=0,"",J56/G56)
A57: ='SCHEDULE OF VALUE WORKSHEET'!A53 -> 47 | B57: ='SCHEDULE OF VALUE WORKSHEET'!B53 -> MASONRY | D57: =SUM('SCHEDULE OF VALUE WORKSHEET'!E53) -> 3562.64 | E57: =SUM('Draw #4'!E57:F57) -> 0 | F57: 0 | G57: =SUM('Draw #4'!G57)+'Draw #5'!F57 -> 3562.64 | H57: =SUM(G57-J57) -> 3562.64 | I57: 0 | J57: =SUM(I57+'Draw #4'!J57) -> 0 | K57: =IF(J57=0,"",J57/G57)
A58: ='SCHEDULE OF VALUE WORKSHEET'!A54 -> 48 | B58: ='SCHEDULE OF VALUE WORKSHEET'!B54 -> METALS | D58: =SUM('SCHEDULE OF VALUE WORKSHEET'!E54) -> 324100 | E58: =SUM('Draw #4'!E58:F58) -> 0 | F58: 0 | G58: =SUM('Draw #4'!G58)+'Draw #5'!F58 -> 324100 | H58: =SUM(G58-J58) -> 324100 | I58: 0 | J58: =SUM(I58+'Draw #4'!J58) -> 0 | K58: =IF(J58=0,"",J58/G58)
A59: ='SCHEDULE OF VALUE WORKSHEET'!A55 -> 49 | B59: ='SCHEDULE OF VALUE WORKSHEET'!B55 -> FRAMING | D59: =SUM('SCHEDULE OF VALUE WORKSHEET'!E55) -> 818554 | E59: =SUM('Draw #4'!E59:F59) -> 0 | F59: 0 | G59: =SUM('Draw #4'!G59)+'Draw #5'!F59 -> 818554 | H59: =SUM(G59-J59) -> 818554 | I59: 0 | J59: =SUM(I59+'Draw #4'!J59) -> 0 | K59: =IF(J59=0,"",J59/G59)
A60: ='SCHEDULE OF VALUE WORKSHEET'!A56 -> 50 | B60: ='SCHEDULE OF VALUE WORKSHEET'!B56 -> COUNTERTOPS | D60: =SUM('SCHEDULE OF VALUE WORKSHEET'!E56) -> 56930 | E60: =SUM('Draw #4'!E60:F60) -> 0 | F60: 0 | G60: =SUM('Draw #4'!G60)+'Draw #5'!F60 -> 56930 | H60: =SUM(G60-J60) -> 56930 | I60: 0 | J60: =SUM(I60+'Draw #4'!J60) -> 0 | K60: =IF(J60=0,"",J60/G60)
A61: ='SCHEDULE OF VALUE WORKSHEET'!A57 -> 51 | B61: ='SCHEDULE OF VALUE WORKSHEET'!B57 -> CABINETS | D61: =SUM('SCHEDULE OF VALUE WORKSHEET'!E57) -> 56930 | E61: =SUM('Draw #4'!E61:F61) -> 0 | F61: 0 | G61: =SUM('Draw #4'!G61)+'Draw #5'!F61 -> 56930 | H61: =SUM(G61-J61) -> 56930 | I61: 0 | J61: =SUM(I61+'Draw #4'!J61) -> 0 | K61: =IF(J61=0,"",J61/G61)
A62: ='SCHEDULE OF VALUE WORKSHEET'!A58 -> 52 | B62: ='SCHEDULE OF VALUE WORKSHEET'!B58 -> THERMAL MOISTURE PROTECTION | D62: =SUM('SCHEDULE OF VALUE WORKSHEET'!E58) -> 173148 | E62: =SUM('Draw #4'!E62:F62) -> 0 | F62: 0 | G62: =SUM('Draw #4'!G62)+'Draw #5'!F62 -> 173148 | H62: =SUM(G62-J62) -> 173148 | I62: 0 | J62: =SUM(I62+'Draw #4'!J62) -> 0 | K62: =IF(J62=0,"",J62/G62)
A63: ='SCHEDULE OF VALUE WORKSHEET'!A59 -> 53 | B63: ='SCHEDULE OF VALUE WORKSHEET'!B59 -> DOORS | D63: =SUM('SCHEDULE OF VALUE WORKSHEET'!E59) -> 204087.33 | E63: =SUM('Draw #4'!E63:F63) -> 0 | F63: 0 | G63: =SUM('Draw #4'!G63)+'Draw #5'!F63 -> 204087.33 | H63: =SUM(G63-J63) -> 204087.33 | I63: 0 | J63: =SUM(I63+'Draw #4'!J63) -> 0 | K63: =IF(J63=0,"",J63/G63)
A64: ='SCHEDULE OF VALUE WORKSHEET'!A60 -> 54 | B64: ='SCHEDULE OF VALUE WORKSHEET'!B60 -> WINDOWS | D64: =SUM('SCHEDULE OF VALUE WORKSHEET'!E60) -> 106274.25 | E64: =SUM('Draw #4'!E64:F64) -> 0 | F64: 0 | G64: =SUM('Draw #4'!G64)+'Draw #5'!F64 -> 106274.25 | H64: =SUM(G64-J64) -> 106274.25 | I64: 0 | J64: =SUM(I64+'Draw #4'!J64) -> 0 | K64: =IF(J64=0,"",J64/G64)
... A90: ='SCHEDULE OF VALUE WORKSHEET'!A86 -> 80 | B90: ='SCHEDULE OF VALUE WORKSHEET'!B86 -> FINANCING COSTS | D90: =SUM('SCHEDULE OF VALUE WORKSHEET'!E86) -> 0 | E90: =SUM('Draw #4'!E90:F90) -> 0 | F90: 0 | G90: =SUM('Draw #4'!G90)+'Draw #5'!F90 -> 0 | H90: =SUM(G90-J90) -> 0 | I90: 0 | J90: =SUM(I90+'Draw #4'!J90) -> 0 | K90: =IF(J90=0,"",J90/G90)
A91: ='SCHEDULE OF VALUE WORKSHEET'!#REF! -> #REF! | B91: ='SCHEDULE OF VALUE WORKSHEET'!#REF! -> #REF! | D91: =SUM('SCHEDULE OF VALUE WORKSHEET'!#REF!) -> #REF! | E91: =SUM('Draw #4'!E91:F91) -> 0 | F91: 0 | G91: =SUM('Draw #4'!G91)+'Draw #5'!F91 -> #REF! | H91: =SUM(G91-J91) -> #REF! | I91: 0 | J91: =SUM(I91+'Draw #4'!J91) -> 0 | K91: =IF(J91=0,"",J91/G91)
A92: ='SCHEDULE OF VALUE WORKSHEET'!#REF! -> #REF! | B92: ='SCHEDULE OF VALUE WORKSHEET'!#REF! -> #REF! | D92: =SUM('SCHEDULE OF VALUE WORKSHEET'!#REF!) -> #REF! | E92: =SUM('Draw #4'!E92:F92) -> 0 | F92: 0 | G92: =SUM('Draw #4'!G92)+'Draw #5'!F92 -> #REF! | H92: =SUM(G92-J92) -> #REF! | I92: 0 | J92: =SUM(I92+'Draw #4'!J92) -> 0 | K92: =IF(J92=0,"",J92/G92)
A93: ='SCHEDULE OF VALUE WORKSHEET'!#REF! -> #REF! | B93: ='SCHEDULE OF VALUE WORKSHEET'!#REF! -> #REF! | D93: =SUM('SCHEDULE OF VALUE WORKSHEET'!#REF!) -> #REF! | E93: =SUM('Draw #4'!E93:F93) -> 0 | F93: 0 | G93: =SUM('Draw #4'!G93)+'Draw #5'!F93 -> #REF! | H93: =SUM(G93-J93) -> #REF! | I93: 0 | J93: =SUM(I93+'Draw #4'!J93) -> 0 | K93: =IF(J93=0,"",J93/G93)
A94: ='SCHEDULE OF VALUE WORKSHEET'!#REF! -> #REF! | B94: ='SCHEDULE OF VALUE WORKSHEET'!#REF! -> #REF! | D94: =SUM('SCHEDULE OF VALUE WORKSHEET'!#REF!) -> #REF! | E94: =SUM('Draw #4'!E94:F94) -> 0 | F94: 0 | G94: =SUM('Draw #4'!G94)+'Draw #5'!F94 -> #REF! | H94: =SUM(G94-J94) -> #REF! | I94: 0 | J94: =SUM(I94+'Draw #4'!J94) -> 0 | K94: =IF(J94=0,"",J94/G94)
A95: ='SCHEDULE OF VALUE WORKSHEET'!#REF! -> #REF! | B95: ='SCHEDULE OF VALUE WORKSHEET'!#REF! -> #REF! | D95: =SUM('SCHEDULE OF VALUE WORKSHEET'!#REF!) -> #REF! | E95: =SUM('Draw #4'!E95:F95) -> 0 | F95: 0 | G95: =SUM('Draw #4'!G95)+'Draw #5'!F95 -> #REF! | H95: =SUM(G95-J95) -> #REF! | I95: 0 | J95: =SUM(I95+'Draw #4'!J95) -> 0 | K95: =IF(J95=0,"",J95/G95)
A96: ='SCHEDULE OF VALUE WORKSHEET'!#REF! -> #REF! | B96: ='SCHEDULE OF VALUE WORKSHEET'!#REF! -> #REF! | D96: =SUM('SCHEDULE OF VALUE WORKSHEET'!#REF!) -> #REF! | E96: =SUM('Draw #4'!E96:F96) -> 0 | F96: 0 | G96: =SUM('Draw #4'!G96)+'Draw #5'!F96 -> #REF! | H96: =SUM(G96-J96) -> #REF! | I96: 0 | J96: =SUM(I96+'Draw #4'!J96) -> 0 | K96: =IF(J96=0,"",J96/G96)
A97: ='SCHEDULE OF VALUE WORKSHEET'!#REF! -> #REF! | B97: ='SCHEDULE OF VALUE WORKSHEET'!#REF! -> #REF! | D97: =SUM('SCHEDULE OF VALUE WORKSHEET'!#REF!) -> #REF! | E97: =SUM('Draw #4'!E97:F97) -> 0 | F97: 0 | G97: =SUM('Draw #4'!G97)+'Draw #5'!F97 -> #REF! | H97: =SUM(G97-J97) -> #REF! | I97: 0 | J97: =SUM(I97+'Draw #4'!J97) -> 0 | K97: =IF(J97=0,"",J97/G97)
A98: ='SCHEDULE OF VALUE WORKSHEET'!#REF! -> #REF! | B98: ='SCHEDULE OF VALUE WORKSHEET'!#REF! -> #REF! | D98: =SUM('SCHEDULE OF VALUE WORKSHEET'!#REF!) -> #REF! | E98: =SUM('Draw #4'!E98:F98) -> 0 | F98: 0 | G98: =SUM('Draw #4'!G98)+'Draw #5'!F98 -> #REF! | H98: =SUM(G98-J98) -> #REF! | I98: 0 | J98: =SUM(I98+'Draw #4'!J98) -> 0 | K98: =IF(J98=0,"",J98/G98)
A99: ='SCHEDULE OF VALUE WORKSHEET'!#REF! -> #REF! | B99: ='SCHEDULE OF VALUE WORKSHEET'!#REF! -> #REF! | D99: =SUM('SCHEDULE OF VALUE WORKSHEET'!#REF!) -> #REF! | E99: =SUM('Draw #4'!E99:F99) -> 0 | F99: 0 | G99: =SUM('Draw #4'!G99)+'Draw #5'!F99 -> #REF! | H99: =SUM(G99-J99) -> #REF! | I99: 0 | J99: =SUM(I99+'Draw #4'!J99) -> 0 | K99: =IF(J99=0,"",J99/G99)
A100: ='SCHEDULE OF VALUE WORKSHEET'!#REF! -> #REF! | B100: ='SCHEDULE OF VALUE WORKSHEET'!#REF! -> #REF! | D100: =SUM('SCHEDULE OF VALUE WORKSHEET'!#REF!) -> #REF! | E100: =SUM('Draw #4'!E100:F100) -> 0 | F100: 0 | G100: =SUM('Draw #4'!G100)+'Draw #5'!F100 -> #REF! | H100: =SUM(G100-J100) -> #REF! | I100: 0 | J100: =SUM(I100+'Draw #4'!J100) -> 0 | K100: =IF(J100=0,"",J100/G100)
A101: ='SCHEDULE OF VALUE WORKSHEET'!#REF! -> #REF! | B101: ='SCHEDULE OF VALUE WORKSHEET'!#REF! -> #REF! | D101: =SUM('SCHEDULE OF VALUE WORKSHEET'!#REF!) -> #REF! | E101: =SUM('Draw #4'!E101:F101) -> 0 | F101: 0 | G101: =SUM('Draw #4'!G101)+'Draw #5'!F101 -> #REF! | H101: =SUM(G101-J101) -> #REF! | I101: 0 | J101: =SUM(I101+'Draw #4'!J101) -> 0 | K101: =IF(J101=0,"",J101/G101)
A102: ='SCHEDULE OF VALUE WORKSHEET'!#REF! -> #REF! | B102: ='SCHEDULE OF VALUE WORKSHEET'!#REF! -> #REF! | D102: =SUM('SCHEDULE OF VALUE WORKSHEET'!#REF!) -> #REF! | E102: =SUM('Draw #4'!E102:F102) -> 0 | F102: 0 | G102: =SUM('Draw #4'!G102)+'Draw #5'!F102 -> #REF! | H102: =SUM(G102-J102) -> #REF! | I102: 0 | J102: =SUM(I102+'Draw #4'!J102) -> 0 | K102: =IF(J102=0,"",J102/G102)
... A116: ='SCHEDULE OF VALUE WORKSHEET'!#REF! -> #REF! | B116: ='SCHEDULE OF VALUE WORKSHEET'!#REF! -> #REF! | D116: =SUM('SCHEDULE OF VALUE WORKSHEET'!#REF!) -> #REF! | E116: =SUM('Draw #4'!E116:F116) -> 0 | F116: 0 | G116: =SUM('Draw #4'!G116)+'Draw #5'!F116 -> #REF! | H116: =SUM(G116-J116) -> #REF! | I116: 0 | J116: =SUM(I116+'Draw #4'!J116) -> 0 | K116: =IF(J116=0,"",J116/G116)
A117: ='SCHEDULE OF VALUE WORKSHEET'!A87 -> 82 | B117: ='SCHEDULE OF VALUE WORKSHEET'!B87 -> Open Item | D117: =SUM('SCHEDULE OF VALUE WORKSHEET'!E87) -> 0 | E117: =SUM('Draw #4'!E117:F117) -> 0 | F117: 0 | G117: =SUM('Draw #4'!G117)+'Draw #5'!F117 -> 0 | H117: =SUM(G117-J117) -> 0 | I117: 0 | J117: =SUM(I117+'Draw #4'!J117) -> 0 | K117: =IF(J117=0,"",J117/G117)
A118: ='SCHEDULE OF VALUE WORKSHEET'!A88 -> 83 | B118: ='SCHEDULE OF VALUE WORKSHEET'!B88 -> Open Item | D118: =SUM('SCHEDULE OF VALUE WORKSHEET'!E88) -> 0 | E118: =SUM('Draw #4'!E118:F118) -> 0 | F118: 0 | G118: =SUM('Draw #4'!G118)+'Draw #5'!F118 -> 0 | H118: =SUM(G118-J118) -> 0 | I118: 0 | J118: =SUM(I118+'Draw #4'!J118) -> 0 | K118: =IF(J118=0,"",J118/G118)
A119: ='SCHEDULE OF VALUE WORKSHEET'!A89 -> 84 | B119: ='SCHEDULE OF VALUE WORKSHEET'!B89 -> Open Item | D119: =SUM('SCHEDULE OF VALUE WORKSHEET'!E89) -> 0 | E119: =SUM('Draw #4'!E119:F119) -> 0 | F119: 0 | G119: =SUM('Draw #4'!G119)+'Draw #5'!F119 -> 0 | H119: =SUM(G119-J119) -> 0 | I119: 0 | J119: =SUM(I119+'Draw #4'!J119) -> 0 | K119: =IF(J119=0,"",J119/G119)
A120: ='SCHEDULE OF VALUE WORKSHEET'!A90 -> 85 | B120: ='SCHEDULE OF VALUE WORKSHEET'!B90 -> Open Item | D120: =SUM('SCHEDULE OF VALUE WORKSHEET'!E90) -> 0 | E120: =SUM('Draw #4'!E120:F120) -> 0 | F120: 0 | G120: =SUM('Draw #4'!G120)+'Draw #5'!F120 -> 0 | H120: =SUM(G120-J120) -> 0 | I120: 0 | J120: =SUM(I120+'Draw #4'!J120) -> 0 | K120: =IF(J120=0,"",J120/G120)
A121: ='SCHEDULE OF VALUE WORKSHEET'!A91 -> 86 | B121: ='SCHEDULE OF VALUE WORKSHEET'!B91 -> Open Item | D121: =SUM('SCHEDULE OF VALUE WORKSHEET'!E91) -> 0 | E121: =SUM('Draw #4'!E121:F121) -> 0 | F121: 0 | G121: =SUM('Draw #4'!G121)+'Draw #5'!F121 -> 0 | H121: =SUM(G121-J121) -> 0 | I121: 0 | J121: =SUM(I121+'Draw #4'!J121) -> 0 | K121: =IF(J121=0,"",J121/G121)
A122: ='SCHEDULE OF VALUE WORKSHEET'!A92 -> 87 | B122: ='SCHEDULE OF VALUE WORKSHEET'!B92 -> Open Item | D122: =SUM('SCHEDULE OF VALUE WORKSHEET'!E92) -> 0 | E122: =SUM('Draw #4'!E122:F122) -> 0 | F122: 0 | G122: =SUM('Draw #4'!G122)+'Draw #5'!F122 -> 0 | H122: =SUM(G122-J122) -> 0 | I122: 0 | J122: =SUM(I122+'Draw #4'!J122) -> 0 | K122: =IF(J122=0,"",J122/G122)
A123: ='SCHEDULE OF VALUE WORKSHEET'!A93 -> 88 | B123: ='SCHEDULE OF VALUE WORKSHEET'!B93 -> Open Item | D123: =SUM('SCHEDULE OF VALUE WORKSHEET'!E93) -> 0 | E123: =SUM('Draw #4'!E123:F123) -> 0 | F123: 0 | G123: =SUM('Draw #4'!G123)+'Draw #5'!F123 -> 0 | H123: =SUM(G123-J123) -> 0 | I123: 0 | J123: =SUM(I123+'Draw #4'!J123) -> 0 | K123: =IF(J123=0,"",J123/G123)
A124: ='SCHEDULE OF VALUE WORKSHEET'!A94 -> 89 | B124: ='SCHEDULE OF VALUE WORKSHEET'!B94 -> Open Item | D124: =SUM('SCHEDULE OF VALUE WORKSHEET'!E94) -> 0 | E124: =SUM('Draw #4'!E124:F124) -> 0 | F124: 0 | G124: =SUM('Draw #4'!G124)+'Draw #5'!F124 -> 0 | H124: =SUM(G124-J124) -> 0 | I124: 0 | J124: =SUM(I124+'Draw #4'!J124) -> 0 | K124: =IF(J124=0,"",J124/G124)
A125: ='SCHEDULE OF VALUE WORKSHEET'!A95 -> 90 | B125: ='SCHEDULE OF VALUE WORKSHEET'!B95 -> Open Item | D125: =SUM('SCHEDULE OF VALUE WORKSHEET'!E95) -> 0 | E125: =SUM('Draw #4'!E125:F125) -> 0 | F125: 0 | G125: =SUM('Draw #4'!G125)+'Draw #5'!F125 -> 0 | H125: =SUM(G125-J125) -> 0 | I125: 0 | J125: =SUM(I125+'Draw #4'!J125) -> 0 | K125: =IF(J125=0,"",J125/G125)
A126: ='SCHEDULE OF VALUE WORKSHEET'!A96 -> 91 | B126: ='SCHEDULE OF VALUE WORKSHEET'!B96 -> Open Item | D126: =SUM('SCHEDULE OF VALUE WORKSHEET'!E96) -> 0 | E126: =SUM('Draw #4'!E126:F126) -> 0 | F126: 0 | G126: =SUM('Draw #4'!G126)+'Draw #5'!F126 -> 0 | H126: =SUM(G126-J126) -> 0 | I126: 0 | J126: =SUM(I126+'Draw #4'!J126) -> 0 | K126: =IF(J126=0,"",J126/G126)
A127: ='SCHEDULE OF VALUE WORKSHEET'!A97 -> 92 | B127: ='SCHEDULE OF VALUE WORKSHEET'!B97 -> Open Item | D127: =SUM('SCHEDULE OF VALUE WORKSHEET'!E97) -> 0 | E127: =SUM('Draw #4'!E127:F127) -> 0 | F127: 0 | G127: =SUM('Draw #4'!G127)+'Draw #5'!F127 -> 0 | H127: =SUM(G127-J127) -> 0 | I127: 0 | J127: =SUM(I127+'Draw #4'!J127) -> 0 | K127: =IF(J127=0,"",J127/G127)
A128: ='SCHEDULE OF VALUE WORKSHEET'!A98 -> 93 | B128: ='SCHEDULE OF VALUE WORKSHEET'!B98 -> Open Item | D128: =SUM('SCHEDULE OF VALUE WORKSHEET'!E98) -> 0 | E128: =SUM('Draw #4'!E128:F128) -> 0 | F128: 0 | G128: =SUM('Draw #4'!G128)+'Draw #5'!F128 -> 0 | H128: =SUM(G128-J128) -> 0 | I128: 0 | J128: =SUM(I128+'Draw #4'!J128) -> 0 | K128: =IF(J128=0,"",J128/G128)
... A134: ='SCHEDULE OF VALUE WORKSHEET'!A104 -> 99 | B134: ='SCHEDULE OF VALUE WORKSHEET'!B104 -> Open Item | D134: =SUM('SCHEDULE OF VALUE WORKSHEET'!E104) -> 0 | E134: =SUM('Draw #4'!E134:F134) -> 0 | F134: 0 | G134: =SUM('Draw #4'!G134)+'Draw #5'!F134 -> 0 | H134: =SUM(G134-J134) -> 0 | I134: 0 | J134: =SUM(I134+'Draw #4'!J134) -> 0 | K134: =IF(J134=0,"",J134/G134)
A135: ='SCHEDULE OF VALUE WORKSHEET'!#REF! -> #REF! | B135: ='SCHEDULE OF VALUE WORKSHEET'!#REF! -> #REF! | D135: =SUM('SCHEDULE OF VALUE WORKSHEET'!#REF!) -> #REF! | E135: =SUM('Draw #4'!E135:F135) -> 0 | F135: 0 | G135: =SUM('Draw #4'!G135)+'Draw #5'!F135 -> #REF! | H135: =SUM(G135-J135) -> #REF! | I135: 0 | J135: =SUM(I135+'Draw #4'!J135) -> 0 | K135: =IF(J135=0,"",J135/G135)
B137: TOTAL | D137: =SUM(D10:D135) -> #REF! | E137: =SUM(E10:E135) -> 0 | F137: =SUM(F10:F135) -> 0 | G137: =SUM(G10:G135) -> #REF! | H137: =SUM(H10:H135) -> #REF! | I137: =SUM(I10:I135) -> 0 | J137: =SUM(J10:J135) -> 0

Sheet Draw #6
A1: GENESIS CAPITAL DRAW FORM
B3: CLIENT: | C3: ='SCHEDULE OF VALUE WORKSHEET'!$B$3 -> Angeleno Investments | I3: TOTAL COMPLETED TO DATE: | J3: =SUM(J137) -> 0 | K3: =SUM(J3)/J7 -> #REF!
B4: DATE: | C4: =TODAY() -> 45978 | I4: REMAINING $ IN BUDGET: | J4: =SUM(H137) -> #REF!
B5: PROJECT: | C5: ='SCHEDULE OF VALUE WORKSHEET'!B5 -> 10910 Huston Street | I5: ORIGINAL SCHEDULE OF VALUES: | J5: =SUM(D137) -> #REF!
B6: DRAW REQUEST: | C6: =SUM(I137) -> 0 | I6: CHANGE ORDERS: | J6: =SUM(F137) -> 0
I7: REVISED SCHEDULE OF VALUES: | J7: =SUM(G137) -> #REF!
B8: DESCRIPTION OF WORK | D8: SCHEDULED VALUES | E8: PREVIOUS | F8: + / - CHANGES | G8: REVISED VALUES | H8: REMAINING | I8: DRAW | J8: COMPLETED AND
E9: CHANGES | H9: BUDGET | I9: 6 | J9: STORED TO DATE
A10: ='SCHEDULE OF VALUE WORKSHEET'!A7 -> 1 | B10: ='SCHEDULE OF VALUE WORKSHEET'!B7 -> SOFT COSTS | D10: =SUM('SCHEDULE OF VALUE WORKSHEET'!E7) -> 0 | E10: =SUM('Draw #5'!E10:F10) -> 0 | F10: 0 | G10: =SUM('Draw #5'!G10)+F10 -> 0 | H10: =SUM(G10-J10) -> 0 | I10: 0 | J10: =SUM(I10+'Draw #5'!J10) -> 0 | K10: =IF(J10=0,"",J10/G10)
A11: ='SCHEDULE OF VALUE WORKSHEET'!A8 -> 2 | B11: ='SCHEDULE OF VALUE WORKSHEET'!B8 -> Site Security | D11: =SUM('SCHEDULE OF VALUE WORKSHEET'!E8) -> 10580.63 | E11: =SUM('Draw #5'!E11:F11) -> 0 | F11: 0 | G11: =SUM('Draw #5'!G11)+F11 -> 10580.63 | H11: =SUM(G11-J11) -> 10580.63 | I11: 0 | J11: =SUM(I11+'Draw #5'!J11) -> 0 | K11: =IF(J11=0,"",J11/G11)
A12: ='SCHEDULE OF VALUE WORKSHEET'!A9 -> 3 | B12: ='SCHEDULE OF VALUE WORKSHEET'!B9 -> Soils Inspection | D12: =SUM('SCHEDULE OF VALUE WORKSHEET'!E9) -> 0 | E12: =SUM('Draw #5'!E12:F12) -> 0 | F12: 0 | G12: =SUM('Draw #5'!G12)+F12 -> 0 | H12: =SUM(G12-J12) -> 0 | I12: 0 | J12: =SUM(I12+'Draw #5'!J12) -> 0 | K12: =IF(J12=0,"",J12/G12)
A13: ='SCHEDULE OF VALUE WORKSHEET'!A10 -> 4 | B13: ='SCHEDULE OF VALUE WORKSHEET'!B10 -> Offsites (Transformer) | D13: =SUM('SCHEDULE OF VALUE WORKSHEET'!E10) -> 20000 | E13: =SUM('Draw #5'!E13:F13) -> 0 | F13: 0 | G13: =SUM('Draw #5'!G13)+F13 -> 20000 | H13: =SUM(G13-J13) -> 20000 | I13: 0 | J13: =SUM(I13+'Draw #5'!J13) -> 0 | K13: =IF(J13=0,"",J13/G13)
A14: ='SCHEDULE OF VALUE WORKSHEET'!A11 -> 5 | B14: ='SCHEDULE OF VALUE WORKSHEET'!B11 -> Plan Check Fees | D14: =SUM('SCHEDULE OF VALUE WORKSHEET'!E11) -> 0 | E14: =SUM('Draw #5'!E14:F14) -> 0 | F14: 0 | G14: =SUM('Draw #5'!G14)+F14 -> 0 | H14: =SUM(G14-J14) -> 0 | I14: 0 | J14: =SUM(I14+'Draw #5'!J14) -> 0 | K14: =IF(J14=0,"",J14/G14)
A15: ='SCHEDULE OF VALUE WORKSHEET'!A12 -> 6 | B15: ='SCHEDULE OF VALUE WORKSHEET'!B12 -> Permits | D15: =SUM('SCHEDULE OF VALUE WORKSHEET'!E12) -> 0 | E15: =SUM('Draw #5'!E15:F15) -> 0 | F15: 0 | G15: =SUM('Draw #5'!G15)+F15 -> 0 | H15: =SUM(G15-J15) -> 0 | I15: 0 | J15: =SUM(I15+'Draw #5'!J15) -> 0 | K15: =IF(J15=0,"",J15/G15)
A16: ='SCHEDULE OF VALUE WORKSHEET'!A13 -> 7 | B16: ='SCHEDULE OF VALUE WORKSHEET'!B13 -> Survey | D16: =SUM('SCHEDULE OF VALUE WORKSHEET'!E13) -> 0 | E16: =SUM('Draw #5'!E16:F16) -> 0 | F16: 0 | G16: =SUM('Draw #5'!G16)+F16 -> 0 | H16: =SUM(G16-J16) -> 0 | I16: 0 | J16: =SUM(I16+'Draw #5'!J16) -> 0 | K16: =IF(J16=0,"",J16/G16)
A17: ='SCHEDULE OF VALUE WORKSHEET'!A14 -> 8 | B17: ='SCHEDULE OF VALUE WORKSHEET'!B14 -> Soils Engineer | D17: =SUM('SCHEDULE OF VALUE WORKSHEET'!E14) -> 0 | E17: =SUM('Draw #5'!E17:F17) -> 0 | F17: 0 | G17: =SUM('Draw #5'!G17)+F17 -> 0 | H17: =SUM(G17-J17) -> 0 | I17: 0 | J17: =SUM(I17+'Draw #5'!J17) -> 0 | K17: =IF(J17=0,"",J17/G17)
A18: ='SCHEDULE OF VALUE WORKSHEET'!A15 -> 9 | B18: ='SCHEDULE OF VALUE WORKSHEET'!B15 -> Soils Permit + T24 | D18: =SUM('SCHEDULE OF VALUE WORKSHEET'!E15) -> 2500 | E18: =SUM('Draw #5'!E18:F18) -> 0 | F18: 0 | G18: =SUM('Draw #5'!G18)+F18 -> 2500 | H18: =SUM(G18-J18) -> 2500 | I18: 0 | J18: =SUM(I18+'Draw #5'!J18) -> 0 | K18: =IF(J18=0,"",J18/G18)
A19: ='SCHEDULE OF VALUE WORKSHEET'!A16 -> 10 | B19: ='SCHEDULE OF VALUE WORKSHEET'!B16 -> Special Inspections - Deputy | D19: =SUM('SCHEDULE OF VALUE WORKSHEET'!E16) -> 15000 | E19: =SUM('Draw #5'!E19:F19) -> 0 | F19: 0 | G19: =SUM('Draw #5'!G19)+F19 -> 15000 | H19: =SUM(G19-J19) -> 15000 | I19: 0 | J19: =SUM(I19+'Draw #5'!J19) -> 0 | K19: =IF(J19=0,"",J19/G19)
A20: ='SCHEDULE OF VALUE WORKSHEET'!A17 -> 11 | B20: ='SCHEDULE OF VALUE WORKSHEET'!B17 -> Architect | D20: =SUM('SCHEDULE OF VALUE WORKSHEET'!E17) -> 0 | E20: =SUM('Draw #5'!E20:F20) -> 0 | F20: 0 | G20: =SUM('Draw #5'!G20)+F20 -> 0 | H20: =SUM(G20-J20) -> 0 | I20: 0 | J20: =SUM(I20+'Draw #5'!J20) -> 0 | K20: =IF(J20=0,"",J20/G20)
A21: ='SCHEDULE OF VALUE WORKSHEET'!A18 -> 12 | B21: ='SCHEDULE OF VALUE WORKSHEET'!B18 -> Structural Engineer | D21: =SUM('SCHEDULE OF VALUE WORKSHEET'!E18) -> 0 | E21: =SUM('Draw #5'!E21:F21) -> 0 | F21: 0 | G21: =SUM('Draw #5'!G21)+F21 -> 0 | H21: =SUM(G21-J21) -> 0 | I21: 0 | J21: =SUM(I21+'Draw #5'!J21) -> 0 | K21: =IF(J21=0,"",J21/G21)
... A45: ='SCHEDULE OF VALUE WORKSHEET'!A42 -> 36 | B45: ='SCHEDULE OF VALUE WORKSHEET'!B42 -> Construction Management / Observation (OO) | D45: =SUM('SCHEDULE OF VALUE WORKSHEET'!E42) -> 49427.9 | E45: =SUM('Draw #5'!E45:F45) -> 0 | F45: 0 | G45: =SUM('Draw #5'!G45)+F45 -> 49427.9 | H45: =SUM(G45-J45) -> 49427.9 | I45: 0 | J45: =SUM(I45+'Draw #5'!J45) -> 0 | K45: =IF(J45=0,"",J45/G45)
A46: ='SCHEDULE OF VALUE WORKSHEET'!#REF! -> #REF! | B46: ='SCHEDULE OF VALUE WORKSHEET'!#REF! -> #REF! | D46: =SUM('SCHEDULE OF VALUE WORKSHEET'!#REF!) -> #REF! | E46: =SUM('Draw #5'!E46:F46) -> 0 | F46: 0 | G46: =SUM('Draw #5'!G46)+F46 -> #REF! | H46: =SUM(G46-J46) -> #REF! | I46: 0 | J46: =SUM(I46+'Draw #5'!J46) -> 0 | K46: =IF(J46=0,"",J46/G46)
A47: ='SCHEDULE OF VALUE WORKSHEET'!A43 -> 37 | B47: ='SCHEDULE OF VALUE WORKSHEET'!B43 -> CMFA Startup Fee | D47: =SUM('SCHEDULE OF VALUE WORKSHEET'!E43) -> 22800 | E47: =SUM('Draw #5'!E47:F47) -> 0 | F47: 0 | G47: =SUM('Draw #5'!G47)+F47 -> 22800 | H47: =SUM(G47-J47) -> 22800 | I47: 0 | J47: =SUM(I47+'Draw #5'!J47) -> 0 | K47: =IF(J47=0,"",J47/G47)
A48: ='SCHEDULE OF VALUE WORKSHEET'!A44 -> 38 | B48: ='SCHEDULE OF VALUE WORKSHEET'!B44 -> Non-Profit Start Up Fee | D48: =SUM('SCHEDULE OF VALUE WORKSHEET'!E44) -> 25000 | E48: =SUM('Draw #5'!E48:F48) -> 0 | F48: 0 | G48: =SUM('Draw #5'!G48)+F48 -> 25000 | H48: =SUM(G48-J48) -> 25000 | I48: 0 | J48: =SUM(I48+'Draw #5'!J48) -> 0 | K48: =IF(J48=0,"",J48/G48)
A49: ='SCHEDULE OF VALUE WORKSHEET'!A45 -> 39 | B49: ='SCHEDULE OF VALUE WORKSHEET'!B45 -> CMFA Construction Fee | D49: =SUM('SCHEDULE OF VALUE WORKSHEET'!E45) -> 12000 | E49: =SUM('Draw #5'!E49:F49) -> 0 | F49: 0 | G49: =SUM('Draw #5'!G49)+F49 -> 12000 | H49: =SUM(G49-J49) -> 12000 | I49: 0 | J49: =SUM(I49+'Draw #5'!J49) -> 0 | K49: =IF(J49=0,"",J49/G49)
A50: ='SCHEDULE OF VALUE WORKSHEET'!A46 -> 40 | B50: ='SCHEDULE OF VALUE WORKSHEET'!B46 -> Non-Profit Construction Fee | D50: =SUM('SCHEDULE OF VALUE WORKSHEET'!E46) -> 10000 | E50: =SUM('Draw #5'!E50:F50) -> 0 | F50: 0 | G50: =SUM('Draw #5'!G50)+F50 -> 10000 | H50: =SUM(G50-J50) -> 10000 | I50: 0 | J50: =SUM(I50+'Draw #5'!J50) -> 0 | K50: =IF(J50=0,"",J50/G50)
A51: ='SCHEDULE OF VALUE WORKSHEET'!A47 -> 41 | B51: ='SCHEDULE OF VALUE WORKSHEET'!B47 -> WTE Legal Costs for CMFA & Non-Profit Partner | D51: =SUM('SCHEDULE OF VALUE WORKSHEET'!E47) -> 20000 | E51: =SUM('Draw #5'!E51:F51) -> 0 | F51: 0 | G51: =SUM('Draw #5'!G51)+F51 -> 20000 | H51: =SUM(G51-J51) -> 20000 | I51: 0 | J51: =SUM(I51+'Draw #5'!J51) -> 0 | K51: =IF(J51=0,"",J51/G51)
A52: ='SCHEDULE OF VALUE WORKSHEET'!#REF! -> #REF! | B52: ='SCHEDULE OF VALUE WORKSHEET'!#REF! -> #REF! | D52: =SUM('SCHEDULE OF VALUE WORKSHEET'!#REF!) -> #REF! | E52: =SUM('Draw #5'!E52:F52) -> 0 | F52: 0 | G52: =SUM('Draw #5'!G52)+F52 -> #REF! | H52: =SUM(G52-J52) -> #REF! | I52: 0 | J52: =SUM(I52+'Draw #5'!J52) -> 0 | K52: =IF(J52=0,"",J52/G52)
A53: ='SCHEDULE OF VALUE WORKSHEET'!A49 -> 43 | B53: ='SCHEDULE OF VALUE WORKSHEET'!B49 -> GENERAL CONDITIONS | D53: =SUM('SCHEDULE OF VALUE WORKSHEET'!E49) -> 362115.24 | E53: =SUM('Draw #5'!E53:F53) -> 0 | F53: 0 | G53: =SUM('Draw #5'!G53)+F53 -> 362115.24 | H53: =SUM(G53-J53) -> 362115.24 | I53: 0 | J53: =SUM(I53+'Draw #5'!J53) -> 0 | K53: =IF(J53=0,"",J53/G53)
A54: ='SCHEDULE OF VALUE WORKSHEET'!A50 -> 44 | B54: ='SCHEDULE OF VALUE WORKSHEET'!B50 -> GENERAL REQUIREMENT | D54: =SUM('SCHEDULE OF VALUE WORKSHEET'!E50) -> 124657.88 | E54: =SUM('Draw #5'!E54:F54) -> 0 | F54: 0 | G54: =SUM('Draw #5'!G54)+F54 -> 124657.88 | H54: =SUM(G54-J54) -> 124657.88 | I54: 0 | J54: =SUM(I54+'Draw #5'!J54) -> 0 | K54: =IF(J54=0,"",J54/G54)
A55: ='SCHEDULE OF VALUE WORKSHEET'!A51 -> 45 | B55: ='SCHEDULE OF VALUE WORKSHEET'!B51 -> SITE WORK | D55: =SUM('SCHEDULE OF VALUE WORKSHEET'!E51) -> 139049.51 | E55: =SUM('Draw #5'!E55:F55) -> 0 | F55: 0 | G55: =SUM('Draw #5'!G55)+F55 -> 139049.51 | H55: =SUM(G55-J55) -> 139049.51 | I55: 0 | J55: =SUM(I55+'Draw #5'!J55) -> 0 | K55: =IF(J55=0,"",J55/G55)
A56: ='SCHEDULE OF VALUE WORKSHEET'!A52 -> 46 | B56: ='SCHEDULE OF VALUE WORKSHEET'!B52 -> CONCRETE | D56: =SUM('SCHEDULE OF VALUE WORKSHEET'!E52) -> 253182 | E56: =SUM('Draw #5'!E56:F56) -> 0 | F56: 0 | G56: =SUM('Draw #5'!G56)+F56 -> 253182 | H56: =SUM(G56-J56) -> 253182 | I56: 0 | J56: =SUM(I56+'Draw #5'!J56) -> 0 | K56: =IF(J56=0,"",J56/G56)
A57: ='SCHEDULE OF VALUE WORKSHEET'!A53 -> 47 | B57: ='SCHEDULE OF VALUE WORKSHEET'!B53 -> MASONRY | D57: =SUM('SCHEDULE OF VALUE WORKSHEET'!E53) -> 3562.64 | E57: =SUM('Draw #5'!E57:F57) -> 0 | F57: 0 | G57: =SUM('Draw #5'!G57)+F57 -> 3562.64 | H57: =SUM(G57-J57) -> 3562.64 | I57: 0 | J57: =SUM(I57+'Draw #5'!J57) -> 0 | K57: =IF(J57=0,"",J57/G57)
A58: ='SCHEDULE OF VALUE WORKSHEET'!A54 -> 48 | B58: ='SCHEDULE OF VALUE WORKSHEET'!B54 -> METALS | D58: =SUM('SCHEDULE OF VALUE WORKSHEET'!E54) -> 324100 | E58: =SUM('Draw #5'!E58:F58) -> 0 | F58: 0 | G58: =SUM('Draw #5'!G58)+F58 -> 324100 | H58: =SUM(G58-J58) -> 324100 | I58: 0 | J58: =SUM(I58+'Draw #5'!J58) -> 0 | K58: =IF(J58=0,"",J58/G58)
A59: ='SCHEDULE OF VALUE WORKSHEET'!A55 -> 49 | B59: ='SCHEDULE OF VALUE WORKSHEET'!B55 -> FRAMING | D59: =SUM('SCHEDULE OF VALUE WORKSHEET'!E55) -> 818554 | E59: =SUM('Draw #5'!E59:F59) -> 0 | F59: 0 | G59: =SUM('Draw #5'!G59)+F59 -> 818554 | H59: =SUM(G59-J59) -> 818554 | I59: 0 | J59: =SUM(I59+'Draw #5'!J59) -> 0 | K59: =IF(J59=0,"",J59/G59)
A60: ='SCHEDULE OF VALUE WORKSHEET'!A56 -> 50 | B60: ='SCHEDULE OF VALUE WORKSHEET'!B56 -> COUNTERTOPS | D60: =SUM('SCHEDULE OF VALUE WORKSHEET'!E56) -> 56930 | E60: =SUM('Draw #5'!E60:F60) -> 0 | F60: 0 | G60: =SUM('Draw #5'!G60)+F60 -> 56930 | H60: =SUM(G60-J60) -> 56930 | I60: 0 | J60: =SUM(I60+'Draw #5'!J60) -> 0 | K60: =IF(J60=0,"",J60/G60)
A61: ='SCHEDULE OF VALUE WORKSHEET'!A57 -> 51 | B61: ='SCHEDULE OF VALUE WORKSHEET'!B57 -> CABINETS | D61: =SUM('SCHEDULE OF VALUE WORKSHEET'!E57) -> 56930 | E61: =SUM('Draw #5'!E61:F61) -> 0 | F61: 0 | G61: =SUM('Draw #5'!G61)+F61 -> 56930 | H61: =SUM(G61-J61) -> 56930 | I61: 0 | J61: =SUM(I61+'Draw #5'!J61) -> 0 | K61: =IF(J61=0,"",J61/G61)
A62: ='SCHEDULE OF VALUE WORKSHEET'!A58 -> 52 | B62: ='SCHEDULE OF VALUE WORKSHEET'!B58 -> THERMAL MOISTURE PROTECTION | D62: =SUM('SCHEDULE OF VALUE WORKSHEET'!E58) -> 173148 | E62: =SUM('Draw #5'!E62:F62) -> 0 | F62: 0 | G62: =SUM('Draw #5'!G62)+F62 -> 173148 | H62: =SUM(G62-J62) -> 173148 | I62: 0 | J62: =SUM(I62+'Draw #5'!J62) -> 0 | K62: =IF(J62=0,"",J62/G62)
A63: ='SCHEDULE OF VALUE WORKSHEET'!A59 -> 53 | B63: ='SCHEDULE OF VALUE WORKSHEET'!B59 -> DOORS | D63: =SUM('SCHEDULE OF VALUE WORKSHEET'!E59) -> 204087.33 | E63: =SUM('Draw #5'!E63:F63) -> 0 | F63: 0 | G63: =SUM('Draw #5'!G63)+F63 -> 204087.33 | H63: =SUM(G63-J63) -> 204087.33 | I63: 0 | J63: =SUM(I63+'Draw #5'!J63) -> 0 | K63: =IF(J63=0,"",J63/G63)
A64: ='SCHEDULE OF VALUE WORKSHEET'!A60 -> 54 | B64: ='SCHEDULE OF VALUE WORKSHEET'!B60 -> WINDOWS | D64: =SUM('SCHEDULE OF VALUE WORKSHEET'!E60) -> 106274.25 | E64: =SUM('Draw #5'!E64:F64) -> 0 | F64: 0 | G64: =SUM('Draw #5'!G64)+F64 -> 106274.25 | H64: =SUM(G64-J64) -> 106274.25 | I64: 0 | J64: =SUM(I64+'Draw #5'!J64) -> 0 | K64: =IF(J64=0,"",J64/G64)
... A90: ='SCHEDULE OF VALUE WORKSHEET'!A86 -> 80 | B90: ='SCHEDULE OF VALUE WORKSHEET'!B86 -> FINANCING COSTS | D90: =SUM('SCHEDULE OF VALUE WORKSHEET'!E86) -> 0 | E90: =SUM('Draw #5'!E90:F90) -> 0 | F90: 0 | G90: =SUM('Draw #5'!G90)+F90 -> 0 | H90: =SUM(G90-J90) -> 0 | I90: 0 | J90: =SUM(I90+'Draw #5'!J90) -> 0 | K90: =IF(J90=0,"",J90/G90)
A91: ='SCHEDULE OF VALUE WORKSHEET'!#REF! -> #REF! | B91: ='SCHEDULE OF VALUE WORKSHEET'!#REF! -> #REF! | D91: =SUM('SCHEDULE OF VALUE WORKSHEET'!#REF!) -> #REF! | E91: =SUM('Draw #5'!E91:F91) -> 0 | F91: 0 | G91: =SUM('Draw #5'!G91)+F91 -> #REF! | H91: =SUM(G91-J91) -> #REF! | I91: 0 | J91: =SUM(I91+'Draw #5'!J91) -> 0 | K91: =IF(J91=0,"",J91/G91)
A92: ='SCHEDULE OF VALUE WORKSHEET'!#REF! -> #REF! | B92: ='SCHEDULE OF VALUE WORKSHEET'!#REF! -> #REF! | D92: =SUM('SCHEDULE OF VALUE WORKSHEET'!#REF!) -> #REF! | E92: =SUM('Draw #5'!E92:F92) -> 0 | F92: 0 | G92: =SUM('Draw #5'!G92)+F92 -> #REF! | H92: =SUM(G92-J92) -> #REF! | I92: 0 | J92: =SUM(I92+'Draw #5'!J92) -> 0 | K92: =IF(J92=0,"",J92/G92)
A93: ='SCHEDULE OF VALUE WORKSHEET'!#REF! -> #REF! | B93: ='SCHEDULE OF VALUE WORKSHEET'!#REF! -> #REF! | D93: =SUM('SCHEDULE OF VALUE WORKSHEET'!#REF!) -> #REF! | E93: =SUM('Draw #5'!E93:F93) -> 0 | F93: 0 | G93: =SUM('Draw #5'!G93)+F93 -> #REF! | H93: =SUM(G93-J93) -> #REF! | I93: 0 | J93: =SUM(I93+'Draw #5'!J93) -> 0 | K93: =IF(J93=0,"",J93/G93)
A94: ='SCHEDULE OF VALUE WORKSHEET'!#REF! -> #REF! | B94: ='SCHEDULE OF VALUE WORKSHEET'!#REF! -> #REF! | D94: =SUM('SCHEDULE OF VALUE WORKSHEET'!#REF!) -> #REF! | E94: =SUM('Draw #5'!E94:F94) -> 0 | F94: 0 | G94: =SUM('Draw #5'!G94)+F94 -> #REF! | H94: =SUM(G94-J94) -> #REF! | I94: 0 | J94: =SUM(I94+'Draw #5'!J94) -> 0 | K94: =IF(J94=0,"",J94/G94)
A95: ='SCHEDULE OF VALUE WORKSHEET'!#REF! -> #REF! | B95: ='SCHEDULE OF VALUE WORKSHEET'!#REF! -> #REF! | D95: =SUM('SCHEDULE OF VALUE WORKSHEET'!#REF!) -> #REF! | E95: =SUM('Draw #5'!E95:F95) -> 0 | F95: 0 | G95: =SUM('Draw #5'!G95)+F95 -> #REF! | H95: =SUM(G95-J95) -> #REF! | I95: 0 | J95: =SUM(I95+'Draw #5'!J95) -> 0 | K95: =IF(J95=0,"",J95/G95)
A96: ='SCHEDULE OF VALUE WORKSHEET'!#REF! -> #REF! | B96: ='SCHEDULE OF VALUE WORKSHEET'!#REF! -> #REF! | D96: =SUM('SCHEDULE OF VALUE WORKSHEET'!#REF!) -> #REF! | E96: =SUM('Draw #5'!E96:F96) -> 0 | F96: 0 | G96: =SUM('Draw #5'!G96)+F96 -> #REF! | H96: =SUM(G96-J96) -> #REF! | I96: 0 | J96: =SUM(I96+'Draw #5'!J96) -> 0 | K96: =IF(J96=0,"",J96/G96)
A97: ='SCHEDULE OF VALUE WORKSHEET'!#REF! -> #REF! | B97: ='SCHEDULE OF VALUE WORKSHEET'!#REF! -> #REF! | D97: =SUM('SCHEDULE OF VALUE WORKSHEET'!#REF!) -> #REF! | E97: =SUM('Draw #5'!E97:F97) -> 0 | F97: 0 | G97: =SUM('Draw #5'!G97)+F97 -> #REF! | H97: =SUM(G97-J97) -> #REF! | I97: 0 | J97: =SUM(I97+'Draw #5'!J97) -> 0 | K97: =IF(J97=0,"",J97/G97)
A98: ='SCHEDULE OF VALUE WORKSHEET'!#REF! -> #REF! | B98: ='SCHEDULE OF VALUE WORKSHEET'!#REF! -> #REF! | D98: =SUM('SCHEDULE OF VALUE WORKSHEET'!#REF!) -> #REF! | E98: =SUM('Draw #5'!E98:F98) -> 0 | F98: 0 | G98: =SUM('Draw #5'!G98)+F98 -> #REF! | H98: =SUM(G98-J98) -> #REF! | I98: 0 | J98: =SUM(I98+'Draw #5'!J98) -> 0 | K98: =IF(J98=0,"",J98/G98)
A99: ='SCHEDULE OF VALUE WORKSHEET'!#REF! -> #REF! | B99: ='SCHEDULE OF VALUE WORKSHEET'!#REF! -> #REF! | D99: =SUM('SCHEDULE OF VALUE WORKSHEET'!#REF!) -> #REF! | E99: =SUM('Draw #5'!E99:F99) -> 0 | F99: 0 | G99: =SUM('Draw #5'!G99)+F99 -> #REF! | H99: =SUM(G99-J99) -> #REF! | I99: 0 | J99: =SUM(I99+'Draw #5'!J99) -> 0 | K99: =IF(J99=0,"",J99/G99)
A100: ='SCHEDULE OF VALUE WORKSHEET'!#REF! -> #REF! | B100: ='SCHEDULE OF VALUE WORKSHEET'!#REF! -> #REF! | D100: =SUM('SCHEDULE OF VALUE WORKSHEET'!#REF!) -> #REF! | E100: =SUM('Draw #5'!E100:F100) -> 0 | F100: 0 | G100: =SUM('Draw #5'!G100)+F100 -> #REF! | H100: =SUM(G100-J100) -> #REF! | I100: 0 | J100: =SUM(I100+'Draw #5'!J100) -> 0 | K100: =IF(J100=0,"",J100/G100)
A101: ='SCHEDULE OF VALUE WORKSHEET'!#REF! -> #REF! | B101: ='SCHEDULE OF VALUE WORKSHEET'!#REF! -> #REF! | D101: =SUM('SCHEDULE OF VALUE WORKSHEET'!#REF!) -> #REF! | E101: =SUM('Draw #5'!E101:F101) -> 0 | F101: 0 | G101: =SUM('Draw #5'!G101)+F101 -> #REF! | H101: =SUM(G101-J101) -> #REF! | I101: 0 | J101: =SUM(I101+'Draw #5'!J101) -> 0 | K101: =IF(J101=0,"",J101/G101)
A102: ='SCHEDULE OF VALUE WORKSHEET'!#REF! -> #REF! | B102: ='SCHEDULE OF VALUE WORKSHEET'!#REF! -> #REF! | D102: =SUM('SCHEDULE OF VALUE WORKSHEET'!#REF!) -> #REF! | E102: =SUM('Draw #5'!E102:F102) -> 0 | F102: 0 | G102: =SUM('Draw #5'!G102)+F102 -> #REF! | H102: =SUM(G102-J102) -> #REF! | I102: 0 | J102: =SUM(I102+'Draw #5'!J102) -> 0 | K102: =IF(J102=0,"",J102/G102)
... A116: ='SCHEDULE OF VALUE WORKSHEET'!#REF! -> #REF! | B116: ='SCHEDULE OF VALUE WORKSHEET'!#REF! -> #REF! | D116: =SUM('SCHEDULE OF VALUE WORKSHEET'!#REF!) -> #REF! | E116: =SUM('Draw #5'!E116:F116) -> 0 | F116: 0 | G116: =SUM('Draw #5'!G116)+F116 -> #REF! | H116: =SUM(G116-J116) -> #REF! | I116: 0 | J116: =SUM(I116+'Draw #5'!J116) -> 0 | K116: =IF(J116=0,"",J116/G116)
A117: ='SCHEDULE OF VALUE WORKSHEET'!A87 -> 82 | B117: ='SCHEDULE OF VALUE WORKSHEET'!B87 -> Open Item | D117: =SUM('SCHEDULE OF VALUE WORKSHEET'!E87) -> 0 | E117: =SUM('Draw #5'!E117:F117) -> 0 | F117: 0 | G117: =SUM('Draw #5'!G117)+F117 -> 0 | H117: =SUM(G117-J117) -> 0 | I117: 0 | J117: =SUM(I117+'Draw #5'!J117) -> 0 | K117: =IF(J117=0,"",J117/G117)
A118: ='SCHEDULE OF VALUE WORKSHEET'!A88 -> 83 | B118: ='SCHEDULE OF VALUE WORKSHEET'!B88 -> Open Item | D118: =SUM('SCHEDULE OF VALUE WORKSHEET'!E88) -> 0 | E118: =SUM('Draw #5'!E118:F118) -> 0 | F118: 0 | G118: =SUM('Draw #5'!G118)+F118 -> 0 | H118: =SUM(G118-J118) -> 0 | I118: 0 | J118: =SUM(I118+'Draw #5'!J118) -> 0 | K118: =IF(J118=0,"",J118/G118)
A119: ='SCHEDULE OF VALUE WORKSHEET'!A89 -> 84 | B119: ='SCHEDULE OF VALUE WORKSHEET'!B89 -> Open Item | D119: =SUM('SCHEDULE OF VALUE WORKSHEET'!E89) -> 0 | E119: =SUM('Draw #5'!E119:F119) -> 0 | F119: 0 | G119: =SUM('Draw #5'!G119)+F119 -> 0 | H119: =SUM(G119-J119) -> 0 | I119: 0 | J119: =SUM(I119+'Draw #5'!J119) -> 0 | K119: =IF(J119=0,"",J119/G119)
A120: ='SCHEDULE OF VALUE WORKSHEET'!A90 -> 85 | B120: ='SCHEDULE OF VALUE WORKSHEET'!B90 -> Open Item | D120: =SUM('SCHEDULE OF VALUE WORKSHEET'!E90) -> 0 | E120: =SUM('Draw #5'!E120:F120) -> 0 | F120: 0 | G120: =SUM('Draw #5'!G120)+F120 -> 0 | H120: =SUM(G120-J120) -> 0 | I120: 0 | J120: =SUM(I120+'Draw #5'!J120) -> 0 | K120: =IF(J120=0,"",J120/G120)
A121: ='SCHEDULE OF VALUE WORKSHEET'!A91 -> 86 | B121: ='SCHEDULE OF VALUE WORKSHEET'!B91 -> Open Item | D121: =SUM('SCHEDULE OF VALUE WORKSHEET'!E91) -> 0 | E121: =SUM('Draw #5'!E121:F121) -> 0 | F121: 0 | G121: =SUM('Draw #5'!G121)+F121 -> 0 | H121: =SUM(G121-J121) -> 0 | I121: 0 | J121: =SUM(I121+'Draw #5'!J121) -> 0 | K121: =IF(J121=0,"",J121/G121)
A122: ='SCHEDULE OF VALUE WORKSHEET'!A92 -> 87 | B122: ='SCHEDULE OF VALUE WORKSHEET'!B92 -> Open Item | D122: =SUM('SCHEDULE OF VALUE WORKSHEET'!E92) -> 0 | E122: =SUM('Draw #5'!E122:F122) -> 0 | F122: 0 | G122: =SUM('Draw #5'!G122)+F122 -> 0 | H122: =SUM(G122-J122) -> 0 | I122: 0 | J122: =SUM(I122+'Draw #5'!J122) -> 0 | K122: =IF(J122=0,"",J122/G122)
A123: ='SCHEDULE OF VALUE WORKSHEET'!A93 -> 88 | B123: ='SCHEDULE OF VALUE WORKSHEET'!B93 -> Open Item | D123: =SUM('SCHEDULE OF VALUE WORKSHEET'!E93) -> 0 | E123: =SUM('Draw #5'!E123:F123) -> 0 | F123: 0 | G123: =SUM('Draw #5'!G123)+F123 -> 0 | H123: =SUM(G123-J123) -> 0 | I123: 0 | J123: =SUM(I123+'Draw #5'!J123) -> 0 | K123: =IF(J123=0,"",J123/G123)
A124: ='SCHEDULE OF VALUE WORKSHEET'!A94 -> 89 | B124: ='SCHEDULE OF VALUE WORKSHEET'!B94 -> Open Item | D124: =SUM('SCHEDULE OF VALUE WORKSHEET'!E94) -> 0 | E124: =SUM('Draw #5'!E124:F124) -> 0 | F124: 0 | G124: =SUM('Draw #5'!G124)+F124 -> 0 | H124: =SUM(G124-J124) -> 0 | I124: 0 | J124: =SUM(I124+'Draw #5'!J124) -> 0 | K124: =IF(J124=0,"",J124/G124)
A125: ='SCHEDULE OF VALUE WORKSHEET'!A95 -> 90 | B125: ='SCHEDULE OF VALUE WORKSHEET'!B95 -> Open Item | D125: =SUM('SCHEDULE OF VALUE WORKSHEET'!E95) -> 0 | E125: =SUM('Draw #5'!E125:F125) -> 0 | F125: 0 | G125: =SUM('Draw #5'!G125)+F125 -> 0 | H125: =SUM(G125-J125) -> 0 | I125: 0 | J125: =SUM(I125+'Draw #5'!J125) -> 0 | K125: =IF(J125=0,"",J125/G125)
A126: ='SCHEDULE OF VALUE WORKSHEET'!A96 -> 91 | B126: ='SCHEDULE OF VALUE WORKSHEET'!B96 -> Open Item | D126: =SUM('SCHEDULE OF VALUE WORKSHEET'!E96) -> 0 | E126: =SUM('Draw #5'!E126:F126) -> 0 | F126: 0 | G126: =SUM('Draw #5'!G126)+F126 -> 0 | H126: =SUM(G126-J126) -> 0 | I126: 0 | J126: =SUM(I126+'Draw #5'!J126) -> 0 | K126: =IF(J126=0,"",J126/G126)
A127: ='SCHEDULE OF VALUE WORKSHEET'!A97 -> 92 | B127: ='SCHEDULE OF VALUE WORKSHEET'!B97 -> Open Item | D127: =SUM('SCHEDULE OF VALUE WORKSHEET'!E97) -> 0 | E127: =SUM('Draw #5'!E127:F127) -> 0 | F127: 0 | G127: =SUM('Draw #5'!G127)+F127 -> 0 | H127: =SUM(G127-J127) -> 0 | I127: 0 | J127: =SUM(I127+'Draw #5'!J127) -> 0 | K127: =IF(J127=0,"",J127/G127)
A128: ='SCHEDULE OF VALUE WORKSHEET'!A98 -> 93 | B128: ='SCHEDULE OF VALUE WORKSHEET'!B98 -> Open Item | D128: =SUM('SCHEDULE OF VALUE WORKSHEET'!E98) -> 0 | E128: =SUM('Draw #5'!E128:F128) -> 0 | F128: 0 | G128: =SUM('Draw #5'!G128)+F128 -> 0 | H128: =SUM(G128-J128) -> 0 | I128: 0 | J128: =SUM(I128+'Draw #5'!J128) -> 0 | K128: =IF(J128=0,"",J128/G128)
... A134: ='SCHEDULE OF VALUE WORKSHEET'!A104 -> 99 | B134: ='SCHEDULE OF VALUE WORKSHEET'!B104 -> Open Item | D134: =SUM('SCHEDULE OF VALUE WORKSHEET'!E104) -> 0 | E134: =SUM('Draw #5'!E134:F134) -> 0 | F134: 0 | G134: =SUM('Draw #5'!G134)+F134 -> 0 | H134: =SUM(G134-J134) -> 0 | I134: 0 | J134: =SUM(I134+'Draw #5'!J134) -> 0 | K134: =IF(J134=0,"",J134/G134)
A135: ='SCHEDULE OF VALUE WORKSHEET'!#REF! -> #REF! | B135: ='SCHEDULE OF VALUE WORKSHEET'!#REF! -> #REF! | D135: =SUM('SCHEDULE OF VALUE WORKSHEET'!#REF!) -> #REF! | E135: =SUM('Draw #5'!E135:F135) -> 0 | F135: 0 | G135: =SUM('Draw #5'!G135)+F135 -> #REF! | H135: =SUM(G135-J135) -> #REF! | I135: 0 | J135: =SUM(I135+'Draw #5'!J135) -> 0 | K135: =IF(J135=0,"",J135/G135)
B137: TOTAL | D137: =SUM(D10:D135) -> #REF! | E137: =SUM(E10:E135) -> 0 | F137: =SUM(F10:F135) -> 0 | G137: =SUM(G10:G135) -> #REF! | H137: =SUM(H10:H135) -> #REF! | I137: =SUM(I10:I135) -> 0 | J137: =SUM(J10:J135) -> 0

Sheet Draw #7
A1: GENESIS CAPITAL DRAW FORM
B3: CLIENT: | C3: ='SCHEDULE OF VALUE WORKSHEET'!$B$3 -> Angeleno Investments | I3: TOTAL COMPLETED TO DATE: | J3: =SUM(J137) -> 0 | K3: =SUM(J3)/J7 -> #REF!
B4: DATE: | C4: =TODAY() -> 45978 | I4: REMAINING $ IN BUDGET: | J4: =SUM(H137) -> #REF!
B5: PROJECT: | C5: ='SCHEDULE OF VALUE WORKSHEET'!B5 -> 10910 Huston Street | I5: ORIGINAL SCHEDULE OF VALUES: | J5: =SUM(D137) -> #REF!
B6: DRAW REQUEST: | C6: =SUM(I137) -> 0 | I6: CHANGE ORDERS: | J6: =SUM(F137) -> 0
I7: REVISED SCHEDULE OF VALUES: | J7: =SUM(G137) -> #REF!
B8: DESCRIPTION OF WORK | D8: SCHEDULED VALUES | E8: PREVIOUS | F8: + / - CHANGES | G8: REVISED VALUES | H8: REMAINING | I8: DRAW | J8: COMPLETED AND
E9: CHANGES | H9: BUDGET | I9: 7 | J9: STORED TO DATE
A10: ='SCHEDULE OF VALUE WORKSHEET'!A7 -> 1 | B10: ='SCHEDULE OF VALUE WORKSHEET'!B7 -> SOFT COSTS | D10: =SUM('SCHEDULE OF VALUE WORKSHEET'!E7) -> 0 | E10: =SUM('Draw #6'!E10:F10) -> 0 | F10: 0 | G10: =SUM('Draw #6'!G10)+F10 -> 0 | H10: =SUM(G10-J10) -> 0 | I10: 0 | J10: =SUM(I10+'Draw #6'!J10) -> 0 | K10: =IF(J10=0,"",J10/G10)
A11: ='SCHEDULE OF VALUE WORKSHEET'!A8 -> 2 | B11: ='SCHEDULE OF VALUE WORKSHEET'!B8 -> Site Security | D11: =SUM('SCHEDULE OF VALUE WORKSHEET'!E8) -> 10580.63 | E11: =SUM('Draw #6'!E11:F11) -> 0 | F11: 0 | G11: =SUM('Draw #6'!G11)+F11 -> 10580.63 | H11: =SUM(G11-J11) -> 10580.63 | I11: 0 | J11: =SUM(I11+'Draw #6'!J11) -> 0 | K11: =IF(J11=0,"",J11/G11)
A12: ='SCHEDULE OF VALUE WORKSHEET'!A9 -> 3 | B12: ='SCHEDULE OF VALUE WORKSHEET'!B9 -> Soils Inspection | D12: =SUM('SCHEDULE OF VALUE WORKSHEET'!E9) -> 0 | E12: =SUM('Draw #6'!E12:F12) -> 0 | F12: 0 | G12: =SUM('Draw #6'!G12)+F12 -> 0 | H12: =SUM(G12-J12) -> 0 | I12: 0 | J12: =SUM(I12+'Draw #6'!J12) -> 0 | K12: =IF(J12=0,"",J12/G12)
A13: ='SCHEDULE OF VALUE WORKSHEET'!A10 -> 4 | B13: ='SCHEDULE OF VALUE WORKSHEET'!B10 -> Offsites (Transformer) | D13: =SUM('SCHEDULE OF VALUE WORKSHEET'!E10) -> 20000 | E13: =SUM('Draw #6'!E13:F13) -> 0 | F13: 0 | G13: =SUM('Draw #6'!G13)+F13 -> 20000 | H13: =SUM(G13-J13) -> 20000 | I13: 0 | J13: =SUM(I13+'Draw #6'!J13) -> 0 | K13: =IF(J13=0,"",J13/G13)
A14: ='SCHEDULE OF VALUE WORKSHEET'!A11 -> 5 | B14: ='SCHEDULE OF VALUE WORKSHEET'!B11 -> Plan Check Fees | D14: =SUM('SCHEDULE OF VALUE WORKSHEET'!E11) -> 0 | E14: =SUM('Draw #6'!E14:F14) -> 0 | F14: 0 | G14: =SUM('Draw #6'!G14)+F14 -> 0 | H14: =SUM(G14-J14) -> 0 | I14: 0 | J14: =SUM(I14+'Draw #6'!J14) -> 0 | K14: =IF(J14=0,"",J14/G14)
A15: ='SCHEDULE OF VALUE WORKSHEET'!A12 -> 6 | B15: ='SCHEDULE OF VALUE WORKSHEET'!B12 -> Permits | D15: =SUM('SCHEDULE OF VALUE WORKSHEET'!E12) -> 0 | E15: =SUM('Draw #6'!E15:F15) -> 0 | F15: 0 | G15: =SUM('Draw #6'!G15)+F15 -> 0 | H15: =SUM(G15-J15) -> 0 | I15: 0 | J15: =SUM(I15+'Draw #6'!J15) -> 0 | K15: =IF(J15=0,"",J15/G15)
A16: ='SCHEDULE OF VALUE WORKSHEET'!A13 -> 7 | B16: ='SCHEDULE OF VALUE WORKSHEET'!B13 -> Survey | D16: =SUM('SCHEDULE OF VALUE WORKSHEET'!E13) -> 0 | E16: =SUM('Draw #6'!E16:F16) -> 0 | F16: 0 | G16: =SUM('Draw #6'!G16)+F16 -> 0 | H16: =SUM(G16-J16) -> 0 | I16: 0 | J16: =SUM(I16+'Draw #6'!J16) -> 0 | K16: =IF(J16=0,"",J16/G16)
A17: ='SCHEDULE OF VALUE WORKSHEET'!A14 -> 8 | B17: ='SCHEDULE OF VALUE WORKSHEET'!B14 -> Soils Engineer | D17: =SUM('SCHEDULE OF VALUE WORKSHEET'!E14) -> 0 | E17: =SUM('Draw #6'!E17:F17) -> 0 | F17: 0 | G17: =SUM('Draw #6'!G17)+F17 -> 0 | H17: =SUM(G17-J17) -> 0 | I17: 0 | J17: =SUM(I17+'Draw #6'!J17) -> 0 | K17: =IF(J17=0,"",J17/G17)
A18: ='SCHEDULE OF VALUE WORKSHEET'!A15 -> 9 | B18: ='SCHEDULE OF VALUE WORKSHEET'!B15 -> Soils Permit + T24 | D18: =SUM('SCHEDULE OF VALUE WORKSHEET'!E15) -> 2500 | E18: =SUM('Draw #6'!E18:F18) -> 0 | F18: 0 | G18: =SUM('Draw #6'!G18)+F18 -> 2500 | H18: =SUM(G18-J18) -> 2500 | I18: 0 | J18: =SUM(I18+'Draw #6'!J18) -> 0 | K18: =IF(J18=0,"",J18/G18)
A19: ='SCHEDULE OF VALUE WORKSHEET'!A16 -> 10 | B19: ='SCHEDULE OF VALUE WORKSHEET'!B16 -> Special Inspections - Deputy | D19: =SUM('SCHEDULE OF VALUE WORKSHEET'!E16) -> 15000 | E19: =SUM('Draw #6'!E19:F19) -> 0 | F19: 0 | G19: =SUM('Draw #6'!G19)+F19 -> 15000 | H19: =SUM(G19-J19) -> 15000 | I19: 0 | J19: =SUM(I19+'Draw #6'!J19) -> 0 | K19: =IF(J19=0,"",J19/G19)
A20: ='SCHEDULE OF VALUE WORKSHEET'!A17 -> 11 | B20: ='SCHEDULE OF VALUE WORKSHEET'!B17 -> Architect | D20: =SUM('SCHEDULE OF VALUE WORKSHEET'!E17) -> 0 | E20: =SUM('Draw #6'!E20:F20) -> 0 | F20: 0 | G20: =SUM('Draw #6'!G20)+F20 -> 0 | H20: =SUM(G20-J20) -> 0 | I20: 0 | J20: =SUM(I20+'Draw #6'!J20) -> 0 | K20: =IF(J20=0,"",J20/G20)
A21: ='SCHEDULE OF VALUE WORKSHEET'!A18 -> 12 | B21: ='SCHEDULE OF VALUE WORKSHEET'!B18 -> Structural Engineer | D21: =SUM('SCHEDULE OF VALUE WORKSHEET'!E18) -> 0 | E21: =SUM('Draw #6'!E21:F21) -> 0 | F21: 0 | G21: =SUM('Draw #6'!G21)+F21 -> 0 | H21: =SUM(G21-J21) -> 0 | I21: 0 | J21: =SUM(I21+'Draw #6'!J21) -> 0 | K21: =IF(J21=0,"",J21/G21)
... A45: ='SCHEDULE OF VALUE WORKSHEET'!A42 -> 36 | B45: ='SCHEDULE OF VALUE WORKSHEET'!B42 -> Construction Management / Observation (OO) | D45: =SUM('SCHEDULE OF VALUE WORKSHEET'!E42) -> 49427.9 | E45: =SUM('Draw #6'!E45:F45) -> 0 | F45: 0 | G45: =SUM('Draw #6'!G45)+F45 -> 49427.9 | H45: =SUM(G45-J45) -> 49427.9 | I45: 0 | J45: =SUM(I45+'Draw #6'!J45) -> 0 | K45: =IF(J45=0,"",J45/G45)
A46: ='SCHEDULE OF VALUE WORKSHEET'!#REF! -> #REF! | B46: ='SCHEDULE OF VALUE WORKSHEET'!#REF! -> #REF! | D46: =SUM('SCHEDULE OF VALUE WORKSHEET'!#REF!) -> #REF! | E46: =SUM('Draw #6'!E46:F46) -> 0 | F46: 0 | G46: =SUM('Draw #6'!G46)+F46 -> #REF! | H46: =SUM(G46-J46) -> #REF! | I46: 0 | J46: =SUM(I46+'Draw #6'!J46) -> 0 | K46: =IF(J46=0,"",J46/G46)
A47: ='SCHEDULE OF VALUE WORKSHEET'!A43 -> 37 | B47: ='SCHEDULE OF VALUE WORKSHEET'!B43 -> CMFA Startup Fee | D47: =SUM('SCHEDULE OF VALUE WORKSHEET'!E43) -> 22800 | E47: =SUM('Draw #6'!E47:F47) -> 0 | F47: 0 | G47: =SUM('Draw #6'!G47)+F47 -> 22800 | H47: =SUM(G47-J47) -> 22800 | I47: 0 | J47: =SUM(I47+'Draw #6'!J47) -> 0 | K47: =IF(J47=0,"",J47/G47)
A48: ='SCHEDULE OF VALUE WORKSHEET'!A44 -> 38 | B48: ='SCHEDULE OF VALUE WORKSHEET'!B44 -> Non-Profit Start Up Fee | D48: =SUM('SCHEDULE OF VALUE WORKSHEET'!E44) -> 25000 | E48: =SUM('Draw #6'!E48:F48) -> 0 | F48: 0 | G48: =SUM('Draw #6'!G48)+F48 -> 25000 | H48: =SUM(G48-J48) -> 25000 | I48: 0 | J48: =SUM(I48+'Draw #6'!J48) -> 0 | K48: =IF(J48=0,"",J48/G48)
A49: ='SCHEDULE OF VALUE WORKSHEET'!A45 -> 39 | B49: ='SCHEDULE OF VALUE WORKSHEET'!B45 -> CMFA Construction Fee | D49: =SUM('SCHEDULE OF VALUE WORKSHEET'!E45) -> 12000 | E49: =SUM('Draw #6'!E49:F49) -> 0 | F49: 0 | G49: =SUM('Draw #6'!G49)+F49 -> 12000 | H49: =SUM(G49-J49) -> 12000 | I49: 0 | J49: =SUM(I49+'Draw #6'!J49) -> 0 | K49: =IF(J49=0,"",J49/G49)
A50: ='SCHEDULE OF VALUE WORKSHEET'!A46 -> 40 | B50: ='SCHEDULE OF VALUE WORKSHEET'!B46 -> Non-Profit Construction Fee | D50: =SUM('SCHEDULE OF VALUE WORKSHEET'!E46) -> 10000 | E50: =SUM('Draw #6'!E50:F50) -> 0 | F50: 0 | G50: =SUM('Draw #6'!G50)+F50 -> 10000 | H50: =SUM(G50-J50) -> 10000 | I50: 0 | J50: =SUM(I50+'Draw #6'!J50) -> 0 | K50: =IF(J50=0,"",J50/G50)
A51: ='SCHEDULE OF VALUE WORKSHEET'!A47 -> 41 | B51: ='SCHEDULE OF VALUE WORKSHEET'!B47 -> WTE Legal Costs for CMFA & Non-Profit Partner | D51: =SUM('SCHEDULE OF VALUE WORKSHEET'!E47) -> 20000 | E51: =SUM('Draw #6'!E51:F51) -> 0 | F51: 0 | G51: =SUM('Draw #6'!G51)+F51 -> 20000 | H51: =SUM(G51-J51) -> 20000 | I51: 0 | J51: =SUM(I51+'Draw #6'!J51) -> 0 | K51: =IF(J51=0,"",J51/G51)
A52: ='SCHEDULE OF VALUE WORKSHEET'!#REF! -> #REF! | B52: ='SCHEDULE OF VALUE WORKSHEET'!#REF! -> #REF! | D52: =SUM('SCHEDULE OF VALUE WORKSHEET'!#REF!) -> #REF! | E52: =SUM('Draw #6'!E52:F52) -> 0 | F52: 0 | G52: =SUM('Draw #6'!G52)+F52 -> #REF! | H52: =SUM(G52-J52) -> #REF! | I52: 0 | J52: =SUM(I52+'Draw #6'!J52) -> 0 | K52: =IF(J52=0,"",J52/G52)
A53: ='SCHEDULE OF VALUE WORKSHEET'!A49 -> 43 | B53: ='SCHEDULE OF VALUE WORKSHEET'!B49 -> GENERAL CONDITIONS | D53: =SUM('SCHEDULE OF VALUE WORKSHEET'!E49) -> 362115.24 | E53: =SUM('Draw #6'!E53:F53) -> 0 | F53: 0 | G53: =SUM('Draw #6'!G53)+F53 -> 362115.24 | H53: =SUM(G53-J53) -> 362115.24 | I53: 0 | J53: =SUM(I53+'Draw #6'!J53) -> 0 | K53: =IF(J53=0,"",J53/G53)
A54: ='SCHEDULE OF VALUE WORKSHEET'!A50 -> 44 | B54: ='SCHEDULE OF VALUE WORKSHEET'!B50 -> GENERAL REQUIREMENT | D54: =SUM('SCHEDULE OF VALUE WORKSHEET'!E50) -> 124657.88 | E54: =SUM('Draw #6'!E54:F54) -> 0 | F54: 0 | G54: =SUM('Draw #6'!G54)+F54 -> 124657.88 | H54: =SUM(G54-J54) -> 124657.88 | I54: 0 | J54: =SUM(I54+'Draw #6'!J54) -> 0 | K54: =IF(J54=0,"",J54/G54)
A55: ='SCHEDULE OF VALUE WORKSHEET'!A51 -> 45 | B55: ='SCHEDULE OF VALUE WORKSHEET'!B51 -> SITE WORK | D55: =SUM('SCHEDULE OF VALUE WORKSHEET'!E51) -> 139049.51 | E55: =SUM('Draw #6'!E55:F55) -> 0 | F55: 0 | G55: =SUM('Draw #6'!G55)+F55 -> 139049.51 | H55: =SUM(G55-J55) -> 139049.51 | I55: 0 | J55: =SUM(I55+'Draw #6'!J55) -> 0 | K55: =IF(J55=0,"",J55/G55)
A56: ='SCHEDULE OF VALUE WORKSHEET'!A52 -> 46 | B56: ='SCHEDULE OF VALUE WORKSHEET'!B52 -> CONCRETE | D56: =SUM('SCHEDULE OF VALUE WORKSHEET'!E52) -> 253182 | E56: =SUM('Draw #6'!E56:F56) -> 0 | F56: 0 | G56: =SUM('Draw #6'!G56)+F56 -> 253182 | H56: =SUM(G56-J56) -> 253182 | I56: 0 | J56: =SUM(I56+'Draw #6'!J56) -> 0 | K56: =IF(J56=0,"",J56/G56)
A57: ='SCHEDULE OF VALUE WORKSHEET'!A53 -> 47 | B57: ='SCHEDULE OF VALUE WORKSHEET'!B53 -> MASONRY | D57: =SUM('SCHEDULE OF VALUE WORKSHEET'!E53) -> 3562.64 | E57: =SUM('Draw #6'!E57:F57) -> 0 | F57: 0 | G57: =SUM('Draw #6'!G57)+F57 -> 3562.64 | H57: =SUM(G57-J57) -> 3562.64 | I57: 0 | J57: =SUM(I57+'Draw #6'!J57) -> 0 | K57: =IF(J57=0,"",J57/G57)
A58: ='SCHEDULE OF VALUE WORKSHEET'!A54 -> 48 | B58: ='SCHEDULE OF VALUE WORKSHEET'!B54 -> METALS | D58: =SUM('SCHEDULE OF VALUE WORKSHEET'!E54) -> 324100 | E58: =SUM('Draw #6'!E58:F58) -> 0 | F58: 0 | G58: =SUM('Draw #6'!G58)+F58 -> 324100 | H58: =SUM(G58-J58) -> 324100 | I58: 0 | J58: =SUM(I58+'Draw #6'!J58) -> 0 | K58: =IF(J58=0,"",J58/G58)
A59: ='SCHEDULE OF VALUE WORKSHEET'!A55 -> 49 | B59: ='SCHEDULE OF VALUE WORKSHEET'!B55 -> FRAMING | D59: =SUM('SCHEDULE OF VALUE WORKSHEET'!E55) -> 818554 | E59: =SUM('Draw #6'!E59:F59) -> 0 | F59: 0 | G59: =SUM('Draw #6'!G59)+F59 -> 818554 | H59: =SUM(G59-J59) -> 818554 | I59: 0 | J59: =SUM(I59+'Draw #6'!J59) -> 0 | K59: =IF(J59=0,"",J59/G59)
A60: ='SCHEDULE OF VALUE WORKSHEET'!A56 -> 50 | B60: ='SCHEDULE OF VALUE WORKSHEET'!B56 -> COUNTERTOPS | D60: =SUM('SCHEDULE OF VALUE WORKSHEET'!E56) -> 56930 | E60: =SUM('Draw #6'!E60:F60) -> 0 | F60: 0 | G60: =SUM('Draw #6'!G60)+F60 -> 56930 | H60: =SUM(G60-J60) -> 56930 | I60: 0 | J60: =SUM(I60+'Draw #6'!J60) -> 0 | K60: =IF(J60=0,"",J60/G60)
A61: ='SCHEDULE OF VALUE WORKSHEET'!A57 -> 51 | B61: ='SCHEDULE OF VALUE WORKSHEET'!B57 -> CABINETS | D61: =SUM('SCHEDULE OF VALUE WORKSHEET'!E57) -> 56930 | E61: =SUM('Draw #6'!E61:F61) -> 0 | F61: 0 | G61: =SUM('Draw #6'!G61)+F61 -> 56930 | H61: =SUM(G61-J61) -> 56930 | I61: 0 | J61: =SUM(I61+'Draw #6'!J61) -> 0 | K61: =IF(J61=0,"",J61/G61)
A62: ='SCHEDULE OF VALUE WORKSHEET'!A58 -> 52 | B62: ='SCHEDULE OF VALUE WORKSHEET'!B58 -> THERMAL MOISTURE PROTECTION | D62: =SUM('SCHEDULE OF VALUE WORKSHEET'!E58) -> 173148 | E62: =SUM('Draw #6'!E62:F62) -> 0 | F62: 0 | G62: =SUM('Draw #6'!G62)+F62 -> 173148 | H62: =SUM(G62-J62) -> 173148 | I62: 0 | J62: =SUM(I62+'Draw #6'!J62) -> 0 | K62: =IF(J62=0,"",J62/G62)
A63: ='SCHEDULE OF VALUE WORKSHEET'!A59 -> 53 | B63: ='SCHEDULE OF VALUE WORKSHEET'!B59 -> DOORS | D63: =SUM('SCHEDULE OF VALUE WORKSHEET'!E59) -> 204087.33 | E63: =SUM('Draw #6'!E63:F63) -> 0 | F63: 0 | G63: =SUM('Draw #6'!G63)+F63 -> 204087.33 | H63: =SUM(G63-J63) -> 204087.33 | I63: 0 | J63: =SUM(I63+'Draw #6'!J63) -> 0 | K63: =IF(J63=0,"",J63/G63)
A64: ='SCHEDULE OF VALUE WORKSHEET'!A60 -> 54 | B64: ='SCHEDULE OF VALUE WORKSHEET'!B60 -> WINDOWS | D64: =SUM('SCHEDULE OF VALUE WORKSHEET'!E60) -> 106274.25 | E64: =SUM('Draw #6'!E64:F64) -> 0 | F64: 0 | G64: =SUM('Draw #6'!G64)+F64 -> 106274.25 | H64: =SUM(G64-J64) -> 106274.25 | I64: 0 | J64: =SUM(I64+'Draw #6'!J64) -> 0 | K64: =IF(J64=0,"",J64/G64)
... A90: ='SCHEDULE OF VALUE WORKSHEET'!A86 -> 80 | B90: ='SCHEDULE OF VALUE WORKSHEET'!B86 -> FINANCING COSTS | D90: =SUM('SCHEDULE OF VALUE WORKSHEET'!E86) -> 0 | E90: =SUM('Draw #6'!E90:F90) -> 0 | F90: 0 | G90: =SUM('Draw #6'!G90)+F90 -> 0 | H90: =SUM(G90-J90) -> 0 | I90: 0 | J90: =SUM(I90+'Draw #6'!J90) -> 0 | K90: =IF(J90=0,"",J90/G90)
A91: ='SCHEDULE OF VALUE WORKSHEET'!#REF! -> #REF! | B91: ='SCHEDULE OF VALUE WORKSHEET'!#REF! -> #REF! | D91: =SUM('SCHEDULE OF VALUE WORKSHEET'!#REF!) -> #REF! | E91: =SUM('Draw #6'!E91:F91) -> 0 | F91: 0 | G91: =SUM('Draw #6'!G91)+F91 -> #REF! | H91: =SUM(G91-J91) -> #REF! | I91: 0 | J91: =SUM(I91+'Draw #6'!J91) -> 0 | K91: =IF(J91=0,"",J91/G91)
A92: ='SCHEDULE OF VALUE WORKSHEET'!#REF! -> #REF! | B92: ='SCHEDULE OF VALUE WORKSHEET'!#REF! -> #REF! | D92: =SUM('SCHEDULE OF VALUE WORKSHEET'!#REF!) -> #REF! | E92: =SUM('Draw #6'!E92:F92) -> 0 | F92: 0 | G92: =SUM('Draw #6'!G92)+F92 -> #REF! | H92: =SUM(G92-J92) -> #REF! | I92: 0 | J92: =SUM(I92+'Draw #6'!J92) -> 0 | K92: =IF(J92=0,"",J92/G92)
A93: ='SCHEDULE OF VALUE WORKSHEET'!#REF! -> #REF! | B93: ='SCHEDULE OF VALUE WORKSHEET'!#REF! -> #REF! | D93: =SUM('SCHEDULE OF VALUE WORKSHEET'!#REF!) -> #REF! | E93: =SUM('Draw #6'!E93:F93) -> 0 | F93: 0 | G93: =SUM('Draw #6'!G93)+F93 -> #REF! | H93: =SUM(G93-J93) -> #REF! | I93: 0 | J93: =SUM(I93+'Draw #6'!J93) -> 0 | K93: =IF(J93=0,"",J93/G93)
A94: ='SCHEDULE OF VALUE WORKSHEET'!#REF! -> #REF! | B94: ='SCHEDULE OF VALUE WORKSHEET'!#REF! -> #REF! | D94: =SUM('SCHEDULE OF VALUE WORKSHEET'!#REF!) -> #REF! | E94: =SUM('Draw #6'!E94:F94) -> 0 | F94: 0 | G94: =SUM('Draw #6'!G94)+F94 -> #REF! | H94: =SUM(G94-J94) -> #REF! | I94: 0 | J94: =SUM(I94+'Draw #6'!J94) -> 0 | K94: =IF(J94=0,"",J94/G94)
A95: ='SCHEDULE OF VALUE WORKSHEET'!#REF! -> #REF! | B95: ='SCHEDULE OF VALUE WORKSHEET'!#REF! -> #REF! | D95: =SUM('SCHEDULE OF VALUE WORKSHEET'!#REF!) -> #REF! | E95: =SUM('Draw #6'!E95:F95) -> 0 | F95: 0 | G95: =SUM('Draw #6'!G95)+F95 -> #REF! | H95: =SUM(G95-J95) -> #REF! | I95: 0 | J95: =SUM(I95+'Draw #6'!J95) -> 0 | K95: =IF(J95=0,"",J95/G95)
A96: ='SCHEDULE OF VALUE WORKSHEET'!#REF! -> #REF! | B96: ='SCHEDULE OF VALUE WORKSHEET'!#REF! -> #REF! | D96: =SUM('SCHEDULE OF VALUE WORKSHEET'!#REF!) -> #REF! | E96: =SUM('Draw #6'!E96:F96) -> 0 | F96: 0 | G96: =SUM('Draw #6'!G96)+F96 -> #REF! | H96: =SUM(G96-J96) -> #REF! | I96: 0 | J96: =SUM(I96+'Draw #6'!J96) -> 0 | K96: =IF(J96=0,"",J96/G96)
A97: ='SCHEDULE OF VALUE WORKSHEET'!#REF! -> #REF! | B97: ='SCHEDULE OF VALUE WORKSHEET'!#REF! -> #REF! | D97: =SUM('SCHEDULE OF VALUE WORKSHEET'!#REF!) -> #REF! | E97: =SUM('Draw #6'!E97:F97) -> 0 | F97: 0 | G97: =SUM('Draw #6'!G97)+F97 -> #REF! | H97: =SUM(G97-J97) -> #REF! | I97: 0 | J97: =SUM(I97+'Draw #6'!J97) -> 0 | K97: =IF(J97=0,"",J97/G97)
A98: ='SCHEDULE OF VALUE WORKSHEET'!#REF! -> #REF! | B98: ='SCHEDULE OF VALUE WORKSHEET'!#REF! -> #REF! | D98: =SUM('SCHEDULE OF VALUE WORKSHEET'!#REF!) -> #REF! | E98: =SUM('Draw #6'!E98:F98) -> 0 | F98: 0 | G98: =SUM('Draw #6'!G98)+F98 -> #REF! | H98: =SUM(G98-J98) -> #REF! | I98: 0 | J98: =SUM(I98+'Draw #6'!J98) -> 0 | K98: =IF(J98=0,"",J98/G98)
A99: ='SCHEDULE OF VALUE WORKSHEET'!#REF! -> #REF! | B99: ='SCHEDULE OF VALUE WORKSHEET'!#REF! -> #REF! | D99: =SUM('SCHEDULE OF VALUE WORKSHEET'!#REF!) -> #REF! | E99: =SUM('Draw #6'!E99:F99) -> 0 | F99: 0 | G99: =SUM('Draw #6'!G99)+F99 -> #REF! | H99: =SUM(G99-J99) -> #REF! | I99: 0 | J99: =SUM(I99+'Draw #6'!J99) -> 0 | K99: =IF(J99=0,"",J99/G99)
A100: ='SCHEDULE OF VALUE WORKSHEET'!#REF! -> #REF! | B100: ='SCHEDULE OF VALUE WORKSHEET'!#REF! -> #REF! | D100: =SUM('SCHEDULE OF VALUE WORKSHEET'!#REF!) -> #REF! | E100: =SUM('Draw #6'!E100:F100) -> 0 | F100: 0 | G100: =SUM('Draw #6'!G100)+F100 -> #REF! | H100: =SUM(G100-J100) -> #REF! | I100: 0 | J100: =SUM(I100+'Draw #6'!J100) -> 0 | K100: =IF(J100=0,"",J100/G100)
A101: ='SCHEDULE OF VALUE WORKSHEET'!#REF! -> #REF! | B101: ='SCHEDULE OF VALUE WORKSHEET'!#REF! -> #REF! | D101: =SUM('SCHEDULE OF VALUE WORKSHEET'!#REF!) -> #REF! | E101: =SUM('Draw #6'!E101:F101) -> 0 | F101: 0 | G101: =SUM('Draw #6'!G101)+F101 -> #REF! | H101: =SUM(G101-J101) -> #REF! | I101: 0 | J101: =SUM(I101+'Draw #6'!J101) -> 0 | K101: =IF(J101=0,"",J101/G101)
A102: ='SCHEDULE OF VALUE WORKSHEET'!#REF! -> #REF! | B102: ='SCHEDULE OF VALUE WORKSHEET'!#REF! -> #REF! | D102: =SUM('SCHEDULE OF VALUE WORKSHEET'!#REF!) -> #REF! | E102: =SUM('Draw #6'!E102:F102) -> 0 | F102: 0 | G102: =SUM('Draw #6'!G102)+F102 -> #REF! | H102: =SUM(G102-J102) -> #REF! | I102: 0 | J102: =SUM(I102+'Draw #6'!J102) -> 0 | K102: =IF(J102=0,"",J102/G102)
... A116: ='SCHEDULE OF VALUE WORKSHEET'!#REF! -> #REF! | B116: ='SCHEDULE OF VALUE WORKSHEET'!#REF! -> #REF! | D116: =SUM('SCHEDULE OF VALUE WORKSHEET'!#REF!) -> #REF! | E116: =SUM('Draw #6'!E116:F116) -> 0 | F116: 0 | G116: =SUM('Draw #6'!G116)+F116 -> #REF! | H116: =SUM(G116-J116) -> #REF! | I116: 0 | J116: =SUM(I116+'Draw #6'!J116) -> 0 | K116: =IF(J116=0,"",J116/G116)
A117: ='SCHEDULE OF VALUE WORKSHEET'!A87 -> 82 | B117: ='SCHEDULE OF VALUE WORKSHEET'!B87 -> Open Item | D117: =SUM('SCHEDULE OF VALUE WORKSHEET'!E87) -> 0 | E117: =SUM('Draw #6'!E117:F117) -> 0 | F117: 0 | G117: =SUM('Draw #6'!G117)+F117 -> 0 | H117: =SUM(G117-J117) -> 0 | I117: 0 | J117: =SUM(I117+'Draw #6'!J117) -> 0 | K117: =IF(J117=0,"",J117/G117)
A118: ='SCHEDULE OF VALUE WORKSHEET'!A88 -> 83 | B118: ='SCHEDULE OF VALUE WORKSHEET'!B88 -> Open Item | D118: =SUM('SCHEDULE OF VALUE WORKSHEET'!E88) -> 0 | E118: =SUM('Draw #6'!E118:F118) -> 0 | F118: 0 | G118: =SUM('Draw #6'!G118)+F118 -> 0 | H118: =SUM(G118-J118) -> 0 | I118: 0 | J118: =SUM(I118+'Draw #6'!J118) -> 0 | K118: =IF(J118=0,"",J118/G118)
A119: ='SCHEDULE OF VALUE WORKSHEET'!A89 -> 84 | B119: ='SCHEDULE OF VALUE WORKSHEET'!B89 -> Open Item | D119: =SUM('SCHEDULE OF VALUE WORKSHEET'!E89) -> 0 | E119: =SUM('Draw #6'!E119:F119) -> 0 | F119: 0 | G119: =SUM('Draw #6'!G119)+F119 -> 0 | H119: =SUM(G119-J119) -> 0 | I119: 0 | J119: =SUM(I119+'Draw #6'!J119) -> 0 | K119: =IF(J119=0,"",J119/G119)
A120: ='SCHEDULE OF VALUE WORKSHEET'!A90 -> 85 | B120: ='SCHEDULE OF VALUE WORKSHEET'!B90 -> Open Item | D120: =SUM('SCHEDULE OF VALUE WORKSHEET'!E90) -> 0 | E120: =SUM('Draw #6'!E120:F120) -> 0 | F120: 0 | G120: =SUM('Draw #6'!G120)+F120 -> 0 | H120: =SUM(G120-J120) -> 0 | I120: 0 | J120: =SUM(I120+'Draw #6'!J120) -> 0 | K120: =IF(J120=0,"",J120/G120)
A121: ='SCHEDULE OF VALUE WORKSHEET'!A91 -> 86 | B121: ='SCHEDULE OF VALUE WORKSHEET'!B91 -> Open Item | D121: =SUM('SCHEDULE OF VALUE WORKSHEET'!E91) -> 0 | E121: =SUM('Draw #6'!E121:F121) -> 0 | F121: 0 | G121: =SUM('Draw #6'!G121)+F121 -> 0 | H121: =SUM(G121-J121) -> 0 | I121: 0 | J121: =SUM(I121+'Draw #6'!J121) -> 0 | K121: =IF(J121=0,"",J121/G121)
A122: ='SCHEDULE OF VALUE WORKSHEET'!A92 -> 87 | B122: ='SCHEDULE OF VALUE WORKSHEET'!B92 -> Open Item | D122: =SUM('SCHEDULE OF VALUE WORKSHEET'!E92) -> 0 | E122: =SUM('Draw #6'!E122:F122) -> 0 | F122: 0 | G122: =SUM('Draw #6'!G122)+F122 -> 0 | H122: =SUM(G122-J122) -> 0 | I122: 0 | J122: =SUM(I122+'Draw #6'!J122) -> 0 | K122: =IF(J122=0,"",J122/G122)
A123: ='SCHEDULE OF VALUE WORKSHEET'!A93 -> 88 | B123: ='SCHEDULE OF VALUE WORKSHEET'!B93 -> Open Item | D123: =SUM('SCHEDULE OF VALUE WORKSHEET'!E93) -> 0 | E123: =SUM('Draw #6'!E123:F123) -> 0 | F123: 0 | G123: =SUM('Draw #6'!G123)+F123 -> 0 | H123: =SUM(G123-J123) -> 0 | I123: 0 | J123: =SUM(I123+'Draw #6'!J123) -> 0 | K123: =IF(J123=0,"",J123/G123)
A124: ='SCHEDULE OF VALUE WORKSHEET'!A94 -> 89 | B124: ='SCHEDULE OF VALUE WORKSHEET'!B94 -> Open Item | D124: =SUM('SCHEDULE OF VALUE WORKSHEET'!E94) -> 0 | E124: =SUM('Draw #6'!E124:F124) -> 0 | F124: 0 | G124: =SUM('Draw #6'!G124)+F124 -> 0 | H124: =SUM(G124-J124) -> 0 | I124: 0 | J124: =SUM(I124+'Draw #6'!J124) -> 0 | K124: =IF(J124=0,"",J124/G124)
A125: ='SCHEDULE OF VALUE WORKSHEET'!A95 -> 90 | B125: ='SCHEDULE OF VALUE WORKSHEET'!B95 -> Open Item | D125: =SUM('SCHEDULE OF VALUE WORKSHEET'!E95) -> 0 | E125: =SUM('Draw #6'!E125:F125) -> 0 | F125: 0 | G125: =SUM('Draw #6'!G125)+F125 -> 0 | H125: =SUM(G125-J125) -> 0 | I125: 0 | J125: =SUM(I125+'Draw #6'!J125) -> 0 | K125: =IF(J125=0,"",J125/G125)
A126: ='SCHEDULE OF VALUE WORKSHEET'!A96 -> 91 | B126: ='SCHEDULE OF VALUE WORKSHEET'!B96 -> Open Item | D126: =SUM('SCHEDULE OF VALUE WORKSHEET'!E96) -> 0 | E126: =SUM('Draw #6'!E126:F126) -> 0 | F126: 0 | G126: =SUM('Draw #6'!G126)+F126 -> 0 | H126: =SUM(G126-J126) -> 0 | I126: 0 | J126: =SUM(I126+'Draw #6'!J126) -> 0 | K126: =IF(J126=0,"",J126/G126)
A127: ='SCHEDULE OF VALUE WORKSHEET'!A97 -> 92 | B127: ='SCHEDULE OF VALUE WORKSHEET'!B97 -> Open Item | D127: =SUM('SCHEDULE OF VALUE WORKSHEET'!E97) -> 0 | E127: =SUM('Draw #6'!E127:F127) -> 0 | F127: 0 | G127: =SUM('Draw #6'!G127)+F127 -> 0 | H127: =SUM(G127-J127) -> 0 | I127: 0 | J127: =SUM(I127+'Draw #6'!J127) -> 0 | K127: =IF(J127=0,"",J127/G127)
A128: ='SCHEDULE OF VALUE WORKSHEET'!A98 -> 93 | B128: ='SCHEDULE OF VALUE WORKSHEET'!B98 -> Open Item | D128: =SUM('SCHEDULE OF VALUE WORKSHEET'!E98) -> 0 | E128: =SUM('Draw #6'!E128:F128) -> 0 | F128: 0 | G128: =SUM('Draw #6'!G128)+F128 -> 0 | H128: =SUM(G128-J128) -> 0 | I128: 0 | J128: =SUM(I128+'Draw #6'!J128) -> 0 | K128: =IF(J128=0,"",J128/G128)
... A134: ='SCHEDULE OF VALUE WORKSHEET'!A104 -> 99 | B134: ='SCHEDULE OF VALUE WORKSHEET'!B104 -> Open Item | D134: =SUM('SCHEDULE OF VALUE WORKSHEET'!E104) -> 0 | E134: =SUM('Draw #6'!E134:F134) -> 0 | F134: 0 | G134: =SUM('Draw #6'!G134)+F134 -> 0 | H134: =SUM(G134-J134) -> 0 | I134: 0 | J134: =SUM(I134+'Draw #6'!J134) -> 0 | K134: =IF(J134=0,"",J134/G134)
A135: ='SCHEDULE OF VALUE WORKSHEET'!#REF! -> #REF! | B135: ='SCHEDULE OF VALUE WORKSHEET'!#REF! -> #REF! | D135: =SUM('SCHEDULE OF VALUE WORKSHEET'!#REF!) -> #REF! | E135: =SUM('Draw #6'!E135:F135) -> 0 | F135: 0 | G135: =SUM('Draw #6'!G135)+F135 -> #REF! | H135: =SUM(G135-J135) -> #REF! | I135: 0 | J135: =SUM(I135+'Draw #6'!J135) -> 0 | K135: =IF(J135=0,"",J135/G135)
B137: TOTAL | D137: =SUM(D10:D135) -> #REF! | E137: =SUM(E10:E135) -> 0 | F137: =SUM(F10:F135) -> 0 | G137: =SUM(G10:G135) -> #REF! | H137: =SUM(H10:H135) -> #REF! | I137: =SUM(I10:I135) -> 0 | J137: =SUM(J10:J135) -> 0

Sheet Draw #8
A1: GENESIS CAPITAL DRAW FORM
B3: CLIENT: | C3: ='SCHEDULE OF VALUE WORKSHEET'!$B$3 -> Angeleno Investments | I3: TOTAL COMPLETED TO DATE: | J3: =SUM(J137) -> 0 | K3: =SUM(J3)/J7 -> #REF!
B4: DATE: | C4: =TODAY() -> 45978 | I4: REMAINING $ IN BUDGET: | J4: =SUM(H137) -> #REF!
B5: PROJECT: | C5: ='SCHEDULE OF VALUE WORKSHEET'!B5 -> 10910 Huston Street | I5: ORIGINAL SCHEDULE OF VALUES: | J5: =SUM(D137) -> #REF!
B6: DRAW REQUEST: | C6: =SUM(I137) -> 0 | I6: CHANGE ORDERS: | J6: =SUM(F137) -> 0
I7: REVISED SCHEDULE OF VALUES: | J7: =SUM(G137) -> #REF!
B8: DESCRIPTION OF WORK | D8: SCHEDULED VALUES | E8: PREVIOUS | F8: + / - CHANGES | G8: REVISED VALUES | H8: REMAINING | I8: DRAW | J8: COMPLETED AND
E9: CHANGES | H9: BUDGET | I9: 8 | J9: STORED TO DATE
A10: ='SCHEDULE OF VALUE WORKSHEET'!A7 -> 1 | B10: ='SCHEDULE OF VALUE WORKSHEET'!B7 -> SOFT COSTS | D10: =SUM('SCHEDULE OF VALUE WORKSHEET'!E7) -> 0 | E10: =SUM('Draw #7'!E10:F10) -> 0 | F10: 0 | G10: =SUM('Draw #7'!G10)+F10 -> 0 | H10: =SUM(G10-J10) -> 0 | I10: 0 | J10: =SUM(I10+'Draw #7'!J10) -> 0 | K10: =IF(J10=0,"",J10/G10)
A11: ='SCHEDULE OF VALUE WORKSHEET'!A8 -> 2 | B11: ='SCHEDULE OF VALUE WORKSHEET'!B8 -> Site Security | D11: =SUM('SCHEDULE OF VALUE WORKSHEET'!E8) -> 10580.63 | E11: =SUM('Draw #7'!E11:F11) -> 0 | F11: 0 | G11: =SUM('Draw #7'!G11)+F11 -> 10580.63 | H11: =SUM(G11-J11) -> 10580.63 | I11: 0 | J11: =SUM(I11+'Draw #7'!J11) -> 0 | K11: =IF(J11=0,"",J11/G11)
A12: ='SCHEDULE OF VALUE WORKSHEET'!A9 -> 3 | B12: ='SCHEDULE OF VALUE WORKSHEET'!B9 -> Soils Inspection | D12: =SUM('SCHEDULE OF VALUE WORKSHEET'!E9) -> 0 | E12: =SUM('Draw #7'!E12:F12) -> 0 | F12: 0 | G12: =SUM('Draw #7'!G12)+F12 -> 0 | H12: =SUM(G12-J12) -> 0 | I12: 0 | J12: =SUM(I12+'Draw #7'!J12) -> 0 | K12: =IF(J12=0,"",J12/G12)
A13: ='SCHEDULE OF VALUE WORKSHEET'!A10 -> 4 | B13: ='SCHEDULE OF VALUE WORKSHEET'!B10 -> Offsites (Transformer) | D13: =SUM('SCHEDULE OF VALUE WORKSHEET'!E10) -> 20000 | E13: =SUM('Draw #7'!E13:F13) -> 0 | F13: 0 | G13: =SUM('Draw #7'!G13)+F13 -> 20000 | H13: =SUM(G13-J13) -> 20000 | I13: 0 | J13: =SUM(I13+'Draw #7'!J13) -> 0 | K13: =IF(J13=0,"",J13/G13)
A14: ='SCHEDULE OF VALUE WORKSHEET'!A11 -> 5 | B14: ='SCHEDULE OF VALUE WORKSHEET'!B11 -> Plan Check Fees | D14: =SUM('SCHEDULE OF VALUE WORKSHEET'!E11) -> 0 | E14: =SUM('Draw #7'!E14:F14) -> 0 | F14: 0 | G14: =SUM('Draw #7'!G14)+F14 -> 0 | H14: =SUM(G14-J14) -> 0 | I14: 0 | J14: =SUM(I14+'Draw #7'!J14) -> 0 | K14: =IF(J14=0,"",J14/G14)
A15: ='SCHEDULE OF VALUE WORKSHEET'!A12 -> 6 | B15: ='SCHEDULE OF VALUE WORKSHEET'!B12 -> Permits | D15: =SUM('SCHEDULE OF VALUE WORKSHEET'!E12) -> 0 | E15: =SUM('Draw #7'!E15:F15) -> 0 | F15: 0 | G15: =SUM('Draw #7'!G15)+F15 -> 0 | H15: =SUM(G15-J15) -> 0 | I15: 0 | J15: =SUM(I15+'Draw #7'!J15) -> 0 | K15: =IF(J15=0,"",J15/G15)
A16: ='SCHEDULE OF VALUE WORKSHEET'!A13 -> 7 | B16: ='SCHEDULE OF VALUE WORKSHEET'!B13 -> Survey | D16: =SUM('SCHEDULE OF VALUE WORKSHEET'!E13) -> 0 | E16: =SUM('Draw #7'!E16:F16) -> 0 | F16: 0 | G16: =SUM('Draw #7'!G16)+F16 -> 0 | H16: =SUM(G16-J16) -> 0 | I16: 0 | J16: =SUM(I16+'Draw #7'!J16) -> 0 | K16: =IF(J16=0,"",J16/G16)
A17: ='SCHEDULE OF VALUE WORKSHEET'!A14 -> 8 | B17: ='SCHEDULE OF VALUE WORKSHEET'!B14 -> Soils Engineer | D17: =SUM('SCHEDULE OF VALUE WORKSHEET'!E14) -> 0 | E17: =SUM('Draw #7'!E17:F17) -> 0 | F17: 0 | G17: =SUM('Draw #7'!G17)+F17 -> 0 | H17: =SUM(G17-J17) -> 0 | I17: 0 | J17: =SUM(I17+'Draw #7'!J17) -> 0 | K17: =IF(J17=0,"",J17/G17)
A18: ='SCHEDULE OF VALUE WORKSHEET'!A15 -> 9 | B18: ='SCHEDULE OF VALUE WORKSHEET'!B15 -> Soils Permit + T24 | D18: =SUM('SCHEDULE OF VALUE WORKSHEET'!E15) -> 2500 | E18: =SUM('Draw #7'!E18:F18) -> 0 | F18: 0 | G18: =SUM('Draw #7'!G18)+F18 -> 2500 | H18: =SUM(G18-J18) -> 2500 | I18: 0 | J18: =SUM(I18+'Draw #7'!J18) -> 0 | K18: =IF(J18=0,"",J18/G18)
A19: ='SCHEDULE OF VALUE WORKSHEET'!A16 -> 10 | B19: ='SCHEDULE OF VALUE WORKSHEET'!B16 -> Special Inspections - Deputy | D19: =SUM('SCHEDULE OF VALUE WORKSHEET'!E16) -> 15000 | E19: =SUM('Draw #7'!E19:F19) -> 0 | F19: 0 | G19: =SUM('Draw #7'!G19)+F19 -> 15000 | H19: =SUM(G19-J19) -> 15000 | I19: 0 | J19: =SUM(I19+'Draw #7'!J19) -> 0 | K19: =IF(J19=0,"",J19/G19)
A20: ='SCHEDULE OF VALUE WORKSHEET'!A17 -> 11 | B20: ='SCHEDULE OF VALUE WORKSHEET'!B17 -> Architect | D20: =SUM('SCHEDULE OF VALUE WORKSHEET'!E17) -> 0 | E20: =SUM('Draw #7'!E20:F20) -> 0 | F20: 0 | G20: =SUM('Draw #7'!G20)+F20 -> 0 | H20: =SUM(G20-J20) -> 0 | I20: 0 | J20: =SUM(I20+'Draw #7'!J20) -> 0 | K20: =IF(J20=0,"",J20/G20)
A21: ='SCHEDULE OF VALUE WORKSHEET'!A18 -> 12 | B21: ='SCHEDULE OF VALUE WORKSHEET'!B18 -> Structural Engineer | D21: =SUM('SCHEDULE OF VALUE WORKSHEET'!E18) -> 0 | E21: =SUM('Draw #7'!E21:F21) -> 0 | F21: 0 | G21: =SUM('Draw #7'!G21)+F21 -> 0 | H21: =SUM(G21-J21) -> 0 | I21: 0 | J21: =SUM(I21+'Draw #7'!J21) -> 0 | K21: =IF(J21=0,"",J21/G21)
... A45: ='SCHEDULE OF VALUE WORKSHEET'!A42 -> 36 | B45: ='SCHEDULE OF VALUE WORKSHEET'!B42 -> Construction Management / Observation (OO) | D45: =SUM('SCHEDULE OF VALUE WORKSHEET'!E42) -> 49427.9 | E45: =SUM('Draw #7'!E45:F45) -> 0 | F45: 0 | G45: =SUM('Draw #7'!G45)+F45 -> 49427.9 | H45: =SUM(G45-J45) -> 49427.9 | I45: 0 | J45: =SUM(I45+'Draw #7'!J45) -> 0 | K45: =IF(J45=0,"",J45/G45)
A46: ='SCHEDULE OF VALUE WORKSHEET'!#REF! -> #REF! | B46: ='SCHEDULE OF VALUE WORKSHEET'!#REF! -> #REF! | D46: =SUM('SCHEDULE OF VALUE WORKSHEET'!#REF!) -> #REF! | E46: =SUM('Draw #7'!E46:F46) -> 0 | F46: 0 | G46: =SUM('Draw #7'!G46)+F46 -> #REF! | H46: =SUM(G46-J46) -> #REF! | I46: 0 | J46: =SUM(I46+'Draw #7'!J46) -> 0 | K46: =IF(J46=0,"",J46/G46)
A47: ='SCHEDULE OF VALUE WORKSHEET'!A43 -> 37 | B47: ='SCHEDULE OF VALUE WORKSHEET'!B43 -> CMFA Startup Fee | D47: =SUM('SCHEDULE OF VALUE WORKSHEET'!E43) -> 22800 | E47: =SUM('Draw #7'!E47:F47) -> 0 | F47: 0 | G47: =SUM('Draw #7'!G47)+F47 -> 22800 | H47: =SUM(G47-J47) -> 22800 | I47: 0 | J47: =SUM(I47+'Draw #7'!J47) -> 0 | K47: =IF(J47=0,"",J47/G47)
A48: ='SCHEDULE OF VALUE WORKSHEET'!A44 -> 38 | B48: ='SCHEDULE OF VALUE WORKSHEET'!B44 -> Non-Profit Start Up Fee | D48: =SUM('SCHEDULE OF VALUE WORKSHEET'!E44) -> 25000 | E48: =SUM('Draw #7'!E48:F48) -> 0 | F48: 0 | G48: =SUM('Draw #7'!G48)+F48 -> 25000 | H48: =SUM(G48-J48) -> 25000 | I48: 0 | J48: =SUM(I48+'Draw #7'!J48) -> 0 | K48: =IF(J48=0,"",J48/G48)
A49: ='SCHEDULE OF VALUE WORKSHEET'!A45 -> 39 | B49: ='SCHEDULE OF VALUE WORKSHEET'!B45 -> CMFA Construction Fee | D49: =SUM('SCHEDULE OF VALUE WORKSHEET'!E45) -> 12000 | E49: =SUM('Draw #7'!E49:F49) -> 0 | F49: 0 | G49: =SUM('Draw #7'!G49)+F49 -> 12000 | H49: =SUM(G49-J49) -> 12000 | I49: 0 | J49: =SUM(I49+'Draw #7'!J49) -> 0 | K49: =IF(J49=0,"",J49/G49)
A50: ='SCHEDULE OF VALUE WORKSHEET'!A46 -> 40 | B50: ='SCHEDULE OF VALUE WORKSHEET'!B46 -> Non-Profit Construction Fee | D50: =SUM('SCHEDULE OF VALUE WORKSHEET'!E46) -> 10000 | E50: =SUM('Draw #7'!E50:F50) -> 0 | F50: 0 | G50: =SUM('Draw #7'!G50)+F50 -> 10000 | H50: =SUM(G50-J50) -> 10000 | I50: 0 | J50: =SUM(I50+'Draw #7'!J50) -> 0 | K50: =IF(J50=0,"",J50/G50)
A51: ='SCHEDULE OF VALUE WORKSHEET'!A47 -> 41 | B51: ='SCHEDULE OF VALUE WORKSHEET'!B47 -> WTE Legal Costs for CMFA & Non-Profit Partner | D51: =SUM('SCHEDULE OF VALUE WORKSHEET'!E47) -> 20000 | E51: =SUM('Draw #7'!E51:F51) -> 0 | F51: 0 | G51: =SUM('Draw #7'!G51)+F51 -> 20000 | H51: =SUM(G51-J51) -> 20000 | I51: 0 | J51: =SUM(I51+'Draw #7'!J51) -> 0 | K51: =IF(J51=0,"",J51/G51)
A52: ='SCHEDULE OF VALUE WORKSHEET'!#REF! -> #REF! | B52: ='SCHEDULE OF VALUE WORKSHEET'!#REF! -> #REF! | D52: =SUM('SCHEDULE OF VALUE WORKSHEET'!#REF!) -> #REF! | E52: =SUM('Draw #7'!E52:F52) -> 0 | F52: 0 | G52: =SUM('Draw #7'!G52)+F52 -> #REF! | H52: =SUM(G52-J52) -> #REF! | I52: 0 | J52: =SUM(I52+'Draw #7'!J52) -> 0 | K52: =IF(J52=0,"",J52/G52)
A53: ='SCHEDULE OF VALUE WORKSHEET'!A49 -> 43 | B53: ='SCHEDULE OF VALUE WORKSHEET'!B49 -> GENERAL CONDITIONS | D53: =SUM('SCHEDULE OF VALUE WORKSHEET'!E49) -> 362115.24 | E53: =SUM('Draw #7'!E53:F53) -> 0 | F53: 0 | G53: =SUM('Draw #7'!G53)+F53 -> 362115.24 | H53: =SUM(G53-J53) -> 362115.24 | I53: 0 | J53: =SUM(I53+'Draw #7'!J53) -> 0 | K53: =IF(J53=0,"",J53/G53)
A54: ='SCHEDULE OF VALUE WORKSHEET'!A50 -> 44 | B54: ='SCHEDULE OF VALUE WORKSHEET'!B50 -> GENERAL REQUIREMENT | D54: =SUM('SCHEDULE OF VALUE WORKSHEET'!E50) -> 124657.88 | E54: =SUM('Draw #7'!E54:F54) -> 0 | F54: 0 | G54: =SUM('Draw #7'!G54)+F54 -> 124657.88 | H54: =SUM(G54-J54) -> 124657.88 | I54: 0 | J54: =SUM(I54+'Draw #7'!J54) -> 0 | K54: =IF(J54=0,"",J54/G54)
A55: ='SCHEDULE OF VALUE WORKSHEET'!A51 -> 45 | B55: ='SCHEDULE OF VALUE WORKSHEET'!B51 -> SITE WORK | D55: =SUM('SCHEDULE OF VALUE WORKSHEET'!E51) -> 139049.51 | E55: =SUM('Draw #7'!E55:F55) -> 0 | F55: 0 | G55: =SUM('Draw #7'!G55)+F55 -> 139049.51 | H55: =SUM(G55-J55) -> 139049.51 | I55: 0 | J55: =SUM(I55+'Draw #7'!J55) -> 0 | K55: =IF(J55=0,"",J55/G55)
A56: ='SCHEDULE OF VALUE WORKSHEET'!A52 -> 46 | B56: ='SCHEDULE OF VALUE WORKSHEET'!B52 -> CONCRETE | D56: =SUM('SCHEDULE OF VALUE WORKSHEET'!E52) -> 253182 | E56: =SUM('Draw #7'!E56:F56) -> 0 | F56: 0 | G56: =SUM('Draw #7'!G56)+F56 -> 253182 | H56: =SUM(G56-J56) -> 253182 | I56: 0 | J56: =SUM(I56+'Draw #7'!J56) -> 0 | K56: =IF(J56=0,"",J56/G56)
A57: ='SCHEDULE OF VALUE WORKSHEET'!A53 -> 47 | B57: ='SCHEDULE OF VALUE WORKSHEET'!B53 -> MASONRY | D57: =SUM('SCHEDULE OF VALUE WORKSHEET'!E53) -> 3562.64 | E57: =SUM('Draw #7'!E57:F57) -> 0 | F57: 0 | G57: =SUM('Draw #7'!G57)+F57 -> 3562.64 | H57: =SUM(G57-J57) -> 3562.64 | I57: 0 | J57: =SUM(I57+'Draw #7'!J57) -> 0 | K57: =IF(J57=0,"",J57/G57)
A58: ='SCHEDULE OF VALUE WORKSHEET'!A54 -> 48 | B58: ='SCHEDULE OF VALUE WORKSHEET'!B54 -> METALS | D58: =SUM('SCHEDULE OF VALUE WORKSHEET'!E54) -> 324100 | E58: =SUM('Draw #7'!E58:F58) -> 0 | F58: 0 | G58: =SUM('Draw #7'!G58)+F58 -> 324100 | H58: =SUM(G58-J58) -> 324100 | I58: 0 | J58: =SUM(I58+'Draw #7'!J58) -> 0 | K58: =IF(J58=0,"",J58/G58)
A59: ='SCHEDULE OF VALUE WORKSHEET'!A55 -> 49 | B59: ='SCHEDULE OF VALUE WORKSHEET'!B55 -> FRAMING | D59: =SUM('SCHEDULE OF VALUE WORKSHEET'!E55) -> 818554 | E59: =SUM('Draw #7'!E59:F59) -> 0 | F59: 0 | G59: =SUM('Draw #7'!G59)+F59 -> 818554 | H59: =SUM(G59-J59) -> 818554 | I59: 0 | J59: =SUM(I59+'Draw #7'!J59) -> 0 | K59: =IF(J59=0,"",J59/G59)
A60: ='SCHEDULE OF VALUE WORKSHEET'!A56 -> 50 | B60: ='SCHEDULE OF VALUE WORKSHEET'!B56 -> COUNTERTOPS | D60: =SUM('SCHEDULE OF VALUE WORKSHEET'!E56) -> 56930 | E60: =SUM('Draw #7'!E60:F60) -> 0 | F60: 0 | G60: =SUM('Draw #7'!G60)+F60 -> 56930 | H60: =SUM(G60-J60) -> 56930 | I60: 0 | J60: =SUM(I60+'Draw #7'!J60) -> 0 | K60: =IF(J60=0,"",J60/G60)
A61: ='SCHEDULE OF VALUE WORKSHEET'!A57 -> 51 | B61: ='SCHEDULE OF VALUE WORKSHEET'!B57 -> CABINETS | D61: =SUM('SCHEDULE OF VALUE WORKSHEET'!E57) -> 56930 | E61: =SUM('Draw #7'!E61:F61) -> 0 | F61: 0 | G61: =SUM('Draw #7'!G61)+F61 -> 56930 | H61: =SUM(G61-J61) -> 56930 | I61: 0 | J61: =SUM(I61+'Draw #7'!J61) -> 0 | K61: =IF(J61=0,"",J61/G61)
A62: ='SCHEDULE OF VALUE WORKSHEET'!A58 -> 52 | B62: ='SCHEDULE OF VALUE WORKSHEET'!B58 -> THERMAL MOISTURE PROTECTION | D62: =SUM('SCHEDULE OF VALUE WORKSHEET'!E58) -> 173148 | E62: =SUM('Draw #7'!E62:F62) -> 0 | F62: 0 | G62: =SUM('Draw #7'!G62)+F62 -> 173148 | H62: =SUM(G62-J62) -> 173148 | I62: 0 | J62: =SUM(I62+'Draw #7'!J62) -> 0 | K62: =IF(J62=0,"",J62/G62)
A63: ='SCHEDULE OF VALUE WORKSHEET'!A59 -> 53 | B63: ='SCHEDULE OF VALUE WORKSHEET'!B59 -> DOORS | D63: =SUM('SCHEDULE OF VALUE WORKSHEET'!E59) -> 204087.33 | E63: =SUM('Draw #7'!E63:F63) -> 0 | F63: 0 | G63: =SUM('Draw #7'!G63)+F63 -> 204087.33 | H63: =SUM(G63-J63) -> 204087.33 | I63: 0 | J63: =SUM(I63+'Draw #7'!J63) -> 0 | K63: =IF(J63=0,"",J63/G63)
A64: ='SCHEDULE OF VALUE WORKSHEET'!A60 -> 54 | B64: ='SCHEDULE OF VALUE WORKSHEET'!B60 -> WINDOWS | D64: =SUM('SCHEDULE OF VALUE WORKSHEET'!E60) -> 106274.25 | E64: =SUM('Draw #7'!E64:F64) -> 0 | F64: 0 | G64: =SUM('Draw #7'!G64)+F64 -> 106274.25 | H64: =SUM(G64-J64) -> 106274.25 | I64: 0 | J64: =SUM(I64+'Draw #7'!J64) -> 0 | K64: =IF(J64=0,"",J64/G64)
... A90: ='SCHEDULE OF VALUE WORKSHEET'!A86 -> 80 | B90: ='SCHEDULE OF VALUE WORKSHEET'!B86 -> FINANCING COSTS | D90: =SUM('SCHEDULE OF VALUE WORKSHEET'!E86) -> 0 | E90: =SUM('Draw #7'!E90:F90) -> 0 | F90: 0 | G90: =SUM('Draw #7'!G90)+F90 -> 0 | H90: =SUM(G90-J90) -> 0 | I90: 0 | J90: =SUM(I90+'Draw #7'!J90) -> 0 | K90: =IF(J90=0,"",J90/G90)
A91: ='SCHEDULE OF VALUE WORKSHEET'!#REF! -> #REF! | B91: ='SCHEDULE OF VALUE WORKSHEET'!#REF! -> #REF! | D91: =SUM('SCHEDULE OF VALUE WORKSHEET'!#REF!) -> #REF! | E91: =SUM('Draw #7'!E91:F91) -> 0 | F91: 0 | G91: =SUM('Draw #7'!G91)+F91 -> #REF! | H91: =SUM(G91-J91) -> #REF! | I91: 0 | J91: =SUM(I91+'Draw #7'!J91) -> 0 | K91: =IF(J91=0,"",J91/G91)
A92: ='SCHEDULE OF VALUE WORKSHEET'!#REF! -> #REF! | B92: ='SCHEDULE OF VALUE WORKSHEET'!#REF! -> #REF! | D92: =SUM('SCHEDULE OF VALUE WORKSHEET'!#REF!) -> #REF! | E92: =SUM('Draw #7'!E92:F92) -> 0 | F92: 0 | G92: =SUM('Draw #7'!G92)+F92 -> #REF! | H92: =SUM(G92-J92) -> #REF! | I92: 0 | J92: =SUM(I92+'Draw #7'!J92) -> 0 | K92: =IF(J92=0,"",J92/G92)
A93: ='SCHEDULE OF VALUE WORKSHEET'!#REF! -> #REF! | B93: ='SCHEDULE OF VALUE WORKSHEET'!#REF! -> #REF! | D93: =SUM('SCHEDULE OF VALUE WORKSHEET'!#REF!) -> #REF! | E93: =SUM('Draw #7'!E93:F93) -> 0 | F93: 0 | G93: =SUM('Draw #7'!G93)+F93 -> #REF! | H93: =SUM(G93-J93) -> #REF! | I93: 0 | J93: =SUM(I93+'Draw #7'!J93) -> 0 | K93: =IF(J93=0,"",J93/G93)
A94: ='SCHEDULE OF VALUE WORKSHEET'!#REF! -> #REF! | B94: ='SCHEDULE OF VALUE WORKSHEET'!#REF! -> #REF! | D94: =SUM('SCHEDULE OF VALUE WORKSHEET'!#REF!) -> #REF! | E94: =SUM('Draw #7'!E94:F94) -> 0 | F94: 0 | G94: =SUM('Draw #7'!G94)+F94 -> #REF! | H94: =SUM(G94-J94) -> #REF! | I94: 0 | J94: =SUM(I94+'Draw #7'!J94) -> 0 | K94: =IF(J94=0,"",J94/G94)
A95: ='SCHEDULE OF VALUE WORKSHEET'!#REF! -> #REF! | B95: ='SCHEDULE OF VALUE WORKSHEET'!#REF! -> #REF! | D95: =SUM('SCHEDULE OF VALUE WORKSHEET'!#REF!) -> #REF! | E95: =SUM('Draw #7'!E95:F95) -> 0 | F95: 0 | G95: =SUM('Draw #7'!G95)+F95 -> #REF! | H95: =SUM(G95-J95) -> #REF! | I95: 0 | J95: =SUM(I95+'Draw #7'!J95) -> 0 | K95: =IF(J95=0,"",J95/G95)
A96: ='SCHEDULE OF VALUE WORKSHEET'!#REF! -> #REF! | B96: ='SCHEDULE OF VALUE WORKSHEET'!#REF! -> #REF! | D96: =SUM('SCHEDULE OF VALUE WORKSHEET'!#REF!) -> #REF! | E96: =SUM('Draw #7'!E96:F96) -> 0 | F96: 0 | G96: =SUM('Draw #7'!G96)+F96 -> #REF! | H96: =SUM(G96-J96) -> #REF! | I96: 0 | J96: =SUM(I96+'Draw #7'!J96) -> 0 | K96: =IF(J96=0,"",J96/G96)
A97: ='SCHEDULE OF VALUE WORKSHEET'!#REF! -> #REF! | B97: ='SCHEDULE OF VALUE WORKSHEET'!#REF! -> #REF! | D97: =SUM('SCHEDULE OF VALUE WORKSHEET'!#REF!) -> #REF! | E97: =SUM('Draw #7'!E97:F97) -> 0 | F97: 0 | G97: =SUM('Draw #7'!G97)+F97 -> #REF! | H97: =SUM(G97-J97) -> #REF! | I97: 0 | J97: =SUM(I97+'Draw #7'!J97) -> 0 | K97: =IF(J97=0,"",J97/G97)
A98: ='SCHEDULE OF VALUE WORKSHEET'!#REF! -> #REF! | B98: ='SCHEDULE OF VALUE WORKSHEET'!#REF! -> #REF! | D98: =SUM('SCHEDULE OF VALUE WORKSHEET'!#REF!) -> #REF! | E98: =SUM('Draw #7'!E98:F98) -> 0 | F98: 0 | G98: =SUM('Draw #7'!G98)+F98 -> #REF! | H98: =SUM(G98-J98) -> #REF! | I98: 0 | J98: =SUM(I98+'Draw #7'!J98) -> 0 | K98: =IF(J98=0,"",J98/G98)
A99: ='SCHEDULE OF VALUE WORKSHEET'!#REF! -> #REF! | B99: ='SCHEDULE OF VALUE WORKSHEET'!#REF! -> #REF! | D99: =SUM('SCHEDULE OF VALUE WORKSHEET'!#REF!) -> #REF! | E99: =SUM('Draw #7'!E99:F99) -> 0 | F99: 0 | G99: =SUM('Draw #7'!G99)+F99 -> #REF! | H99: =SUM(G99-J99) -> #REF! | I99: 0 | J99: =SUM(I99+'Draw #7'!J99) -> 0 | K99: =IF(J99=0,"",J99/G99)
A100: ='SCHEDULE OF VALUE WORKSHEET'!#REF! -> #REF! | B100: ='SCHEDULE OF VALUE WORKSHEET'!#REF! -> #REF! | D100: =SUM('SCHEDULE OF VALUE WORKSHEET'!#REF!) -> #REF! | E100: =SUM('Draw #7'!E100:F100) -> 0 | F100: 0 | G100: =SUM('Draw #7'!G100)+F100 -> #REF! | H100: =SUM(G100-J100) -> #REF! | I100: 0 | J100: =SUM(I100+'Draw #7'!J100) -> 0 | K100: =IF(J100=0,"",J100/G100)
A101: ='SCHEDULE OF VALUE WORKSHEET'!#REF! -> #REF! | B101: ='SCHEDULE OF VALUE WORKSHEET'!#REF! -> #REF! | D101: =SUM('SCHEDULE OF VALUE WORKSHEET'!#REF!) -> #REF! | E101: =SUM('Draw #7'!E101:F101) -> 0 | F101: 0 | G101: =SUM('Draw #7'!G101)+F101 -> #REF! | H101: =SUM(G101-J101) -> #REF! | I101: 0 | J101: =SUM(I101+'Draw #7'!J101) -> 0 | K101: =IF(J101=0,"",J101/G101)
A102: ='SCHEDULE OF VALUE WORKSHEET'!#REF! -> #REF! | B102: ='SCHEDULE OF VALUE WORKSHEET'!#REF! -> #REF! | D102: =SUM('SCHEDULE OF VALUE WORKSHEET'!#REF!) -> #REF! | E102: =SUM('Draw #7'!E102:F102) -> 0 | F102: 0 | G102: =SUM('Draw #7'!G102)+F102 -> #REF! | H102: =SUM(G102-J102) -> #REF! | I102: 0 | J102: =SUM(I102+'Draw #7'!J102) -> 0 | K102: =IF(J102=0,"",J102/G102)
... A116: ='SCHEDULE OF VALUE WORKSHEET'!#REF! -> #REF! | B116: ='SCHEDULE OF VALUE WORKSHEET'!#REF! -> #REF! | D116: =SUM('SCHEDULE OF VALUE WORKSHEET'!#REF!) -> #REF! | E116: =SUM('Draw #7'!E116:F116) -> 0 | F116: 0 | G116: =SUM('Draw #7'!G116)+F116 -> #REF! | H116: =SUM(G116-J116) -> #REF! | I116: 0 | J116: =SUM(I116+'Draw #7'!J116) -> 0 | K116: =IF(J116=0,"",J116/G116)
A117: ='SCHEDULE OF VALUE WORKSHEET'!A87 -> 82 | B117: ='SCHEDULE OF VALUE WORKSHEET'!B87 -> Open Item | D117: =SUM('SCHEDULE OF VALUE WORKSHEET'!E87) -> 0 | E117: =SUM('Draw #7'!E117:F117) -> 0 | F117: 0 | G117: =SUM('Draw #7'!G117)+F117 -> 0 | H117: =SUM(G117-J117) -> 0 | I117: 0 | J117: =SUM(I117+'Draw #7'!J117) -> 0 | K117: =IF(J117=0,"",J117/G117)
A118: ='SCHEDULE OF VALUE WORKSHEET'!A88 -> 83 | B118: ='SCHEDULE OF VALUE WORKSHEET'!B88 -> Open Item | D118: =SUM('SCHEDULE OF VALUE WORKSHEET'!E88) -> 0 | E118: =SUM('Draw #7'!E118:F118) -> 0 | F118: 0 | G118: =SUM('Draw #7'!G118)+F118 -> 0 | H118: =SUM(G118-J118) -> 0 | I118: 0 | J118: =SUM(I118+'Draw #7'!J118) -> 0 | K118: =IF(J118=0,"",J118/G118)
A119: ='SCHEDULE OF VALUE WORKSHEET'!A89 -> 84 | B119: ='SCHEDULE OF VALUE WORKSHEET'!B89 -> Open Item | D119: =SUM('SCHEDULE OF VALUE WORKSHEET'!E89) -> 0 | E119: =SUM('Draw #7'!E119:F119) -> 0 | F119: 0 | G119: =SUM('Draw #7'!G119)+F119 -> 0 | H119: =SUM(G119-J119) -> 0 | I119: 0 | J119: =SUM(I119+'Draw #7'!J119) -> 0 | K119: =IF(J119=0,"",J119/G119)
A120: ='SCHEDULE OF VALUE WORKSHEET'!A90 -> 85 | B120: ='SCHEDULE OF VALUE WORKSHEET'!B90 -> Open Item | D120: =SUM('SCHEDULE OF VALUE WORKSHEET'!E90) -> 0 | E120: =SUM('Draw #7'!E120:F120) -> 0 | F120: 0 | G120: =SUM('Draw #7'!G120)+F120 -> 0 | H120: =SUM(G120-J120) -> 0 | I120: 0 | J120: =SUM(I120+'Draw #7'!J120) -> 0 | K120: =IF(J120=0,"",J120/G120)
A121: ='SCHEDULE OF VALUE WORKSHEET'!A91 -> 86 | B121: ='SCHEDULE OF VALUE WORKSHEET'!B91 -> Open Item | D121: =SUM('SCHEDULE OF VALUE WORKSHEET'!E91) -> 0 | E121: =SUM('Draw #7'!E121:F121) -> 0 | F121: 0 | G121: =SUM('Draw #7'!G121)+F121 -> 0 | H121: =SUM(G121-J121) -> 0 | I121: 0 | J121: =SUM(I121+'Draw #7'!J121) -> 0 | K121: =IF(J121=0,"",J121/G121)
A122: ='SCHEDULE OF VALUE WORKSHEET'!A92 -> 87 | B122: ='SCHEDULE OF VALUE WORKSHEET'!B92 -> Open Item | D122: =SUM('SCHEDULE OF VALUE WORKSHEET'!E92) -> 0 | E122: =SUM('Draw #7'!E122:F122) -> 0 | F122: 0 | G122: =SUM('Draw #7'!G122)+F122 -> 0 | H122: =SUM(G122-J122) -> 0 | I122: 0 | J122: =SUM(I122+'Draw #7'!J122) -> 0 | K122: =IF(J122=0,"",J122/G122)
A123: ='SCHEDULE OF VALUE WORKSHEET'!A93 -> 88 | B123: ='SCHEDULE OF VALUE WORKSHEET'!B93 -> Open Item | D123: =SUM('SCHEDULE OF VALUE WORKSHEET'!E93) -> 0 | E123: =SUM('Draw #7'!E123:F123) -> 0 | F123: 0 | G123: =SUM('Draw #7'!G123)+F123 -> 0 | H123: =SUM(G123-J123) -> 0 | I123: 0 | J123: =SUM(I123+'Draw #7'!J123) -> 0 | K123: =IF(J123=0,"",J123/G123)
A124: ='SCHEDULE OF VALUE WORKSHEET'!A94 -> 89 | B124: ='SCHEDULE OF VALUE WORKSHEET'!B94 -> Open Item | D124: =SUM('SCHEDULE OF VALUE WORKSHEET'!E94) -> 0 | E124: =SUM('Draw #7'!E124:F124) -> 0 | F124: 0 | G124: =SUM('Draw #7'!G124)+F124 -> 0 | H124: =SUM(G124-J124) -> 0 | I124: 0 | J124: =SUM(I124+'Draw #7'!J124) -> 0 | K124: =IF(J124=0,"",J124/G124)
A125: ='SCHEDULE OF VALUE WORKSHEET'!A95 -> 90 | B125: ='SCHEDULE OF VALUE WORKSHEET'!B95 -> Open Item | D125: =SUM('SCHEDULE OF VALUE WORKSHEET'!E95) -> 0 | E125: =SUM('Draw #7'!E125:F125) -> 0 | F125: 0 | G125: =SUM('Draw #7'!G125)+F125 -> 0 | H125: =SUM(G125-J125) -> 0 | I125: 0 | J125: =SUM(I125+'Draw #7'!J125) -> 0 | K125: =IF(J125=0,"",J125/G125)
A126: ='SCHEDULE OF VALUE WORKSHEET'!A96 -> 91 | B126: ='SCHEDULE OF VALUE WORKSHEET'!B96 -> Open Item | D126: =SUM('SCHEDULE OF VALUE WORKSHEET'!E96) -> 0 | E126: =SUM('Draw #7'!E126:F126) -> 0 | F126: 0 | G126: =SUM('Draw #7'!G126)+F126 -> 0 | H126: =SUM(G126-J126) -> 0 | I126: 0 | J126: =SUM(I126+'Draw #7'!J126) -> 0 | K126: =IF(J126=0,"",J126/G126)
A127: ='SCHEDULE OF VALUE WORKSHEET'!A97 -> 92 | B127: ='SCHEDULE OF VALUE WORKSHEET'!B97 -> Open Item | D127: =SUM('SCHEDULE OF VALUE WORKSHEET'!E97) -> 0 | E127: =SUM('Draw #7'!E127:F127) -> 0 | F127: 0 | G127: =SUM('Draw #7'!G127)+F127 -> 0 | H127: =SUM(G127-J127) -> 0 | I127: 0 | J127: =SUM(I127+'Draw #7'!J127) -> 0 | K127: =IF(J127=0,"",J127/G127)
A128: ='SCHEDULE OF VALUE WORKSHEET'!A98 -> 93 | B128: ='SCHEDULE OF VALUE WORKSHEET'!B98 -> Open Item | D128: =SUM('SCHEDULE OF VALUE WORKSHEET'!E98) -> 0 | E128: =SUM('Draw #7'!E128:F128) -> 0 | F128: 0 | G128: =SUM('Draw #7'!G128)+F128 -> 0 | H128: =SUM(G128-J128) -> 0 | I128: 0 | J128: =SUM(I128+'Draw #7'!J128) -> 0 | K128: =IF(J128=0,"",J128/G128)
... A134: ='SCHEDULE OF VALUE WORKSHEET'!A104 -> 99 | B134: ='SCHEDULE OF VALUE WORKSHEET'!B104 -> Open Item | D134: =SUM('SCHEDULE OF VALUE WORKSHEET'!E104) -> 0 | E134: =SUM('Draw #7'!E134:F134) -> 0 | F134: 0 | G134: =SUM('Draw #7'!G134)+F134 -> 0 | H134: =SUM(G134-J134) -> 0 | I134: 0 | J134: =SUM(I134+'Draw #7'!J134) -> 0 | K134: =IF(J134=0,"",J134/G134)
A135: ='SCHEDULE OF VALUE WORKSHEET'!#REF! -> #REF! | B135: ='SCHEDULE OF VALUE WORKSHEET'!#REF! -> #REF! | D135: =SUM('SCHEDULE OF VALUE WORKSHEET'!#REF!) -> #REF! | E135: =SUM('Draw #7'!E135:F135) -> 0 | F135: 0 | G135: =SUM('Draw #7'!G135)+F135 -> #REF! | H135: =SUM(G135-J135) -> #REF! | I135: 0 | J135: =SUM(I135+'Draw #7'!J135) -> 0 | K135: =IF(J135=0,"",J135/G135)
B137: TOTAL | D137: =SUM(D10:D135) -> #REF! | E137: =SUM(E10:E135) -> 0 | F137: =SUM(F10:F135) -> 0 | G137: =SUM(G10:G135) -> #REF! | H137: =SUM(H10:H135) -> #REF! | I137: =SUM(I10:I135) -> 0 | J137: =SUM(J10:J135) -> 0

Sheet Draw #9
A1: GENESIS CAPITAL DRAW FORM
B3: CLIENT: | C3: ='SCHEDULE OF VALUE WORKSHEET'!$B$3 -> Angeleno Investments | I3: TOTAL COMPLETED TO DATE: | J3: =SUM(J137) -> 0 | K3: =SUM(J3)/J7 -> #REF!
B4: DATE: | C4: =TODAY() -> 45978 | I4: REMAINING $ IN BUDGET: | J4: =SUM(H137) -> #REF!
B5: PROJECT: | C5: ='SCHEDULE OF VALUE WORKSHEET'!B5 -> 10910 Huston Street | I5: ORIGINAL SCHEDULE OF VALUES: | J5: =SUM(D137) -> #REF!
B6: DRAW REQUEST: | C6: =SUM(I137) -> 0 | I6: CHANGE ORDERS: | J6: =SUM(F137) -> 0
I7: REVISED SCHEDULE OF VALUES: | J7: =SUM(G137) -> #REF!
B8: DESCRIPTION OF WORK | D8: SCHEDULED VALUES | E8: PREVIOUS | F8: + / - CHANGES | G8: REVISED VALUES | H8: REMAINING | I8: DRAW | J8: COMPLETED AND
E9: CHANGES | H9: BUDGET | I9: 9 | J9: STORED TO DATE
A10: ='SCHEDULE OF VALUE WORKSHEET'!A7 -> 1 | B10: ='SCHEDULE OF VALUE WORKSHEET'!B7 -> SOFT COSTS | D10: =SUM('SCHEDULE OF VALUE WORKSHEET'!E7) -> 0 | E10: =SUM('Draw #8'!E10:F10) -> 0 | F10: 0 | G10: =SUM('Draw #8'!G10)+F10 -> 0 | H10: =SUM(G10-J10) -> 0 | I10: 0 | J10: =SUM(I10+'Draw #8'!J10) -> 0 | K10: =IF(J10=0,"",J10/G10)
A11: ='SCHEDULE OF VALUE WORKSHEET'!A8 -> 2 | B11: ='SCHEDULE OF VALUE WORKSHEET'!B8 -> Site Security | D11: =SUM('SCHEDULE OF VALUE WORKSHEET'!E8) -> 10580.63 | E11: =SUM('Draw #8'!E11:F11) -> 0 | F11: 0 | G11: =SUM('Draw #8'!G11)+F11 -> 10580.63 | H11: =SUM(G11-J11) -> 10580.63 | I11: 0 | J11: =SUM(I11+'Draw #8'!J11) -> 0 | K11: =IF(J11=0,"",J11/G11)
A12: ='SCHEDULE OF VALUE WORKSHEET'!A9 -> 3 | B12: ='SCHEDULE OF VALUE WORKSHEET'!B9 -> Soils Inspection | D12: =SUM('SCHEDULE OF VALUE WORKSHEET'!E9) -> 0 | E12: =SUM('Draw #8'!E12:F12) -> 0 | F12: 0 | G12: =SUM('Draw #8'!G12)+F12 -> 0 | H12: =SUM(G12-J12) -> 0 | I12: 0 | J12: =SUM(I12+'Draw #8'!J12) -> 0 | K12: =IF(J12=0,"",J12/G12)
A13: ='SCHEDULE OF VALUE WORKSHEET'!A10 -> 4 | B13: ='SCHEDULE OF VALUE WORKSHEET'!B10 -> Offsites (Transformer) | D13: =SUM('SCHEDULE OF VALUE WORKSHEET'!E10) -> 20000 | E13: =SUM('Draw #8'!E13:F13) -> 0 | F13: 0 | G13: =SUM('Draw #8'!G13)+F13 -> 20000 | H13: =SUM(G13-J13) -> 20000 | I13: 0 | J13: =SUM(I13+'Draw #8'!J13) -> 0 | K13: =IF(J13=0,"",J13/G13)
A14: ='SCHEDULE OF VALUE WORKSHEET'!A11 -> 5 | B14: ='SCHEDULE OF VALUE WORKSHEET'!B11 -> Plan Check Fees | D14: =SUM('SCHEDULE OF VALUE WORKSHEET'!E11) -> 0 | E14: =SUM('Draw #8'!E14:F14) -> 0 | F14: 0 | G14: =SUM('Draw #8'!G14)+F14 -> 0 | H14: =SUM(G14-J14) -> 0 | I14: 0 | J14: =SUM(I14+'Draw #8'!J14) -> 0 | K14: =IF(J14=0,"",J14/G14)
A15: ='SCHEDULE OF VALUE WORKSHEET'!A12 -> 6 | B15: ='SCHEDULE OF VALUE WORKSHEET'!B12 -> Permits | D15: =SUM('SCHEDULE OF VALUE WORKSHEET'!E12) -> 0 | E15: =SUM('Draw #8'!E15:F15) -> 0 | F15: 0 | G15: =SUM('Draw #8'!G15)+F15 -> 0 | H15: =SUM(G15-J15) -> 0 | I15: 0 | J15: =SUM(I15+'Draw #8'!J15) -> 0 | K15: =IF(J15=0,"",J15/G15)
A16: ='SCHEDULE OF VALUE WORKSHEET'!A13 -> 7 | B16: ='SCHEDULE OF VALUE WORKSHEET'!B13 -> Survey | D16: =SUM('SCHEDULE OF VALUE WORKSHEET'!E13) -> 0 | E16: =SUM('Draw #8'!E16:F16) -> 0 | F16: 0 | G16: =SUM('Draw #8'!G16)+F16 -> 0 | H16: =SUM(G16-J16) -> 0 | I16: 0 | J16: =SUM(I16+'Draw #8'!J16) -> 0 | K16: =IF(J16=0,"",J16/G16)
A17: ='SCHEDULE OF VALUE WORKSHEET'!A14 -> 8 | B17: ='SCHEDULE OF VALUE WORKSHEET'!B14 -> Soils Engineer | D17: =SUM('SCHEDULE OF VALUE WORKSHEET'!E14) -> 0 | E17: =SUM('Draw #8'!E17:F17) -> 0 | F17: 0 | G17: =SUM('Draw #8'!G17)+F17 -> 0 | H17: =SUM(G17-J17) -> 0 | I17: 0 | J17: =SUM(I17+'Draw #8'!J17) -> 0 | K17: =IF(J17=0,"",J17/G17)
A18: ='SCHEDULE OF VALUE WORKSHEET'!A15 -> 9 | B18: ='SCHEDULE OF VALUE WORKSHEET'!B15 -> Soils Permit + T24 | D18: =SUM('SCHEDULE OF VALUE WORKSHEET'!E15) -> 2500 | E18: =SUM('Draw #8'!E18:F18) -> 0 | F18: 0 | G18: =SUM('Draw #8'!G18)+F18 -> 2500 | H18: =SUM(G18-J18) -> 2500 | I18: 0 | J18: =SUM(I18+'Draw #8'!J18) -> 0 | K18: =IF(J18=0,"",J18/G18)
A19: ='SCHEDULE OF VALUE WORKSHEET'!A16 -> 10 | B19: ='SCHEDULE OF VALUE WORKSHEET'!B16 -> Special Inspections - Deputy | D19: =SUM('SCHEDULE OF VALUE WORKSHEET'!E16) -> 15000 | E19: =SUM('Draw #8'!E19:F19) -> 0 | F19: 0 | G19: =SUM('Draw #8'!G19)+F19 -> 15000 | H19: =SUM(G19-J19) -> 15000 | I19: 0 | J19: =SUM(I19+'Draw #8'!J19) -> 0 | K19: =IF(J19=0,"",J19/G19)
A20: ='SCHEDULE OF VALUE WORKSHEET'!A17 -> 11 | B20: ='SCHEDULE OF VALUE WORKSHEET'!B17 -> Architect | D20: =SUM('SCHEDULE OF VALUE WORKSHEET'!E17) -> 0 | E20: =SUM('Draw #8'!E20:F20) -> 0 | F20: 0 | G20: =SUM('Draw #8'!G20)+F20 -> 0 | H20: =SUM(G20-J20) -> 0 | I20: 0 | J20: =SUM(I20+'Draw #8'!J20) -> 0 | K20: =IF(J20=0,"",J20/G20)
A21: ='SCHEDULE OF VALUE WORKSHEET'!A18 -> 12 | B21: ='SCHEDULE OF VALUE WORKSHEET'!B18 -> Structural Engineer | D21: =SUM('SCHEDULE OF VALUE WORKSHEET'!E18) -> 0 | E21: =SUM('Draw #8'!E21:F21) -> 0 | F21: 0 | G21: =SUM('Draw #8'!G21)+F21 -> 0 | H21: =SUM(G21-J21) -> 0 | I21: 0 | J21: =SUM(I21+'Draw #8'!J21) -> 0 | K21: =IF(J21=0,"",J21/G21)
... A45: ='SCHEDULE OF VALUE WORKSHEET'!A42 -> 36 | B45: ='SCHEDULE OF VALUE WORKSHEET'!B42 -> Construction Management / Observation (OO) | D45: =SUM('SCHEDULE OF VALUE WORKSHEET'!E42) -> 49427.9 | E45: =SUM('Draw #8'!E45:F45) -> 0 | F45: 0 | G45: =SUM('Draw #8'!G45)+F45 -> 49427.9 | H45: =SUM(G45-J45) -> 49427.9 | I45: 0 | J45: =SUM(I45+'Draw #8'!J45) -> 0 | K45: =IF(J45=0,"",J45/G45)
A46: ='SCHEDULE OF VALUE WORKSHEET'!#REF! -> #REF! | B46: ='SCHEDULE OF VALUE WORKSHEET'!#REF! -> #REF! | D46: =SUM('SCHEDULE OF VALUE WORKSHEET'!#REF!) -> #REF! | E46: =SUM('Draw #8'!E46:F46) -> 0 | F46: 0 | G46: =SUM('Draw #8'!G46)+F46 -> #REF! | H46: =SUM(G46-J46) -> #REF! | I46: 0 | J46: =SUM(I46+'Draw #8'!J46) -> 0 | K46: =IF(J46=0,"",J46/G46)
A47: ='SCHEDULE OF VALUE WORKSHEET'!A43 -> 37 | B47: ='SCHEDULE OF VALUE WORKSHEET'!B43 -> CMFA Startup Fee | D47: =SUM('SCHEDULE OF VALUE WORKSHEET'!E43) -> 22800 | E47: =SUM('Draw #8'!E47:F47) -> 0 | F47: 0 | G47: =SUM('Draw #8'!G47)+F47 -> 22800 | H47: =SUM(G47-J47) -> 22800 | I47: 0 | J47: =SUM(I47+'Draw #8'!J47) -> 0 | K47: =IF(J47=0,"",J47/G47)
A48: ='SCHEDULE OF VALUE WORKSHEET'!A44 -> 38 | B48: ='SCHEDULE OF VALUE WORKSHEET'!B44 -> Non-Profit Start Up Fee | D48: =SUM('SCHEDULE OF VALUE WORKSHEET'!E44) -> 25000 | E48: =SUM('Draw #8'!E48:F48) -> 0 | F48: 0 | G48: =SUM('Draw #8'!G48)+F48 -> 25000 | H48: =SUM(G48-J48) -> 25000 | I48: 0 | J48: =SUM(I48+'Draw #8'!J48) -> 0 | K48: =IF(J48=0,"",J48/G48)
A49: ='SCHEDULE OF VALUE WORKSHEET'!A45 -> 39 | B49: ='SCHEDULE OF VALUE WORKSHEET'!B45 -> CMFA Construction Fee | D49: =SUM('SCHEDULE OF VALUE WORKSHEET'!E45) -> 12000 | E49: =SUM('Draw #8'!E49:F49) -> 0 | F49: 0 | G49: =SUM('Draw #8'!G49)+F49 -> 12000 | H49: =SUM(G49-J49) -> 12000 | I49: 0 | J49: =SUM(I49+'Draw #8'!J49) -> 0 | K49: =IF(J49=0,"",J49/G49)
A50: ='SCHEDULE OF VALUE WORKSHEET'!A46 -> 40 | B50: ='SCHEDULE OF VALUE WORKSHEET'!B46 -> Non-Profit Construction Fee | D50: =SUM('SCHEDULE OF VALUE WORKSHEET'!E46) -> 10000 | E50: =SUM('Draw #8'!E50:F50) -> 0 | F50: 0 | G50: =SUM('Draw #8'!G50)+F50 -> 10000 | H50: =SUM(G50-J50) -> 10000 | I50: 0 | J50: =SUM(I50+'Draw #8'!J50) -> 0 | K50: =IF(J50=0,"",J50/G50)
A51: ='SCHEDULE OF VALUE WORKSHEET'!A47 -> 41 | B51: ='SCHEDULE OF VALUE WORKSHEET'!B47 -> WTE Legal Costs for CMFA & Non-Profit Partner | D51: =SUM('SCHEDULE OF VALUE WORKSHEET'!E47) -> 20000 | E51: =SUM('Draw #8'!E51:F51) -> 0 | F51: 0 | G51: =SUM('Draw #8'!G51)+F51 -> 20000 | H51: =SUM(G51-J51) -> 20000 | I51: 0 | J51: =SUM(I51+'Draw #8'!J51) -> 0 | K51: =IF(J51=0,"",J51/G51)
A52: ='SCHEDULE OF VALUE WORKSHEET'!#REF! -> #REF! | B52: ='SCHEDULE OF VALUE WORKSHEET'!#REF! -> #REF! | D52: =SUM('SCHEDULE OF VALUE WORKSHEET'!#REF!) -> #REF! | E52: =SUM('Draw #8'!E52:F52) -> 0 | F52: 0 | G52: =SUM('Draw #8'!G52)+F52 -> #REF! | H52: =SUM(G52-J52) -> #REF! | I52: 0 | J52: =SUM(I52+'Draw #8'!J52) -> 0 | K52: =IF(J52=0,"",J52/G52)
A53: ='SCHEDULE OF VALUE WORKSHEET'!A49 -> 43 | B53: ='SCHEDULE OF VALUE WORKSHEET'!B49 -> GENERAL CONDITIONS | D53: =SUM('SCHEDULE OF VALUE WORKSHEET'!E49) -> 362115.24 | E53: =SUM('Draw #8'!E53:F53) -> 0 | F53: 0 | G53: =SUM('Draw #8'!G53)+F53 -> 362115.24 | H53: =SUM(G53-J53) -> 362115.24 | I53: 0 | J53: =SUM(I53+'Draw #8'!J53) -> 0 | K53: =IF(J53=0,"",J53/G53)
A54: ='SCHEDULE OF VALUE WORKSHEET'!A50 -> 44 | B54: ='SCHEDULE OF VALUE WORKSHEET'!B50 -> GENERAL REQUIREMENT | D54: =SUM('SCHEDULE OF VALUE WORKSHEET'!E50) -> 124657.88 | E54: =SUM('Draw #8'!E54:F54) -> 0 | F54: 0 | G54: =SUM('Draw #8'!G54)+F54 -> 124657.88 | H54: =SUM(G54-J54) -> 124657.88 | I54: 0 | J54: =SUM(I54+'Draw #8'!J54) -> 0 | K54: =IF(J54=0,"",J54/G54)
A55: ='SCHEDULE OF VALUE WORKSHEET'!A51 -> 45 | B55: ='SCHEDULE OF VALUE WORKSHEET'!B51 -> SITE WORK | D55: =SUM('SCHEDULE OF VALUE WORKSHEET'!E51) -> 139049.51 | E55: =SUM('Draw #8'!E55:F55) -> 0 | F55: 0 | G55: =SUM('Draw #8'!G55)+F55 -> 139049.51 | H55: =SUM(G55-J55) -> 139049.51 | I55: 0 | J55: =SUM(I55+'Draw #8'!J55) -> 0 | K55: =IF(J55=0,"",J55/G55)
A56: ='SCHEDULE OF VALUE WORKSHEET'!A52 -> 46 | B56: ='SCHEDULE OF VALUE WORKSHEET'!B52 -> CONCRETE | D56: =SUM('SCHEDULE OF VALUE WORKSHEET'!E52) -> 253182 | E56: =SUM('Draw #8'!E56:F56) -> 0 | F56: 0 | G56: =SUM('Draw #8'!G56)+F56 -> 253182 | H56: =SUM(G56-J56) -> 253182 | I56: 0 | J56: =SUM(I56+'Draw #8'!J56) -> 0 | K56: =IF(J56=0,"",J56/G56)
A57: ='SCHEDULE OF VALUE WORKSHEET'!A53 -> 47 | B57: ='SCHEDULE OF VALUE WORKSHEET'!B53 -> MASONRY | D57: =SUM('SCHEDULE OF VALUE WORKSHEET'!E53) -> 3562.64 | E57: =SUM('Draw #8'!E57:F57) -> 0 | F57: 0 | G57: =SUM('Draw #8'!G57)+F57 -> 3562.64 | H57: =SUM(G57-J57) -> 3562.64 | I57: 0 | J57: =SUM(I57+'Draw #8'!J57) -> 0 | K57: =IF(J57=0,"",J57/G57)
A58: ='SCHEDULE OF VALUE WORKSHEET'!A54 -> 48 | B58: ='SCHEDULE OF VALUE WORKSHEET'!B54 -> METALS | D58: =SUM('SCHEDULE OF VALUE WORKSHEET'!E54) -> 324100 | E58: =SUM('Draw #8'!E58:F58) -> 0 | F58: 0 | G58: =SUM('Draw #8'!G58)+F58 -> 324100 | H58: =SUM(G58-J58) -> 324100 | I58: 0 | J58: =SUM(I58+'Draw #8'!J58) -> 0 | K58: =IF(J58=0,"",J58/G58)
A59: ='SCHEDULE OF VALUE WORKSHEET'!A55 -> 49 | B59: ='SCHEDULE OF VALUE WORKSHEET'!B55 -> FRAMING | D59: =SUM('SCHEDULE OF VALUE WORKSHEET'!E55) -> 818554 | E59: =SUM('Draw #8'!E59:F59) -> 0 | F59: 0 | G59: =SUM('Draw #8'!G59)+F59 -> 818554 | H59: =SUM(G59-J59) -> 818554 | I59: 0 | J59: =SUM(I59+'Draw #8'!J59) -> 0 | K59: =IF(J59=0,"",J59/G59)
A60: ='SCHEDULE OF VALUE WORKSHEET'!A56 -> 50 | B60: ='SCHEDULE OF VALUE WORKSHEET'!B56 -> COUNTERTOPS | D60: =SUM('SCHEDULE OF VALUE WORKSHEET'!E56) -> 56930 | E60: =SUM('Draw #8'!E60:F60) -> 0 | F60: 0 | G60: =SUM('Draw #8'!G60)+F60 -> 56930 | H60: =SUM(G60-J60) -> 56930 | I60: 0 | J60: =SUM(I60+'Draw #8'!J60) -> 0 | K60: =IF(J60=0,"",J60/G60)
A61: ='SCHEDULE OF VALUE WORKSHEET'!A57 -> 51 | B61: ='SCHEDULE OF VALUE WORKSHEET'!B57 -> CABINETS | D61: =SUM('SCHEDULE OF VALUE WORKSHEET'!E57) -> 56930 | E61: =SUM('Draw #8'!E61:F61) -> 0 | F61: 0 | G61: =SUM('Draw #8'!G61)+F61 -> 56930 | H61: =SUM(G61-J61) -> 56930 | I61: 0 | J61: =SUM(I61+'Draw #8'!J61) -> 0 | K61: =IF(J61=0,"",J61/G61)
A62: ='SCHEDULE OF VALUE WORKSHEET'!A58 -> 52 | B62: ='SCHEDULE OF VALUE WORKSHEET'!B58 -> THERMAL MOISTURE PROTECTION | D62: =SUM('SCHEDULE OF VALUE WORKSHEET'!E58) -> 173148 | E62: =SUM('Draw #8'!E62:F62) -> 0 | F62: 0 | G62: =SUM('Draw #8'!G62)+F62 -> 173148 | H62: =SUM(G62-J62) -> 173148 | I62: 0 | J62: =SUM(I62+'Draw #8'!J62) -> 0 | K62: =IF(J62=0,"",J62/G62)
A63: ='SCHEDULE OF VALUE WORKSHEET'!A59 -> 53 | B63: ='SCHEDULE OF VALUE WORKSHEET'!B59 -> DOORS | D63: =SUM('SCHEDULE OF VALUE WORKSHEET'!E59) -> 204087.33 | E63: =SUM('Draw #8'!E63:F63) -> 0 | F63: 0 | G63: =SUM('Draw #8'!G63)+F63 -> 204087.33 | H63: =SUM(G63-J63) -> 204087.33 | I63: 0 | J63: =SUM(I63+'Draw #8'!J63) -> 0 | K63: =IF(J63=0,"",J63/G63)
A64: ='SCHEDULE OF VALUE WORKSHEET'!A60 -> 54 | B64: ='SCHEDULE OF VALUE WORKSHEET'!B60 -> WINDOWS | D64: =SUM('SCHEDULE OF VALUE WORKSHEET'!E60) -> 106274.25 | E64: =SUM('Draw #8'!E64:F64) -> 0 | F64: 0 | G64: =SUM('Draw #8'!G64)+F64 -> 106274.25 | H64: =SUM(G64-J64) -> 106274.25 | I64: 0 | J64: =SUM(I64+'Draw #8'!J64) -> 0 | K64: =IF(J64=0,"",J64/G64)
... A90: ='SCHEDULE OF VALUE WORKSHEET'!A86 -> 80 | B90: ='SCHEDULE OF VALUE WORKSHEET'!B86 -> FINANCING COSTS | D90: =SUM('SCHEDULE OF VALUE WORKSHEET'!E86) -> 0 | E90: =SUM('Draw #8'!E90:F90) -> 0 | F90: 0 | G90: =SUM('Draw #8'!G90)+F90 -> 0 | H90: =SUM(G90-J90) -> 0 | I90: 0 | J90: =SUM(I90+'Draw #8'!J90) -> 0 | K90: =IF(J90=0,"",J90/G90)
A91: ='SCHEDULE OF VALUE WORKSHEET'!#REF! -> #REF! | B91: ='SCHEDULE OF VALUE WORKSHEET'!#REF! -> #REF! | D91: =SUM('SCHEDULE OF VALUE WORKSHEET'!#REF!) -> #REF! | E91: =SUM('Draw #8'!E91:F91) -> 0 | F91: 0 | G91: =SUM('Draw #8'!G91)+F91 -> #REF! | H91: =SUM(G91-J91) -> #REF! | I91: 0 | J91: =SUM(I91+'Draw #8'!J91) -> 0 | K91: =IF(J91=0,"",J91/G91)
A92: ='SCHEDULE OF VALUE WORKSHEET'!#REF! -> #REF! | B92: ='SCHEDULE OF VALUE WORKSHEET'!#REF! -> #REF! | D92: =SUM('SCHEDULE OF VALUE WORKSHEET'!#REF!) -> #REF! | E92: =SUM('Draw #8'!E92:F92) -> 0 | F92: 0 | G92: =SUM('Draw #8'!G92)+F92 -> #REF! | H92: =SUM(G92-J92) -> #REF! | I92: 0 | J92: =SUM(I92+'Draw #8'!J92) -> 0 | K92: =IF(J92=0,"",J92/G92)
A93: ='SCHEDULE OF VALUE WORKSHEET'!#REF! -> #REF! | B93: ='SCHEDULE OF VALUE WORKSHEET'!#REF! -> #REF! | D93: =SUM('SCHEDULE OF VALUE WORKSHEET'!#REF!) -> #REF! | E93: =SUM('Draw #8'!E93:F93) -> 0 | F93: 0 | G93: =SUM('Draw #8'!G93)+F93 -> #REF! | H93: =SUM(G93-J93) -> #REF! | I93: 0 | J93: =SUM(I93+'Draw #8'!J93) -> 0 | K93: =IF(J93=0,"",J93/G93)
A94: ='SCHEDULE OF VALUE WORKSHEET'!#REF! -> #REF! | B94: ='SCHEDULE OF VALUE WORKSHEET'!#REF! -> #REF! | D94: =SUM('SCHEDULE OF VALUE WORKSHEET'!#REF!) -> #REF! | E94: =SUM('Draw #8'!E94:F94) -> 0 | F94: 0 | G94: =SUM('Draw #8'!G94)+F94 -> #REF! | H94: =SUM(G94-J94) -> #REF! | I94: 0 | J94: =SUM(I94+'Draw #8'!J94) -> 0 | K94: =IF(J94=0,"",J94/G94)
